Workbook

Sheet Head
A1: NIK AMG | E1: NIK DAM
A2: 119000001 | B2: Herman Suwanto | C2: Manufacturing Head | E2: 128000005 | F2: Sartono
A3: 119000004 | B3: Angela Stephanie | C3: QC and R&D Deputy Manager | E3: 128000006 | F3: Agnes Vivi Cahyani
A4: 119000010 | B4: Nathan Wilman | C4: Accounting Chief SPV 2 | E4: 128000007 | F4: Stevanus Cahya Pratama
A5: 119000138 | B5: Agnes Vivi Cahyani | C5: HRD & GA Deputy Manager | E5: 128000008 | F5: Natalia Gunawan
A6: 119000223 | B6: Margaret Emmanuel K | C6: HRD & GA Deputy Manager | E6: 128000009 | F6: Angela stephanie
A7: 119000162 | B7: Stevanus Cahya Pratama | C7: Manager ACC | E7: 128000045 | F7: NATHANIA HARTONO
A8: 119000029 | B8: Sartono | C8: Logistic Deputy Manager | E8: 128000046 | F8: NATHAN WILMAN
A9: 119000078 | B9: Nathania Hartono | C9: Supervisor Purchasing | E9: 128000047 | F9: Joan Imanuela
A10: 119000082 | B10: Joan Imanuela | C10: Supervisor Material Plan & Raw Material | E10: 128000050 | F10: Herman Suwanto
E11: 128000085 | F11: Margaret Emmanuel K

Sheet CONFIG_MODUL
A1: S | B1: LINK_MODUL
A2: GATE_PABRIK | B2: https://script.google.com/macros/s/AKfycbyjQ36Nlastyw1xBgzvojgX6QH2oPxB6462YKg0sELBb3gb08dYQuKHz5X_RLFntfoV9g/exec
A3: AREA_KERJA | B3: https://script.google.com/macros/s/AKfycbyu6uW7XgdZPtJysgtf3x0i3E7cxR5Hrb_dZNKYns0QJ6Lef7xzbC0mT3uP_rREHz5ypA/exec
A4: REPORT | B4: https://script.google.com/macros/s/AKfycbycdcUt4y9RdoQIOTnIzWs6AxyZe5JayFhbk6f9abnv5kr3VAWapXicdVvRGn3o53BS/exec
A5: HOME_PORTAL | B5: https://script.google.com/macros/s/AKfycbzVN4Z58pluVPnUG1jBOBc4hLggJjDAlrSekiW9DtkHqvk8rEsSKuhvhWHTbsHbaP8m/exec

Sheet JADWAL_SHIFT
A1: NIK | B1: NAMA | C1: DEPT | D1: SHIFT | E1: TANGGAL_MULAI | F1: TANGGAL_SELESAI

Sheet KARYAWAN
A1: NIK | B1: NAMA | C1: TYPE KAYARAWAN | D1: DEPT | E1: JABATAN | F1: USER LEVEL | G1: PASSWORD
A2: 128000001 | B2: Iman Nurchaedi S. | C2: STAFF | D2: PROD | E2: Plant Manager | F2: ADMINISTRATOR | G2: ADM0912
A3: 128000003 | B3: Andre Santosa | C3: STAFF | D3: ENG | E3: Engineering Deputy Manager | F3: ADMINISTRATOR | G3: ADM0912
A4: 128000010 | B4: Dendy Saputra | C4: STAFF | D4: PROD | E4: Line Leader | F4: PENGAWAS | G4: PGW0912
A5: 128000012 | B5: Evita | C5: STAFF | D5: PROD | E5: Production Chief SPV 1 | F5: ADMINISTRATOR | G5: ADM0912
A6: 128000013 | B6: Aminulloh | C6: STAFF | D6: LOG | E6: Staff Warehouse Sparepart | F6: PENGAWAS | G6: PGW0912
A7: 128000017 | B7: Sandi Iswanto | C7: STAFF | D7: QRD | E7: Staff Quality Control Production | F7: PENGAWAS | G7: PGW0912
A8: 128000019 | B8: Yeni Ferianto | C8: STAFF | D8: QRD | E8: Staff Quality Control Production | F8: PENGAWAS | G8: PGW0912
A9: 128000020 | B9: Adeliana Dewi Putri Salihah | C9: STAFF | D9: HRGA | E9: Sr. Staff Talent Acquisition | F9: PENGAWAS | G9: PGW0912
A10: 128000022 | B10: Hendra Setiawan | C10: STAFF | D10: PROD | E10: Production Engineer | F10: PENGAWAS | G10: PGW0912
A11: 128000023 | B11: Iman Muaimin | C11: STAFF | D11: LOG | E11: Sr. Staff Warehouse Raw Material | F11: PENGAWAS | G11: PGW0912
A12: 128000024 | B12: Taufik Faturochman | C12: STAFF | D12: LOG | E12: Warehouse Supervisor | F12: ADMINISTRATOR | G12: ADM0912
A13: 128000027 | B13: Gembong Hagung Harsanto | C13: STAFF | D13: ENG | E13: Engineering Chief Spv 1 | F13: ADMINISTRATOR | G13: ADM0912
... A70: 128000123 | B70: Ivan Jovian | C70: STAFF | D70: ENG | E70: Staff ITE | F70: PENGAWAS | G70: PGW0912
A71: 328000001 | B71: RIO GUSTIAWAN | C71: NON STAFF | D71: ENG | E71: ELECTRICAL MAINTENANCE | F71: KARYAWAN
A72: 328000005 | B72: IRGI FAUZI | C72: NON STAFF | D72: ENG | E72: TECHNICIAN | F72: KARYAWAN
A73: 328000006 | B73: RIZKI | C73: NON STAFF | D73: ENG | E73: TECHNICIAN | F73: KARYAWAN
A74: 328000009 | B74: REZZA FEBRIANA | C74: NON STAFF | D74: ENG | E74: TECHNICIAN | F74: KARYAWAN
A75: 328000010 | B75: DIAZ GHERY JUNIARSYAH RAHMAN | C75: NON STAFF | D75: ENG | E75: TECHNICIAN | F75: KARYAWAN
A76: 328000011 | B76: DENI KUSNADI | C76: NON STAFF | D76: LOG | E76: ADMIN WSP | F76: KARYAWAN
A77: 328000022 | B77: AZHAR AIZAD ALFARIDZI | C77: NON STAFF | D77: PROD | E77: OPERATOR | F77: KARYAWAN
A78: 328000023 | B78: KEPIN NUGRAHA | C78: NON STAFF | D78: PROD | E78: OPERATOR | F78: KARYAWAN
A79: 328000026 | B79: DEDE WAHYUDIN | C79: NON STAFF | D79: PROD | E79: OPERATOR | F79: KARYAWAN
A80: 328000027 | B80: GIGIN GINANJAR | C80: NON STAFF | D80: PROD | E80: OPERATOR | F80: KARYAWAN
A81: 328000028 | B81: TISNA GINANJAR | C81: NON STAFF | D81: PROD | E81: OPERATOR | F81: KARYAWAN
A82: 328000030 | B82: DAVA PUTRA YUDIANSYAH | C82: NON STAFF | D82: PROD | E82: OPERATOR | F82: KARYAWAN
... A520: 328000713 | B520: IRWAN CHRISTIANTO HUTAGALUNG | C520: NON STAFF | D520: PROD | E520: OPERATOR PRODUKSI | F520: KARYAWAN
A521: 428000004 | B521: ADI MUZAKI | C521: Mitra Kerja | D521: HRGA | E521: GA Vendor | F521: SECURITY | G521: SEC0912
A522: 428000006 | B522: BAGAS JUAN PRATAMA | C522: Mitra Kerja | D522: HRGA | E522: GA Vendor | F522: SECURITY | G522: SEC0912
A523: 428000011 | B523: DINO DRAJAT | C523: Mitra Kerja | D523: HRGA | E523: GA Vendor | F523: SECURITY | G523: SEC0912
A524: 428000012 | B524: RIDKI MAULANA | C524: Mitra Kerja | D524: HRGA | E524: GA Vendor | F524: SECURITY | G524: SEC0912
A525: 428000014 | B525: ADITYA SAPUTRA | C525: Mitra Kerja | D525: HRGA | E525: GA Vendor | F525: SECURITY | G525: SEC0912
A526: 428000015 | B526: MOCHAMMAD AJAR NURJI | C526: Mitra Kerja | D526: HRGA | E526: GA Vendor | F526: SECURITY | G526: SEC0912
A527: 428000020 | B527: MUSLIM | C527: Mitra Kerja | D527: HRGA | E527: GA Vendor | F527: SECURITY | G527: SEC0912
A528: 428000021 | B528: CARI IRAWAN | C528: Mitra Kerja | D528: HRGA | E528: GA Vendor | F528: SECURITY | G528: SEC0912
A529: 428000024 | B529: ADI MAULANA | C529: Mitra Kerja | D529: HRGA | E529: GA Vendor | F529: SECURITY | G529: SEC0912
A530: 428000030 | B530: ERDI HERDIANSYAH | C530: Mitra Kerja | D530: HRGA | E530: GA Vendor | F530: SECURITY | G530: SEC0912
A531: 428000031 | B531: SARIP HIDAYAT | C531: Mitra Kerja | D531: HRGA | E531: GA Vendor | F531: SECURITY | G531: SEC0912
A532: 428000032 | B532: HERI HOERUDIN | C532: Mitra Kerja | D532: HRGA | E532: GA Vendor | F532: SECURITY | G532: SEC0912
... A578: 428000095 | B578: Muhamad Lutfi Fathir | C578: Mitra Kerja | D578: HRGA | E578: GA Vendor | F578: SECURITY | G578: SEC0912
A579: 428000096 | B579: Aohui Zhang | C579: Mitra Kerja | D579: HRGA | E579: HRD Vendor | F579: KARYAWAN
A580: 428000097 | B580: Changwu Yang | C580: Mitra Kerja | D580: HRGA | E580: HRD Vendor | F580: KARYAWAN
A581: 428000098 | B581: Wan Jiang | C581: Mitra Kerja | D581: HRGA | E581: HRD Vendor | F581: KARYAWAN
A582: 428000099 | B582: Zichun Wang | C582: Mitra Kerja | D582: HRGA | E582: HRD Vendor | F582: KARYAWAN
A583: 428000100 | B583: Jun Xu | C583: Mitra Kerja | D583: HRGA | E583: HRD Harian | F583: KARYAWAN
A584: 428000101 | B584: Jiang Mangke | C584: Mitra Kerja | D584: HRGA | E584: HRD Vendor | F584: KARYAWAN
A585: 428000102 | B585: Abdul Aziz | C585: Mitra Kerja | D585: HRGA | E585: GA Vendor | F585: SECURITY | G585: SEC0912
A586: 428000103 | B586: Yuan Kai | C586: Mitra Kerja | D586: HRGA | E586: HRD Vendor | F586: KARYAWAN
A587: 428000104 | B587: BELLA NURLAILLA. AP | C587: Mitra Kerja | D587: HRGA | E587: GA Vendor | F587: SECURITY | G587: SEC0912
A588: 528000015 | B588: Erwin | C588: Mitra Kerja | D588: LOG | E588: WRM Harian | F588: KARYAWAN
A589: 528000016 | B589: Randi Apriyanto | C589: Mitra Kerja | D589: LOG | E589: WRM Harian | F589: KARYAWAN
A590: 528000040 | B590: Agus Suryaman | C590: Mitra Kerja | D590: PROD | E590: Produksi Harian | F590: KARYAWAN
A591: 528000052 | B591: Mustopa | C591: Mitra Kerja | D591: PROD | E591: Produksi Harian | F591: KARYAWAN
A592: 528000055 | B592: Dika Prasetya | C592: Mitra Kerja | D592: LOG | E592: WRM Harian | F592: KARYAWAN
A593: 528000059 | B593: N. Santika Dewi | C593: Mitra Kerja | D593: PROD | E593: Produksi Harian | F593: KARYAWAN
A594: 528000063 | B594: Muhamad Ripki Pebrian | C594: Mitra Kerja | D594: PROD | E594: Produksi Harian | F594: KARYAWAN
A595: 528000069 | B595: Jajang Ardiansyah | C595: Mitra Kerja | D595: PROD | E595: Produksi Harian | F595: KARYAWAN
A596: 528000070 | B596: Teja Ristina Mukti | C596: Mitra Kerja | D596: PROD | E596: Produksi Harian | F596: KARYAWAN
A597: 528000071 | B597: Pingkan Kustria Budi | C597: Mitra Kerja | D597: PROD | E597: Produksi Harian | F597: KARYAWAN
A598: 528000089 | B598: Santi Susanti | C598: Mitra Kerja | D598: PROD | E598: Produksi Harian | F598: KARYAWAN
A599: 528000090 | B599: Suganda | C599: Mitra Kerja | D599: PROD | E599: Produksi Harian | F599: KARYAWAN
... A874: 628000170 | B874: Didin | C874: Mitra Kerja | D874: LOG | E874: WFG Borongan | F874: KARYAWAN
A875: 928000001 | B875: YOGA | C875: VENDOR | D875: NUMS | E875: VENDOR ADMIN | F875: PENGAWAS | G875: PGW0912

Sheet Sheet4
D1: =IMAGE("https://barcode.tec-it.com/barcode.ashx?data=" & A7 & "&code=Code128")
A6: MK00160 | H6: =IMAGE("https://barcode.tec-it.com/barcode.ashx?data=" & A6 & "&code=Code128")
A7: MK00171 | D7: =IMAGE("https://barcode.tec-it.com/barcode.ashx?data=" & A7 & "&code=Code128")
A8: MK0090 | B8: =IMAGE("https://barcode.tec-it.com/barcode.ashx?data=" & A8 & "&code=Code128")

Sheet BINDING_KARTU_MK
A1: NO_KARTU_MK | B1: NIK | C1: NAMA | D1: DEPT | E1: JABATAN | F1: WAKTU_BIND | G1: STATUS | H1: WAKTU_RELEASE
A2: MK0090 | B2: 528000069 | C2: Jajang Ardiansyah | D2: PROD | E2: Produksi Harian | F2: 46164.853 | G2: FREE | H2: 46164.855
A3: MK00160 | B3: 628000039 | C3: Nani Maryani | D3: PROD | E3: Produksi Borongan | F3: 46166.99 | G3: FREE | H3: 46186.958
A4: MK00112 | B4: 528000016 | C4: Randi Apriyanto | D4: LOG | E4: WRM Harian | F4: 46171.009 | G4: FREE | H4: 46171.012
A5: MK00112 | B5: 528000059 | C5: N. Santika Dewi | D5: PROD | E5: Produksi Harian | F5: 46171.023 | G5: FREE | H5: 46171.024
A6: MK00126 | B6: 528000052 | C6: Mustopa | D6: PROD | E6: Produksi Harian | F6: 46171.026 | G6: FREE | H6: 46171.027
A7: MK00112 | B7: 528000059 | C7: N. Santika Dewi | D7: PROD | E7: Produksi Harian | F7: 46171.042 | G7: FREE | H7: 46087.58
A8: CK0093 | B8: 528000055 | C8: Dika Prasetya | D8: LOG | E8: WRM Harian | F8: 46171.25 | G8: FREE | H8: 46087.581
A9: MK00156 | B9: 528000201 | C9: Zahwa Amelia Choerunissa | D9: PROD | E9: Produksi Harian | F9: 46171.315 | G9: FREE | H9: 46028.242
A10: MK00184 | B10: 528000099 | C10: Siti Nurawaliah | D10: PROD | E10: Produksi Harian | F10: 46171.317 | G10: FREE | H10: 46059.235
A11: MK00116 | B11: 528000244 | C11: Rodian Rifai | D11: PROD | E11: Produksi Harian | F11: 46171.32 | G11: FREE | H11: 46171.673
A12: MK00181 | B12: 528000286 | C12: Imelda Amelia | D12: PROD | E12: Produksi Harian | F12: 46171.325 | G12: FREE | H12: 46172.012
A13: MK00118 | B13: 528000228 | C13: Banyu Resmi Putri | D13: PROD | E13: Produksi Harian | F13: 46171.329 | G13: FREE | H13: 46059.335
... A66: MK00150 | B66: 528000305 | C66: Puji Puspita | D66: PROD | E66: Produksi Harian | F66: 46028.239 | G66: FREE | H66: 46028.589
A67: 7200181 | B67: 528000251 | C67: Salya Nugraha | D67: PROD | E67: Produksi Harian | F67: 46028.24 | G67: FREE | H67: 46198.831
A68: MK00145 | B68: 528000302 | C68: Henkey gumilar | D68: PROD | E68: Produksi Harian | F68: 46028.243 | G68: FREE | H68: 46028.591
A69: MK00156 | B69: 528000270 | C69: Febri Najmudin | D69: LOG | E69: WRM Harian | F69: 46028.243 | G69: FREE | H69: 46028.588
A70: MK00109 | B70: 528000298 | C70: Desta Cahaya Pratama | D70: PROD | E70: Produksi Harian | F70: 46028.244 | G70: FREE | H70: 46028.588
A71: MK00154 | B71: 528000265 | C71: Muhammad Haerul Rozikin | D71: LOG | E71: WRM Harian | F71: 46028.321 | G71: FREE | H71: 46028.67
A72: MK00138 | B72: 528000296 | C72: Nurdin | D72: PROD | E72: Produksi Harian | F72: 46028.335 | G72: FREE | H72: 46087.575
A73: MK00126 | B73: 528000069 | C73: Jajang Ardiansyah | D73: PROD | E73: Produksi Harian | F73: 46028.335 | G73: FREE | H73: 46028.815
A74: MK00151 | B74: 528000279 | C74: Mahdalena Dalfa Riani | D74: PROD | E74: Produksi Harian | F74: 46028.574 | G74: FREE | H74: 46118.249
A75: MK00116 | B75: 528000297 | C75: Muhamad Budiana | D75: PROD | E75: Produksi Harian | F75: 46028.576 | G75: FREE | H75: 46028.921
A76: MK00148 | B76: 528000300 | C76: Lia pitaloka | D76: PROD | E76: Produksi Harian | F76: 46028.577 | G76: FREE | H76: 46028.922
A77: MK00113 | B77: 528000210 | C77: Muhamad Aldi Agustiana | D77: PROD | E77: Produksi Harian | F77: 46028.578 | G77: FREE | H77: 46028.922
A78: MK00093 | B78: 528000292 | C78: Aditia Nugraha | D78: PROD | E78: Produksi Harian | F78: 46028.579 | G78: FREE | H78: 46028.921
A79: MK00154 | B79: 528000052 | C79: Mustopa | D79: PROD | E79: Produksi Harian | F79: 46028.883 | G79: FREE | H79: 46059.253
... A144: MK00138 | B144: 528000090 | C144: Suganda | D144: PROD | E144: Produksi Harian | F144: 46087.581 | G144: FREE | H144: 46087.921
A145: 128000267 | B145: 528000267 | C145: Bagas Patulloh | D145: LOG | E145: WRM Harian | F145: 46087.653 | G145: FREE | H145: 46148.671
A146: MKOO58 | B146: 528000052 | C146: Mustopa | D146: PROD | E146: Produksi Harian | F146: 46087.823 | G146: FREE | H146: 46198.831
A147: MK00192 | B147: 528000195 | C147: Rahma Sariwati | D147: PROD | E147: Produksi Harian | F147: 46087.895 | G147: FREE | H147: 46148.254
A148: MK00221 | B148: 528000266 | C148: M. Syirajatieq | D148: LOG | E148: WFG Harian | F148: 46087.899 | G148: FREE | H148: 46118.252
A149: MK00109 | B149: 528000262 | C149: Ndari Dwiwanti | D149: PROD | E149: Produksi Harian | F149: 46087.901 | G149: FREE | H149: 46118.251
A150: MK00249 | B150: 528000358 | C150: Lulu Agustin | D150: PROD | E150: Produksi Harian | F150: 46087.903 | G150: FREE | H150: 46118.031
A151: MK00213 | B151: 528000261 | C151: Ergi Ergianto | D151: HRGA | E151: GA Harian | F151: 46087.907 | G151: FREE | H151: 46118.252
A152: MK00150 | B152: 528000283 | C152: Purwanda Sugiri | D152: LOG | E152: WRM Harian | F152: 46087.913 | G152: FREE | H152: 46118.254
A153: MK00082 | B153: 528000291 | C153: Andrian | D153: PROD | E153: Produksi Harian | F153: 46087.913 | G153: FREE | H153: 46118.254
A154: MK00155 | B154: 528000301 | C154: Muhammad Mukti Ridwan | D154: PROD | E154: Produksi Harian | F154: 46087.914 | G154: FREE | H154: 46118.256
A155: MK00249 | B155: 528000358 | C155: Lulu Agustin | D155: PROD | E155: Produksi Harian | F155: 46118.031 | G155: FREE | H155: 46118.586
A156: MK00136 | B156: 528000306 | C156: Windy Olivia | D156: PROD | E156: Produksi Harian | F156: 46118.238 | G156: FREE | H156: 46118.589
A157: MK00184 | B157: 528000282 | C157: Defa Desfiana | D157: PROD | E157: Produksi Harian | F157: 46118.24 | G157: FREE | H157: 46118.586
... A188: MK00249 | B188: 528000279 | C188: Mahdalena Dalfa Riani | D188: PROD | E188: Produksi Harian | F188: 46148.247 | G188: FREE | H188: 46148.588
A189: 1000210 | B189: 528000069 | C189: Jajang Ardiansyah | D189: PROD | E189: Produksi Harian | F189: 46148.261 | G189: FREE | H189: 46148.299
A190: MK00209 | B190: 528000282 | C190: Defa Desfiana | D190: PROD | E190: Produksi Harian | F190: 46148.314 | G190: FREE | H190: 46148.667
A191: MK00212 | B191: 528000144 | C191: Jodi Hanafi | D191: LOG | E191: WRM Harian | F191: 46148.315 | G191: FREE | H191: 46179.015
A192: MK00210 | B192: 528000069 | C192: Jajang Ardiansyah | D192: PROD | E192: Produksi Harian | F192: 46148.317 | G192: FREE | H192: 46148.318
A193: MK00192 | B193: 528000287 | C193: Muhamad Angga Ramdani | D193: PROD | E193: Produksi Harian | F193: 46148.323 | G193: FREE | H193: 46148.67
A194: MK00155 | B194: 528000265 | C194: Muhammad Haerul Rozikin | D194: LOG | E194: WRM Harian | F194: 46148.323 | G194: FREE | H194: 46148.669
A195: MK00109 | B195: 528000349 | C195: Anas Abdul Fatah | D195: LOG | E195: WFG Harian | F195: 46148.326 | G195: FREE | H195: 46148.675
A196: MK00112 | B196: 528000351 | C196: Mulyana | D196: PROD | E196: Produksi Harian | F196: 46148.34 | G196: FREE | H196: 46148.667
A197: MK00046 | B197: 528000232 | C197: Agung Aji Suhada | D197: LOG | E197: WRM Harian | F197: 46148.37 | G197: FREE | H197: 46148.71
A198: MA00145 | B198: 528000348 | C198: Saepuloh Ardiansah | D198: LOG | E198: WRM Harian | F198: 46148.37 | G198: FREE | H198: 46148.711
A199: MK00138 | B199: 528000203 | C199: Yudha Ramdhan Putra | D199: ENG | E199: Engineering Harian | F199: 46148.376 | G199: FREE | H199: 46179.371
A200: MK00141 | B200: 528000244 | C200: Rodian Rifai | D200: PROD | E200: Produksi Harian | F200: 46148.563 | G200: FREE | H200: 46148.93
A201: MK00181 | B201: 528000286 | C201: Imelda Amelia | D201: PROD | E201: Produksi Harian | F201: 46148.565 | G201: FREE | H201: 46148.922
... A1199: MK00192 | B1199: 528000288 | C1199: Dede gunawan | D1199: PROD | E1199: Produksi Harian | F1199: 46272.576 | G1199: FREE | H1199: 46302.579
A1200: 207 | B1200: 528000292 | C1200: Aditia Nugraha | D1200: PROD | E1200: Produksi Harian | F1200: 46272.578 | G1200: FREE | H1200: 46224.977
A1201: MK00121 | B1201: 528000279 | C1201: Mahdalena Dalfa Riani | D1201: PROD | E1201: Produksi Harian | F1201: 46272.579 | G1201: FREE | H1201: 46272.921
A1202: MK00125 | B1202: 528000314 | C1202: Rusmana | D1202: PROD | E1202: Produksi Harian | F1202: 46272.637 | G1202: FREE | H1202: 46302.002
A1203: MK00213 | B1203: 528000015 | C1203: Erwin | D1203: LOG | E1203: WRM Harian | F1203: 46272.651 | G1203: FREE | H1203: 46302.002
A1204: MK00221 | B1204: 528000144 | C1204: Jodi Hanafi | D1204: LOG | E1204: WRM Harian | F1204: 46272.666 | G1204: FREE | H1204: 46302.008
A1205: MK00210 | B1205: 528000323 | C1205: Dian Hamidah | D1205: PROD | E1205: Produksi Harian | F1205: 46272.901 | G1205: FREE | H1205: 46302.256
A1206: MK00145 | B1206: 528000286 | C1206: Imelda Amelia | D1206: PROD | E1206: Produksi Harian | F1206: 46272.903 | G1206: FREE | H1206: 46302.255
A1207: MK00154 | B1207: 528000201 | C1207: Zahwa Amelia Choerunissa | D1207: PROD | E1207: Produksi Harian | F1207: 46272.905 | G1207: FREE | H1207: 46302.254
A1208: MK0090 | B1208: 528000099 | C1208: Siti Nurawaliah | D1208: PROD | E1208: Produksi Harian | F1208: 46272.905 | G1208: FREE | H1208: 46302.254
A1209: MK00138 | B1209: 528000241 | C1209: Balia Nurafif Bilah | D1209: PROD | E1209: Produksi Harian | F1209: 46272.91 | G1209: FREE | H1209: 46302.254
A1210: MK00250 | B1210: 528000244 | C1210: Rodian Rifai | D1210: PROD | E1210: Produksi Harian | F1210: 46272.911 | G1210: FREE | H1210: 46302.275
A1211: MK00116 | B1211: 528000274 | C1211: Zepri | D1211: PROD | E1211: Produksi Harian | F1211: 46272.914 | G1211: FREE | H1211: 46302.253
A1212: MK00185 | B1212: 528000289 | C1212: Adit Supriyadi | D1212: PROD | E1212: Produksi Harian | F1212: 46272.914 | G1212: FREE | H1212: 46302.254
... A1538: MK00124 | B1538: 528000212 | C1538: Rizal Fauzi | D1538: PROD | E1538: Produksi Harian | F1538: 46220.667 | G1538: FREE | H1538: 46221.016
A1539: 46 | B1539: 528000335 | C1539: Rizal Saepuloh | D1539: LOG | E1539: WRM Harian | F1539: 46220.731 | G1539: FREE
A1540: MK00217 | B1540: 528000282 | C1540: Defa Desfiana | D1540: PROD | E1540: Produksi Harian | F1540: 46220.736 | G1540: FREE | H1540: 46220.959
A1541: MK00181 | B1541: 528000265 | C1541: Muhammad Haerul Rozikin | D1541: LOG | E1541: WRM Harian | F1541: 46220.74 | G1541: FREE | H1541: 46220.963
A1542: MK00184 | B1542: 528000351 | C1542: Mulyana | D1542: PROD | E1542: Produksi Harian | F1542: 46220.743 | G1542: FREE | H1542: 46220.972
A1543: MK00138 | B1543: 528000310 | C1543: Fachrul Rozzi Suryana | D1543: LOG | E1543: WRM Harian | F1543: 46220.744 | G1543: FREE | H1543: 46220.96
A1544: MK00154 | B1544: 528000069 | C1544: Jajang Ardiansyah | D1544: PROD | E1544: Produksi Harian | F1544: 46220.746 | G1544: FREE | H1544: 46221.257
A1545: MK000221 | B1545: 528000144 | C1545: Jodi Hanafi | D1545: LOG | E1545: WRM Harian | F1545: 46220.753 | G1545: FREE | H1545: 46220.754
A1546: MK00221 | B1546: 528000144 | C1546: Jodi Hanafi | D1546: LOG | E1546: WRM Harian | F1546: 46220.754 | G1546: FREE | H1546: 46221.037
A1547: MK00205 | B1547: 528000348 | C1547: Saepuloh Ardiansah | D1547: LOG | E1547: WRM Harian | F1547: 46220.784 | G1547: FREE | H1547: 46221.007
A1548: MK00210 | B1548: 528000232 | C1548: Agung Aji Suhada | D1548: LOG | E1548: WRM Harian | F1548: 46220.788 | G1548: FREE | H1548: 46221.001
A1549: MK00148 | B1549: 528000040 | C1549: Agus Suryaman | D1549: PROD | E1549: Produksi Harian | F1549: 46220.793 | G1549: FREE | H1549: 46221.001
A1550: MK00228 | B1550: 528000132 | C1550: Giopani | D1550: LOG | E1550: WRM Harian | F1550: 46220.818 | G1550: FREE | H1550: 46221.001
A1551: MK00218 | B1551: 528000337 | C1551: Ahmad Zaldi Firdaus | D1551: PROD | E1551: Produksi Harian | F1551: 46220.956 | G1551: FREE | H1551: 46221.341
... A1583: MK00249 | B1583: 528000090 | C1583: Suganda | D1583: PROD | E1583: Produksi Harian | F1583: 46221.665 | G1583: FREE | H1583: 46223.667
A1584: 52800088 | B1584: 528000244 | C1584: Rodian Rifai | D1584: PROD | E1584: Produksi Harian | F1584: 46221.665 | G1584: FREE | H1584: 46223.661
A1585: MK00113 | B1585: 528000274 | C1585: Zepri | D1585: PROD | E1585: Produksi Harian | F1585: 46221.665 | G1585: FREE | H1585: 46222.003
A1586: MK00220 | B1586: 528000290 | C1586: Eval Pranata | D1586: PROD | E1586: Produksi Harian | F1586: 46221.666 | G1586: FREE | H1586: 46222.003
A1587: MK00088 | B1587: 528000015 | C1587: Erwin | D1587: LOG | E1587: WRM Harian | F1587: 46221.671 | G1587: FREE | H1587: 46221.672
A1588: MK00095 | B1588: 528000273 | C1588: Asep Mulyana | D1588: PROD | E1588: Produksi Harian | F1588: 46221.761 | G1588: FREE | H1588: 46222.004
A1589: MK00202 | B1589: 528000337 | C1589: Ahmad Zaldi Firdaus | D1589: PROD | E1589: Produksi Harian | F1589: 46221.956 | G1589: FREE | H1589: 46222.339
A1590: MK00208 | B1590: 528000336 | C1590: Ali Nurhanafi | D1590: PROD | E1590: Produksi Harian | F1590: 46221.966 | G1590: FREE | H1590: 46222.338
A1591: MK00112 | B1591: 528000262 | C1591: Ndari Dwiwanti | D1591: PROD | E1591: Produksi Harian | F1591: 46221.983 | G1591: FREE | H1591: 46222.336
A1592: MK00138 | B1592: 528000266 | C1592: M. Syirajatieq | D1592: LOG | E1592: WFG Harian | F1592: 46221.986 | G1592: FREE | H1592: 46222.354
A1593: MK00134 | B1593: 528000195 | C1593: Rahma Sariwati | D1593: PROD | E1593: Produksi Harian | F1593: 46221.986 | G1593: FREE | H1593: 46222.337
A1594: MK00204 | B1594: 528000358 | C1594: Lulu Agustin | D1594: PROD | E1594: Produksi Harian | F1594: 46221.987 | G1594: FREE | H1594: 46222.335
A1595: MK00185 | B1595: 528000291 | C1595: Andrian | D1595: PROD | E1595: Produksi Harian | F1595: 46221.992 | G1595: FREE | H1595: 46222.336
A1596: MK00090 | B1596: 528000283 | C1596: Purwanda Sugiri | D1596: LOG | E1596: WRM Harian | F1596: 46221.993 | G1596: FREE | H1596: 46222.99
... A1618: MK00213 | B1618: 528000265 | C1618: Muhammad Haerul Rozikin | D1618: LOG | E1618: WRM Harian | F1618: 46222.665 | G1618: FREE | H1618: 46223.004
A1619: 338 | B1619: 528000273 | C1619: Asep Mulyana | D1619: PROD | E1619: Produksi Harian | F1619: 46222.665 | G1619: FREE | H1619: 46223.002
A1620: MK00212 | B1620: 528000359 | C1620: M. Iqbal Maulana. S | D1620: LOG | E1620: WRM Harian | F1620: 46222.666 | G1620: FREE | H1620: 46223.004
...

Sheet REGISTRASI SAAT MASUK PABRIK
A1: NO KARTU MK | B1: NIK | C1: NAMA | D1: TANGGAL | E1: JAM MASUK | F1: SHIFT | G1: NO LOKER
A2: MK0090 | B2: 528000069 | C2: Jajang Ardiansyah | D2: 46164.417 | E2: 0.43628472 | F2: Shift 1
A3: MK00160 | B3: 628000039 | C3: Nani Maryani | D3: 46166.417 | E3: 0.57347222 | F3: Shift 2
A4: MK00112 | B4: 528000016 | C4: Randi Apriyanto | D4: 46170.417 | E4: 0.59222222 | F4: Shift 2
A5: MK00112 | B5: 528000059 | C5: N. Santika Dewi | D5: 46170.417 | E5: 0.6062963 | F5: Shift 2
A6: MK00126 | B6: 528000052 | C6: Mustopa | D6: 46170.417 | E6: 0.60981481 | F6: Shift 2
A7: MK00112 | B7: 528000059 | C7: N. Santika Dewi | D7: 46170.417 | E7: 0.62488426 | F7: Shift 2
A8: CK0093 | B8: 528000055 | C8: Dika Prasetya | D8: 46170.417 | E8: 0.83355324 | F8: Shift 2
A9: MK00156 | B9: 528000201 | C9: Zahwa Amelia Choerunissa | D9: 46170.417 | E9: 0.89846065 | F9: Shift 3
A10: MK00184 | B10: 528000099 | C10: Siti Nurawaliah | D10: 46170.417 | E10: 0.90024306 | F10: Shift 3
A11: MK00116 | B11: 528000244 | C11: Rodian Rifai | D11: 46170.417 | E11: 0.90334491 | F11: Shift 3 | G11: D-26
A12: MK00181 | B12: 528000286 | C12: Imelda Amelia | D12: 46170.417 | E12: 0.90835648 | F12: Shift 3
A13: MK00118 | B13: 528000228 | C13: Banyu Resmi Putri | D13: 46170.417 | E13: 0.91210648 | F13: Shift 3
A14: MK00082 | B14: 528000241 | C14: Balia Nurafif Bilah | D14: 46170.417 | E14: 0.91518519 | F14: Shift 3
A15: MK00155 | B15: 528000212 | C15: Rizal Fauzi | D15: 46170.417 | E15: 0.91671296 | F15: Shift 3
A16: MK00085 | B16: 528000290 | C16: Eval Pranata | D16: 46170.417 | E16: 0.91706019 | F16: Shift 3
A17: MK00136 | B17: 528000274 | C17: Zepri | D17: 46170.417 | E17: 0.91832176 | F17: Shift 3
A18: MK00093 | B18: 528000090 | C18: Suganda | D18: 46170.417 | E18: 0.91858796 | F18: Shift 3
A19: MK00138 | B19: 528000273 | C19: Asep Mulyana | D19: 46170.417 | E19: 0.92143519 | F19: Shift 3
A20: MK00141 | B20: 528000098 | C20: Edi Junaedi | D20: 46171.417 | E20: 0.22613426 | F20: Shift 1 | G20: 2F
A21: MK00151 | B21: 628000061 | C21: Nayla Fadillah Exwantoro | D21: 46171.417 | E21: 0.23168981 | F21: Shift 1
A22: MK00158 | B22: 528000299 | C22: Siti Nurjanah | D22: 46171.417 | E22: 0.24092593 | F22: Shift 1
A23: MK00145 | B23: 528000302 | C23: Henkey gumilar | D23: 46171.417 | E23: 0.24854167 | F23: Shift 1
A24: MK00150 | B24: 628000091 | C24: Devita Handayani | D24: 46171.417 | E24: 0.24989583 | F24: Shift 1
A25: MK00046 | B25: 528000015 | C25: Erwin | D25: 46171.417 | E25: 0.2530787 | F25: Shift 1
A26: MK00155 | B26: 528000282 | C26: Defa Desfiana | D26: 46171.417 | E26: 0.31886574 | F26: Shift 1 | G26: 23C
A27: MK00085 | B27: 528000265 | C27: Muhammad Haerul Rozikin | D27: 46171.417 | E27: 0.32128472 | F27: Shift 1
A28: MK00136 | B28: 528000351 | C28: Mulyana | D28: 46171.417 | E28: 0.33710648 | F28: Shift 1
A29: MK008I | B29: 528000288 | C29: Dede gunawan | D29: 46171.417 | E29: 0.55028935 | F29: Shift 2
A30: MK00116 | B30: 528000306 | C30: Windy Olivia | D30: 46171.417 | E30: 0.57231481 | F30: Shift 2
A31: MK00155 | B31: 628000064 | C31: Silva Alypia | D31: 46171.417 | E31: 0.57951389 | F31: Shift 2
A32: MK00085 | B32: 528000279 | C32: Mahdalena Dalfa Riani | D32: 46171.417 | E32: 0.58271991 | F32: Shift 2
A33: MK00082 | B33: 528000297 | C33: Muhamad Budiana | D33: 46171.417 | E33: 0.58289352 | F33: Shift 2
A34: 628000061 | B34: 528000089 | C34: Santi Susanti | D34: 46171.417 | E34: 0.59180556 | F34: Shift 2
A35: MK00145 | B35: 528000302 | C35: Henkey gumilar | D35: 46171.417 | E35: 0.59856481 | F35: Shift 2
A36: 528000232 | B36: 528000232 | C36: Agung Aji Suhada | D36: 46171.417 | E36: 0.60163194 | F36: Shift 2
A37: MK528000144 | B37: 528000144 | C37: Jodi Hanafi | D37: 46171.417 | E37: 0.60238426 | F37: Shift 2
A38: MK00093 | B38: 528000273 | C38: Asep Mulyana | D38: 46171.417 | E38: 0.66327546 | F38: Shift 2
A39: MK00158 | B39: 528000244 | C39: Rodian Rifai | D39: 46171.417 | E39: 0.8965625 | F39: Shift 3
A40: MKZ0138 | B40: 528000301 | C40: Muhammad Mukti Ridwan | D40: 46171.417 | E40: 0.89696759 | F40: Shift 3
A41: MK00181 | B41: 528000286 | C41: Imelda Amelia | D41: 46171.417 | E41: 0.90251157 | F41: Shift 3
A42: MK00141 | B42: 528000241 | C42: Balia Nurafif Bilah | D42: 46171.417 | E42: 0.90888889 | F42: Shift 3
A43: MK00145 | B43: 528000274 | C43: Zepri | D43: 46171.417 | E43: 0.91168981 | F43: Shift 3
A44: MK00250 | B44: 528000090 | C44: Suganda | D44: 46171.417 | E44: 0.91299769 | F44: Shift 3
A45: MK00150 | B45: 528000212 | C45: Rizal Fauzi | D45: 46171.417 | E45: 0.91320602 | F45: Shift 3
A46: MK00159 | B46: 528000290 | C46: Eval Pranata | D46: 46171.417 | E46: 0.916875 | F46: Shift 3
A47: MK00136 | B47: 528000052 | C47: Mustopa | D47: 46171.417 | E47: 0.92671296 | F47: Shift 3
A48: 528000296 | B48: 528000296 | C48: Nurdin | D48: 46171.417 | E48: 0.93674769 | F48: Shift 3 | G48: 116
A49: MK00085 | B49: 528000098 | C49: Edi Junaedi | D49: 46172.417 | E49: 0.22502315 | F49: Shift 1
A50: MK00082 | B50: 628000061 | C50: Nayla Fadillah Exwantoro | D50: 46172.417 | E50: 0.23015046 | F50: Shift 1
A51: MK00154 | B51: 528000299 | C51: Siti Nurjanah | D51: 46172.417 | E51: 0.23674769 | F51: Shift 1
A52: MK00055 | B52: 528000302 | C52: Henkey gumilar | D52: 46172.417 | E52: 0.23988426 | F52: Shift 1
A53: MK00126 | B53: 528000251 | C53: Salya Nugraha | D53: 46172.417 | E53: 0.2418287 | F53: Shift 1
A54: MK00151 | B54: 528000270 | C54: Febri Najmudin | D54: 46172.417 | E54: 0.24331019 | F54: Shift 1
A55: MK00145 | B55: 528000354 | C55: Dian Rosdianti | D55: 46172.417 | E55: 0.27275463 | F55: Shift 1
A56: MK00150 | B56: 528000297 | C56: Muhamad Budiana | D56: 46172.417 | E56: 0.57366898 | F56: Shift 2
A57: MK00141 | B57: 528000279 | C57: Mahdalena Dalfa Riani | D57: 46172.417 | E57: 0.57633102 | F57: Shift 2
A58: MK0046 | B58: 628000064 | C58: Silva Alypia | D58: 46172.417 | E58: 0.57788194 | F58: Shift 2
A59: 528000283 | B59: 528000283 | C59: Purwanda Sugiri | D59: 46172.417 | E59: 0.90001157 | F59: Shift 3 | G59: E-12
A60: MK00085 | B60: 528000306 | C60: Windy Olivia | D60: 46172.417 | E60: 0.90064815 | F60: Shift 3
A61: MK00126 | B61: 528000262 | C61: Ndari Dwiwanti | D61: 46172.417 | E61: 0.90082176 | F61: Shift 3
A62: 528000291 | B62: 528000291 | C62: Andrian | D62: 46172.417 | E62: 0.90549769 | F62: Shift 3 | G62: E-14
A63: MK00055 | B63: 528000266 | C63: M. Syirajatieq | D63: 46172.417 | E63: 0.9096875 | F63: Shift 3
A64: MK00151 | B64: 528000283 | C64: Purwanda Sugiri | D64: 46172.417 | E64: 0.91197917 | F64: Shift 3
A65: MK00093 | B65: 528000291 | C65: Andrian | D65: 46172.417 | E65: 0.91351852 | F65: Shift 3
A66: MK00138 | B66: 528000261 | C66: Ergi Ergianto | D66: 46172.417 | E66: 0.91452546 | F66: Shift 3
A67: MK00109 | B67: 528000298 | C67: Desta Cahaya Pratama | D67: 46142.417 | E67: 0.19359954 | F67: Shift 3 | G67: 9-B
A68: MK00250 | B68: 528000098 | C68: Edi Junaedi | D68: 46142.417 | E68: 0.231875 | F68: Shift 1
A69: MK00082 | B69: 628000061 | C69: Nayla Fadillah Exwantoro | D69: 46142.417 | E69: 0.233125 | F69: Shift 1
A70: MK00141 | B70: 528000299 | C70: Siti Nurjanah | D70: 46142.417 | E70: 0.23670139 | F70: Shift 1
A71: MK00150 | B71: 528000305 | C71: Puji Puspita | D71: 46142.417 | E71: 0.23861111 | F71: Shift 1
A72: 7200181 | B72: 528000251 | C72: Salya Nugraha | D72: 46142.417 | E72: 0.24003472 | F72: Shift 1
A73: MK00145 | B73: 528000302 | C73: Henkey gumilar | D73: 46142.417 | E73: 0.24282407 | F73: Shift 1
A74: MK00156 | B74: 528000270 | C74: Febri Najmudin | D74: 46142.417 | E74: 0.24320602 | F74: Shift 1
A75: MK00109 | B75: 528000298 | C75: Desta Cahaya Pratama | D75: 46142.417 | E75: 0.24363426 | F75: Shift 1
A76: MK00154 | B76: 528000265 | C76: Muhammad Haerul Rozikin | D76: 46142.417 | E76: 0.32060185 | F76: Shift 1
A77: MK00138 | B77: 528000296 | C77: Nurdin | D77: 46142.417 | E77: 0.33541667 | F77: Shift 1
A78: MK00126 | B78: 528000069 | C78: Jajang Ardiansyah | D78: 46142.417 | E78: 0.33549769 | F78: Shift 1
A79: MK00151 | B79: 528000279 | C79: Mahdalena Dalfa Riani | D79: 46142.417 | E79: 0.57359954 | F79: Shift 2
A80: MK00116 | B80: 528000297 | C80: Muhamad Budiana | D80: 46142.417 | E80: 0.5759838 | F80: Shift 2
A81: MK00148 | B81: 528000300 | C81: Lia pitaloka | D81: 46142.417 | E81: 0.57743056 | F81: Shift 2
A82: MK00113 | B82: 528000210 | C82: Muhamad Aldi Agustiana | D82: 46142.417 | E82: 0.57784722 | F82: Shift 2
A83: MK00093 | B83: 528000292 | C83: Aditia Nugraha | D83: 46142.417 | E83: 0.57907407 | F83: Shift 2
A84: MK00154 | B84: 528000052 | C84: Mustopa | D84: 46142.417 | E84: 0.88349537 | F84: Shift 3
... A103: MK00088 | B103: 528000069 | C103: Jajang Ardiansyah | D103: 46143.417 | E103: 0.29056713 | F103: Shift 1
A104: MK00145 | B104: 528000282 | C104: Defa Desfiana | D104: 46143.417 | E104: 0.31201389 | F104: Shift 1 | G104: 23C
A105: MK00082 | B105: 528000265 | C105: Muhammad Haerul Rozikin | D105: 46143.417 | E105: 0.32155093 | F105: Shift 1
A106: MK00141 | B106: 528000351 | C106: Mulyana | D106: 46143.417 | E106: 0.32545139 | F106: Shift 1
A107: MK00156 | B107: 528000287 | C107: Muhamad Angga Ramdani | D107: 46143.417 | E107: 0.3291088 | F107: Shift 1
A108: MK00158 | B108: 528000232 | C108: Agung Aji Suhada | D108: 46143.417 | E108: 0.3733912 | F108: Shift 1
A109: MK00154 | B109: 528000203 | C109: Yudha Ramdhan Putra | D109: 46143.417 | E109: 0.37454861 | F109: Shift 1
A110: MK00126 | B110: 528000244 | C110: Rodian Rifai | D110: 46143.417 | E110: 0.55626157 | F110: Shift 2
A111: MK00148 | B111: 528000201 | C111: Zahwa Amelia Choerunissa | D111: 46143.417 | E111: 0.56331019 | F111: Shift 2
A112: MK0155 | B112: 528000212 | C112: Rizal Fauzi | D112: 46143.417 | E112: 0.56353009 | F112: Shift 2
A113: MK00113 | B113: 528000099 | C113: Siti Nurawaliah | D113: 46143.417 | E113: 0.56520833 | F113: Shift 2
A114: MK00207 | B114: 528000286 | C114: Imelda Amelia | D114: 46143.417 | E114: 0.56920139 | F114: Shift 2
A115: MK00208 | B115: 528000241 | C115: Balia Nurafif Bilah | D115: 46143.417 | E115: 0.57673611 | F115: Shift 2
A116: MK00211 | B116: 528000274 | C116: Zepri | D116: 46143.417 | E116: 0.57900463 | F116: Shift 2
... A127: MK00088 | B127: 528000069 | C127: Jajang Ardiansyah | D127: 46144.417 | E127: 0.30548611 | F127: Shift 1
A128: MK00141 | B128: 528000282 | C128: Defa Desfiana | D128: 46144.417 | E128: 0.31065972 | F128: Shift 1 | G128: 23c
...

Sheet STAFF AKTIF
A1: =IFERROR(__xludf.DUMMYFUNCTION("QUERY(IMPORTRANGE(""https://docs.google.com/spreadsheets/d/1FEoklqOOGVEuHVDC9BVeaIu8tA3fqheZAT3eO9syd2Y/edit?gid=380216187#gid=380216187"", ""STAFF DAM AKTIF!A:AN""), ""SELECT Col1,Col2,Col3,Col26,Col27,Col13,Col15,Col18,Col19,Col38,Col20"")"),"#REF!")

Sheet NON STAFF
A1: =IFERROR(__xludf.DUMMYFUNCTION("QUERY(IMPORTRANGE(""https://docs.google.com/spreadsheets/d/1YuKF0APlK-VpXpbB6ITZTO7ALJdeV-34j7idE7TFcDc/edit?gid=478115743#gid=478115743"", ""AKTIF!B8:X""), ""SELECT Col1,Col2, Col4,Col9, Col11"")"),"No.") | B1: =IFERROR(__xludf.DUMMYFUNCTION("""COMPUTED_VALUE"""),"NIK") | C1: =IFERROR(__xludf.DUMMYFUNCTION("""COMPUTED_VALUE"""),"Nama (sesuai KTP)") | D1: =IFERROR(__xludf.DUMMYFUNCTION("""COMPUTED_VALUE"""),"Bagian") | E1: =IFERROR(__xludf.DUMMYFUNCTION("""COMPUTED_VALUE"""),"DEPT")
A2: =IFERROR(__xludf.DUMMYFUNCTION("""COMPUTED_VALUE"""),1.0) | B2: =IFERROR(__xludf.DUMMYFUNCTION("""COMPUTED_VALUE"""),3.28000001E8) | C2: =IFERROR(__xludf.DUMMYFUNCTION("""COMPUTED_VALUE"""),"RIO GUSTIAWAN") | D2: =IFERROR(__xludf.DUMMYFUNCTION("""COMPUTED_VALUE"""),"ELECTRICAL MAINTENANCE") | E2: =IFERROR(__xludf.DUMMYFUNCTION("""COMPUTED_VALUE"""),"ENGINEERING")
A3: =IFERROR(__xludf.DUMMYFUNCTION("""COMPUTED_VALUE"""),2.0) | B3: =IFERROR(__xludf.DUMMYFUNCTION("""COMPUTED_VALUE"""),3.28000006E8) | C3: =IFERROR(__xludf.DUMMYFUNCTION("""COMPUTED_VALUE"""),"RIZKI") | D3: =IFERROR(__xludf.DUMMYFUNCTION("""COMPUTED_VALUE"""),"TECHNICIAN") | E3: =IFERROR(__xludf.DUMMYFUNCTION("""COMPUTED_VALUE"""),"ENGINEERING")
A4: =IFERROR(__xludf.DUMMYFUNCTION("""COMPUTED_VALUE"""),3.0) | B4: =IFERROR(__xludf.DUMMYFUNCTION("""COMPUTED_VALUE"""),3.28000009E8) | C4: =IFERROR(__xludf.DUMMYFUNCTION("""COMPUTED_VALUE"""),"REZZA FEBRIANA") | D4: =IFERROR(__xludf.DUMMYFUNCTION("""COMPUTED_VALUE"""),"TECHNICIAN") | E4: =IFERROR(__xludf.DUMMYFUNCTION("""COMPUTED_VALUE"""),"ENGINEERING")
A5: =IFERROR(__xludf.DUMMYFUNCTION("""COMPUTED_VALUE"""),4.0) | B5: =IFERROR(__xludf.DUMMYFUNCTION("""COMPUTED_VALUE"""),3.2800001E8) | C5: =IFERROR(__xludf.DUMMYFUNCTION("""COMPUTED_VALUE"""),"DIAZ GHERY JUNIARSYAH RAHMAN") | D5: =IFERROR(__xludf.DUMMYFUNCTION("""COMPUTED_VALUE"""),"TECHNICIAN") | E5: =IFERROR(__xludf.DUMMYFUNCTION("""COMPUTED_VALUE"""),"ENGINEERING")
A6: =IFERROR(__xludf.DUMMYFUNCTION("""COMPUTED_VALUE"""),5.0) | B6: =IFERROR(__xludf.DUMMYFUNCTION("""COMPUTED_VALUE"""),3.28000011E8) | C6: =IFERROR(__xludf.DUMMYFUNCTION("""COMPUTED_VALUE"""),"DENI KUSNADI") | D6: =IFERROR(__xludf.DUMMYFUNCTION("""COMPUTED_VALUE"""),"ADMIN WSP") | E6: =IFERROR(__xludf.DUMMYFUNCTION("""COMPUTED_VALUE"""),"LOGISTIC")
A7: =IFERROR(__xludf.DUMMYFUNCTION("""COMPUTED_VALUE"""),6.0) | B7: =IFERROR(__xludf.DUMMYFUNCTION("""COMPUTED_VALUE"""),3.28000022E8) | C7: =IFERROR(__xludf.DUMMYFUNCTION("""COMPUTED_VALUE"""),"AZHAR AIZAD ALFARIDZI ") | D7: =IFERROR(__xludf.DUMMYFUNCTION("""COMPUTED_VALUE"""),"OPERATOR PRODUCTION") | E7: =IFERROR(__xludf.DUMMYFUNCTION("""COMPUTED_VALUE"""),"PRODUCTION")
A8: =IFERROR(__xludf.DUMMYFUNCTION("""COMPUTED_VALUE"""),7.0) | B8: =IFERROR(__xludf.DUMMYFUNCTION("""COMPUTED_VALUE"""),3.28000023E8) | C8: =IFERROR(__xludf.DUMMYFUNCTION("""COMPUTED_VALUE"""),"KEPIN NUGRAHA") | D8: =IFERROR(__xludf.DUMMYFUNCTION("""COMPUTED_VALUE"""),"OPERATOR PRODUCTION") | E8: =IFERROR(__xludf.DUMMYFUNCTION("""COMPUTED_VALUE"""),"PRODUCTION")
A9: =IFERROR(__xludf.DUMMYFUNCTION("""COMPUTED_VALUE"""),8.0) | B9: =IFERROR(__xludf.DUMMYFUNCTION("""COMPUTED_VALUE"""),3.28000026E8) | C9: =IFERROR(__xludf.DUMMYFUNCTION("""COMPUTED_VALUE"""),"DEDE WAHYUDIN ") | D9: =IFERROR(__xludf.DUMMYFUNCTION("""COMPUTED_VALUE"""),"OPERATOR PRODUCTION") | E9: =IFERROR(__xludf.DUMMYFUNCTION("""COMPUTED_VALUE"""),"PRODUCTION")
A10: =IFERROR(__xludf.DUMMYFUNCTION("""COMPUTED_VALUE"""),9.0) | B10: =IFERROR(__xludf.DUMMYFUNCTION("""COMPUTED_VALUE"""),3.28000027E8) | C10: =IFERROR(__xludf.DUMMYFUNCTION("""COMPUTED_VALUE"""),"GIGIN GINANJAR") | D10: =IFERROR(__xludf.DUMMYFUNCTION("""COMPUTED_VALUE"""),"OPERATOR PRODUCTION") | E10: =IFERROR(__xludf.DUMMYFUNCTION("""COMPUTED_VALUE"""),"PRODUCTION")
A11: =IFERROR(__xludf.DUMMYFUNCTION("""COMPUTED_VALUE"""),10.0) | B11: =IFERROR(__xludf.DUMMYFUNCTION("""COMPUTED_VALUE"""),3.28000028E8) | C11: =IFERROR(__xludf.DUMMYFUNCTION("""COMPUTED_VALUE"""),"TISNA GINANJAR") | D11: =IFERROR(__xludf.DUMMYFUNCTION("""COMPUTED_VALUE"""),"OPERATOR PRODUCTION") | E11: =IFERROR(__xludf.DUMMYFUNCTION("""COMPUTED_VALUE"""),"PRODUCTION")
A12: =IFERROR(__xludf.DUMMYFUNCTION("""COMPUTED_VALUE"""),11.0) | B12: =IFERROR(__xludf.DUMMYFUNCTION("""COMPUTED_VALUE"""),3.2800003E8) | C12: =IFERROR(__xludf.DUMMYFUNCTION("""COMPUTED_VALUE"""),"DAVA PUTRA YUDIANSYAH") | D12: =IFERROR(__xludf.DUMMYFUNCTION("""COMPUTED_VALUE"""),"OPERATOR PRODUCTION") | E12: =IFERROR(__xludf.DUMMYFUNCTION("""COMPUTED_VALUE"""),"PRODUCTION")
A13: =IFERROR(__xludf.DUMMYFUNCTION("""COMPUTED_VALUE"""),12.0) | B13: =IFERROR(__xludf.DUMMYFUNCTION("""COMPUTED_VALUE"""),3.28000032E8) | C13: =IFERROR(__xludf.DUMMYFUNCTION("""COMPUTED_VALUE"""),"RUBY SUBASTIAN") | D13: =IFERROR(__xludf.DUMMYFUNCTION("""COMPUTED_VALUE"""),"OPERATOR PRODUCTION") | E13: =IFERROR(__xludf.DUMMYFUNCTION("""COMPUTED_VALUE"""),"PRODUCTION")
A14: =IFERROR(__xludf.DUMMYFUNCTION("""COMPUTED_VALUE"""),13.0) | B14: =IFERROR(__xludf.DUMMYFUNCTION("""COMPUTED_VALUE"""),3.28000033E8) | C14: =IFERROR(__xludf.DUMMYFUNCTION("""COMPUTED_VALUE"""),"HENDRA") | D14: =IFERROR(__xludf.DUMMYFUNCTION("""COMPUTED_VALUE"""),"OPERATOR PRODUCTION") | E14: =IFERROR(__xludf.DUMMYFUNCTION("""COMPUTED_VALUE"""),"PRODUCTION")
A15: =IFERROR(__xludf.DUMMYFUNCTION("""COMPUTED_VALUE"""),14.0) | B15: =IFERROR(__xludf.DUMMYFUNCTION("""COMPUTED_VALUE"""),3.28000038E8) | C15: =IFERROR(__xludf.DUMMYFUNCTION("""COMPUTED_VALUE"""),"MESTHY PEBRIYANTI") | D15: =IFERROR(__xludf.DUMMYFUNCTION("""COMPUTED_VALUE"""),"QC LAB") | E15: =IFERROR(__xludf.DUMMYFUNCTION("""COMPUTED_VALUE"""),"QUALITY AND RESEARCH & DEVELOPMENT")
A16: =IFERROR(__xludf.DUMMYFUNCTION("""COMPUTED_VALUE"""),15.0) | B16: =IFERROR(__xludf.DUMMYFUNCTION("""COMPUTED_VALUE"""),3.28000039E8) | C16: =IFERROR(__xludf.DUMMYFUNCTION("""COMPUTED_VALUE"""),"DESTY MARLIANI") | D16: =IFERROR(__xludf.DUMMYFUNCTION("""COMPUTED_VALUE"""),"QC LAB") | E16: =IFERROR(__xludf.DUMMYFUNCTION("""COMPUTED_VALUE"""),"QUALITY AND RESEARCH & DEVELOPMENT")
A17: =IFERROR(__xludf.DUMMYFUNCTION("""COMPUTED_VALUE"""),16.0) | B17: =IFERROR(__xludf.DUMMYFUNCTION("""COMPUTED_VALUE"""),3.28000041E8) | C17: =IFERROR(__xludf.DUMMYFUNCTION("""COMPUTED_VALUE"""),"BUNGA ADELIYA") | D17: =IFERROR(__xludf.DUMMYFUNCTION("""COMPUTED_VALUE"""),"PACKER") | E17: =IFERROR(__xludf.DUMMYFUNCTION("""COMPUTED_VALUE"""),"PRODUCTION")
A18: =IFERROR(__xludf.DUMMYFUNCTION("""COMPUTED_VALUE"""),17.0) | B18: =IFERROR(__xludf.DUMMYFUNCTION("""COMPUTED_VALUE"""),3.28000043E8) | C18: =IFERROR(__xludf.DUMMYFUNCTION("""COMPUTED_VALUE"""),"ANDINI NOVIA RAMADANI") | D18: =IFERROR(__xludf.DUMMYFUNCTION("""COMPUTED_VALUE"""),"PACKER") | E18: =IFERROR(__xludf.DUMMYFUNCTION("""COMPUTED_VALUE"""),"PRODUCTION")
A19: =IFERROR(__xludf.DUMMYFUNCTION("""COMPUTED_VALUE"""),18.0) | B19: =IFERROR(__xludf.DUMMYFUNCTION("""COMPUTED_VALUE"""),3.28000052E8) | C19: =IFERROR(__xludf.DUMMYFUNCTION("""COMPUTED_VALUE"""),"DIMAS NUGROHO") | D19: =IFERROR(__xludf.DUMMYFUNCTION("""COMPUTED_VALUE"""),"ADMIN WSP") | E19: =IFERROR(__xludf.DUMMYFUNCTION("""COMPUTED_VALUE"""),"LOGISTIC")
A20: =IFERROR(__xludf.DUMMYFUNCTION("""COMPUTED_VALUE"""),19.0) | B20: =IFERROR(__xludf.DUMMYFUNCTION("""COMPUTED_VALUE"""),3.28000053E8) | C20: =IFERROR(__xludf.DUMMYFUNCTION("""COMPUTED_VALUE"""),"VERA PURBA") | D20: =IFERROR(__xludf.DUMMYFUNCTION("""COMPUTED_VALUE"""),"PRODUCTION ADMIN") | E20: =IFERROR(__xludf.DUMMYFUNCTION("""COMPUTED_VALUE"""),"PRODUCTION")
A21: =IFERROR(__xludf.DUMMYFUNCTION("""COMPUTED_VALUE"""),20.0) | B21: =IFERROR(__xludf.DUMMYFUNCTION("""COMPUTED_VALUE"""),3.28000063E8) | C21: =IFERROR(__xludf.DUMMYFUNCTION("""COMPUTED_VALUE"""),"RIZKI AGUNG") | D21: =IFERROR(__xludf.DUMMYFUNCTION("""COMPUTED_VALUE"""),"OPERATOR PRODUCTION") | E21: =IFERROR(__xludf.DUMMYFUNCTION("""COMPUTED_VALUE"""),"PRODUCTION")
A22: =IFERROR(__xludf.DUMMYFUNCTION("""COMPUTED_VALUE"""),21.0) | B22: =IFERROR(__xludf.DUMMYFUNCTION("""COMPUTED_VALUE"""),3.28000066E8) | C22: =IFERROR(__xludf.DUMMYFUNCTION("""COMPUTED_VALUE"""),"NADILA NAZIWA SOPIAN") | D22: =IFERROR(__xludf.DUMMYFUNCTION("""COMPUTED_VALUE"""),"QC LAB") | E22: =IFERROR(__xludf.DUMMYFUNCTION("""COMPUTED_VALUE"""),"QUALITY AND RESEARCH & DEVELOPMENT")
A23: =IFERROR(__xludf.DUMMYFUNCTION("""COMPUTED_VALUE"""),22.0) | B23: =IFERROR(__xludf.DUMMYFUNCTION("""COMPUTED_VALUE"""),3.28000068E8) | C23: =IFERROR(__xludf.DUMMYFUNCTION("""COMPUTED_VALUE"""),"NADINE RIEZKI GHEFIRA") | D23: =IFERROR(__xludf.DUMMYFUNCTION("""COMPUTED_VALUE"""),"QC LAB") | E23: =IFERROR(__xludf.DUMMYFUNCTION("""COMPUTED_VALUE"""),"QUALITY AND RESEARCH & DEVELOPMENT")
A24: =IFERROR(__xludf.DUMMYFUNCTION("""COMPUTED_VALUE"""),23.0) | B24: =IFERROR(__xludf.DUMMYFUNCTION("""COMPUTED_VALUE"""),3.2800007E8) | C24: =IFERROR(__xludf.DUMMYFUNCTION("""COMPUTED_VALUE"""),"BAYU AJIE PANGESTU") | D24: =IFERROR(__xludf.DUMMYFUNCTION("""COMPUTED_VALUE"""),"QC PATROL") | E24: =IFERROR(__xludf.DUMMYFUNCTION("""COMPUTED_VALUE"""),"QUALITY AND RESEARCH & DEVELOPMENT")
A25: =IFERROR(__xludf.DUMMYFUNCTION("""COMPUTED_VALUE"""),24.0) | B25: =IFERROR(__xludf.DUMMYFUNCTION("""COMPUTED_VALUE"""),3.28000072E8) | C25: =IFERROR(__xludf.DUMMYFUNCTION("""COMPUTED_VALUE"""),"ANISA FITALOKA") | D25: =IFERROR(__xludf.DUMMYFUNCTION("""COMPUTED_VALUE"""),"RF") | E25: =IFERROR(__xludf.DUMMYFUNCTION("""COMPUTED_VALUE"""),"PRODUCTION")
A26: =IFERROR(__xludf.DUMMYFUNCTION("""COMPUTED_VALUE"""),25.0) | B26: =IFERROR(__xludf.DUMMYFUNCTION("""COMPUTED_VALUE"""),3.2800008E8) | C26: =IFERROR(__xludf.DUMMYFUNCTION("""COMPUTED_VALUE"""),"ILHAM PAOJI MUHAROM") | D26: =IFERROR(__xludf.DUMMYFUNCTION("""COMPUTED_VALUE"""),"OPERATOR FORKLIFT") | E26: =IFERROR(__xludf.DUMMYFUNCTION("""COMPUTED_VALUE"""),"LOGISTIC")
A27: =IFERROR(__xludf.DUMMYFUNCTION("""COMPUTED_VALUE"""),26.0) | B27: =IFERROR(__xludf.DUMMYFUNCTION("""COMPUTED_VALUE"""),3.28000088E8) | C27: =IFERROR(__xludf.DUMMYFUNCTION("""COMPUTED_VALUE"""),"MEISY TRESA HANDAYANI") | D27: =IFERROR(__xludf.DUMMYFUNCTION("""COMPUTED_VALUE"""),"RF") | E27: =IFERROR(__xludf.DUMMYFUNCTION("""COMPUTED_VALUE"""),"PRODUCTION")
A28: =IFERROR(__xludf.DUMMYFUNCTION("""COMPUTED_VALUE"""),27.0) | B28: =IFERROR(__xludf.DUMMYFUNCTION("""COMPUTED_VALUE"""),3.28000095E8) | C28: =IFERROR(__xludf.DUMMYFUNCTION("""COMPUTED_VALUE"""),"AGUS JONI") | D28: =IFERROR(__xludf.DUMMYFUNCTION("""COMPUTED_VALUE"""),"OPERATOR PRODUCTION") | E28: =IFERROR(__xludf.DUMMYFUNCTION("""COMPUTED_VALUE"""),"PRODUCTION")
A29: =IFERROR(__xludf.DUMMYFUNCTION("""COMPUTED_VALUE"""),28.0) | B29: =IFERROR(__xludf.DUMMYFUNCTION("""COMPUTED_VALUE"""),3.28000097E8) | C29: =IFERROR(__xludf.DUMMYFUNCTION("""COMPUTED_VALUE"""),"YOGI RUDIYANTO") | D29: =IFERROR(__xludf.DUMMYFUNCTION("""COMPUTED_VALUE"""),"PIC AREA") | E29: =IFERROR(__xludf.DUMMYFUNCTION("""COMPUTED_VALUE"""),"LOGISTIC")
A30: =IFERROR(__xludf.DUMMYFUNCTION("""COMPUTED_VALUE"""),29.0) | B30: =IFERROR(__xludf.DUMMYFUNCTION("""COMPUTED_VALUE"""),3.28000104E8) | C30: =IFERROR(__xludf.DUMMYFUNCTION("""COMPUTED_VALUE"""),"TASYA APRIANI") | D30: =IFERROR(__xludf.DUMMYFUNCTION("""COMPUTED_VALUE"""),"PACKER") | E30: =IFERROR(__xludf.DUMMYFUNCTION("""COMPUTED_VALUE"""),"PRODUCTION")
A31: =IFERROR(__xludf.DUMMYFUNCTION("""COMPUTED_VALUE"""),30.0) | B31: =IFERROR(__xludf.DUMMYFUNCTION("""COMPUTED_VALUE"""),3.28000108E8) | C31: =IFERROR(__xludf.DUMMYFUNCTION("""COMPUTED_VALUE"""),"AHMAD NUR FAJAR") | D31: =IFERROR(__xludf.DUMMYFUNCTION("""COMPUTED_VALUE"""),"OPERATOR PRODUCTION") | E31: =IFERROR(__xludf.DUMMYFUNCTION("""COMPUTED_VALUE"""),"PRODUCTION")
A32: =IFERROR(__xludf.DUMMYFUNCTION("""COMPUTED_VALUE"""),31.0) | B32: =IFERROR(__xludf.DUMMYFUNCTION("""COMPUTED_VALUE"""),3.28000109E8) | C32: =IFERROR(__xludf.DUMMYFUNCTION("""COMPUTED_VALUE"""),"RIZKY PRADANA R") | D32: =IFERROR(__xludf.DUMMYFUNCTION("""COMPUTED_VALUE"""),"OPERATOR PRODUCTION") | E32: =IFERROR(__xludf.DUMMYFUNCTION("""COMPUTED_VALUE"""),"PRODUCTION")
A33: =IFERROR(__xludf.DUMMYFUNCTION("""COMPUTED_VALUE"""),32.0) | B33: =IFERROR(__xludf.DUMMYFUNCTION("""COMPUTED_VALUE"""),3.2800011E8) | C33: =IFERROR(__xludf.DUMMYFUNCTION("""COMPUTED_VALUE"""),"PRATAMA WAHYU SAPUTRO") | D33: =IFERROR(__xludf.DUMMYFUNCTION("""COMPUTED_VALUE"""),"OPERATOR PRODUCTION") | E33: =IFERROR(__xludf.DUMMYFUNCTION("""COMPUTED_VALUE"""),"PRODUCTION")
A34: =IFERROR(__xludf.DUMMYFUNCTION("""COMPUTED_VALUE"""),33.0) | B34: =IFERROR(__xludf.DUMMYFUNCTION("""COMPUTED_VALUE"""),3.28000111E8) | C34: =IFERROR(__xludf.DUMMYFUNCTION("""COMPUTED_VALUE"""),"KESLERIA") | D34: =IFERROR(__xludf.DUMMYFUNCTION("""COMPUTED_VALUE"""),"PACKER") | E34: =IFERROR(__xludf.DUMMYFUNCTION("""COMPUTED_VALUE"""),"PRODUCTION")
A35: =IFERROR(__xludf.DUMMYFUNCTION("""COMPUTED_VALUE"""),34.0) | B35: =IFERROR(__xludf.DUMMYFUNCTION("""COMPUTED_VALUE"""),3.28000112E8) | C35: =IFERROR(__xludf.DUMMYFUNCTION("""COMPUTED_VALUE"""),"FIRDAWATI") | D35: =IFERROR(__xludf.DUMMYFUNCTION("""COMPUTED_VALUE"""),"PACKER") | E35: =IFERROR(__xludf.DUMMYFUNCTION("""COMPUTED_VALUE"""),"PRODUCTION")
A36: =IFERROR(__xludf.DUMMYFUNCTION("""COMPUTED_VALUE"""),35.0) | B36: =IFERROR(__xludf.DUMMYFUNCTION("""COMPUTED_VALUE"""),3.28000115E8) | C36: =IFERROR(__xludf.DUMMYFUNCTION("""COMPUTED_VALUE"""),"SELY RISDIYANI") | D36: =IFERROR(__xludf.DUMMYFUNCTION("""COMPUTED_VALUE"""),"PACKER") | E36: =IFERROR(__xludf.DUMMYFUNCTION("""COMPUTED_VALUE"""),"PRODUCTION")
A37: =IFERROR(__xludf.DUMMYFUNCTION("""COMPUTED_VALUE"""),36.0) | B37: =IFERROR(__xludf.DUMMYFUNCTION("""COMPUTED_VALUE"""),3.28000122E8) | C37: =IFERROR(__xludf.DUMMYFUNCTION("""COMPUTED_VALUE"""),"SENDI") | D37: =IFERROR(__xludf.DUMMYFUNCTION("""COMPUTED_VALUE"""),"OPERATOR PRODUCTION") | E37: =IFERROR(__xludf.DUMMYFUNCTION("""COMPUTED_VALUE"""),"PRODUCTION")
A38: =IFERROR(__xludf.DUMMYFUNCTION("""COMPUTED_VALUE"""),37.0) | B38: =IFERROR(__xludf.DUMMYFUNCTION("""COMPUTED_VALUE"""),3.28000129E8) | C38: =IFERROR(__xludf.DUMMYFUNCTION("""COMPUTED_VALUE"""),"AHMAD SYAEFUDIN LATIEF") | D38: =IFERROR(__xludf.DUMMYFUNCTION("""COMPUTED_VALUE"""),"OPERATOR PRODUCTION") | E38: =IFERROR(__xludf.DUMMYFUNCTION("""COMPUTED_VALUE"""),"PRODUCTION")
A39: =IFERROR(__xludf.DUMMYFUNCTION("""COMPUTED_VALUE"""),38.0) | B39: =IFERROR(__xludf.DUMMYFUNCTION("""COMPUTED_VALUE"""),3.2800013E8) | C39: =IFERROR(__xludf.DUMMYFUNCTION("""COMPUTED_VALUE"""),"AGIL AGUSTIAWAN") | D39: =IFERROR(__xludf.DUMMYFUNCTION("""COMPUTED_VALUE"""),"OPERATOR PRODUCTION") | E39: =IFERROR(__xludf.DUMMYFUNCTION("""COMPUTED_VALUE"""),"PRODUCTION")
A40: =IFERROR(__xludf.DUMMYFUNCTION("""COMPUTED_VALUE"""),39.0) | B40: =IFERROR(__xludf.DUMMYFUNCTION("""COMPUTED_VALUE"""),3.28000132E8) | C40: =IFERROR(__xludf.DUMMYFUNCTION("""COMPUTED_VALUE"""),"FIRYAL FITRIYAH ABID SADIAH") | D40: =IFERROR(__xludf.DUMMYFUNCTION("""COMPUTED_VALUE"""),"QC PATROL") | E40: =IFERROR(__xludf.DUMMYFUNCTION("""COMPUTED_VALUE"""),"QUALITY AND RESEARCH & DEVELOPMENT")
A41: =IFERROR(__xludf.DUMMYFUNCTION("""COMPUTED_VALUE"""),40.0) | B41: =IFERROR(__xludf.DUMMYFUNCTION("""COMPUTED_VALUE"""),3.28000133E8) | C41: =IFERROR(__xludf.DUMMYFUNCTION("""COMPUTED_VALUE"""),"AMALIA INDRATAMA") | D41: =IFERROR(__xludf.DUMMYFUNCTION("""COMPUTED_VALUE"""),"QC PATROL") | E41: =IFERROR(__xludf.DUMMYFUNCTION("""COMPUTED_VALUE"""),"QUALITY AND RESEARCH & DEVELOPMENT")
A42: =IFERROR(__xludf.DUMMYFUNCTION("""COMPUTED_VALUE"""),41.0) | B42: =IFERROR(__xludf.DUMMYFUNCTION("""COMPUTED_VALUE"""),3.28000134E8) | C42: =IFERROR(__xludf.DUMMYFUNCTION("""COMPUTED_VALUE"""),"ASEP SEPTIANA") | D42: =IFERROR(__xludf.DUMMYFUNCTION("""COMPUTED_VALUE"""),"OPERATOR PRODUCTION") | E42: =IFERROR(__xludf.DUMMYFUNCTION("""COMPUTED_VALUE"""),"PRODUCTION")
A43: =IFERROR(__xludf.DUMMYFUNCTION("""COMPUTED_VALUE"""),42.0) | B43: =IFERROR(__xludf.DUMMYFUNCTION("""COMPUTED_VALUE"""),3.28000135E8) | C43: =IFERROR(__xludf.DUMMYFUNCTION("""COMPUTED_VALUE"""),"HARRY PANCA") | D43: =IFERROR(__xludf.DUMMYFUNCTION("""COMPUTED_VALUE"""),"OPERATOR PRODUCTION") | E43: =IFERROR(__xludf.DUMMYFUNCTION("""COMPUTED_VALUE"""),"PRODUCTION")
A44: =IFERROR(__xludf.DUMMYFUNCTION("""COMPUTED_VALUE"""),43.0) | B44: =IFERROR(__xludf.DUMMYFUNCTION("""COMPUTED_VALUE"""),3.2800014E8) | C44: =IFERROR(__xludf.DUMMYFUNCTION("""COMPUTED_VALUE"""),"JERY GUNAWAN") | D44: =IFERROR(__xludf.DUMMYFUNCTION("""COMPUTED_VALUE"""),"OPERATOR PRODUCTION") | E44: =IFERROR(__xludf.DUMMYFUNCTION("""COMPUTED_VALUE"""),"PRODUCTION")
A45: =IFERROR(__xludf.DUMMYFUNCTION("""COMPUTED_VALUE"""),44.0) | B45: =IFERROR(__xludf.DUMMYFUNCTION("""COMPUTED_VALUE"""),3.28000141E8) | C45: =IFERROR(__xludf.DUMMYFUNCTION("""COMPUTED_VALUE"""),"MAIMUNAH") | D45: =IFERROR(__xludf.DUMMYFUNCTION("""COMPUTED_VALUE"""),"PACKER") | E45: =IFERROR(__xludf.DUMMYFUNCTION("""COMPUTED_VALUE"""),"PRODUCTION")
A46: =IFERROR(__xludf.DUMMYFUNCTION("""COMPUTED_VALUE"""),45.0) | B46: =IFERROR(__xludf.DUMMYFUNCTION("""COMPUTED_VALUE"""),3.28000149E8) | C46: =IFERROR(__xludf.DUMMYFUNCTION("""COMPUTED_VALUE"""),"IRA RIDAYANTI") | D46: =IFERROR(__xludf.DUMMYFUNCTION("""COMPUTED_VALUE"""),"QC PRODUKSI") | E46: =IFERROR(__xludf.DUMMYFUNCTION("""COMPUTED_VALUE"""),"QUALITY AND RESEARCH & DEVELOPMENT")
A47: =IFERROR(__xludf.DUMMYFUNCTION("""COMPUTED_VALUE"""),46.0) | B47: =IFERROR(__xludf.DUMMYFUNCTION("""COMPUTED_VALUE"""),3.28000148E8) | C47: =IFERROR(__xludf.DUMMYFUNCTION("""COMPUTED_VALUE"""),"MUHAMMAD ALFIKRI") | D47: =IFERROR(__xludf.DUMMYFUNCTION("""COMPUTED_VALUE"""),"CHECKER") | E47: =IFERROR(__xludf.DUMMYFUNCTION("""COMPUTED_VALUE"""),"LOGISTIC")
A48: =IFERROR(__xludf.DUMMYFUNCTION("""COMPUTED_VALUE"""),47.0) | B48: =IFERROR(__xludf.DUMMYFUNCTION("""COMPUTED_VALUE"""),3.2800015E8) | C48: =IFERROR(__xludf.DUMMYFUNCTION("""COMPUTED_VALUE"""),"MUFTI ANAM") | D48: =IFERROR(__xludf.DUMMYFUNCTION("""COMPUTED_VALUE"""),"QC PATROL") | E48: =IFERROR(__xludf.DUMMYFUNCTION("""COMPUTED_VALUE"""),"QUALITY AND RESEARCH & DEVELOPMENT")
A49: =IFERROR(__xludf.DUMMYFUNCTION("""COMPUTED_VALUE"""),48.0) | B49: =IFERROR(__xludf.DUMMYFUNCTION("""COMPUTED_VALUE"""),3.28000153E8) | C49: =IFERROR(__xludf.DUMMYFUNCTION("""COMPUTED_VALUE"""),"SUSILAWATI") | D49: =IFERROR(__xludf.DUMMYFUNCTION("""COMPUTED_VALUE"""),"PACKER") | E49: =IFERROR(__xludf.DUMMYFUNCTION("""COMPUTED_VALUE"""),"PRODUCTION")
A50: =IFERROR(__xludf.DUMMYFUNCTION("""COMPUTED_VALUE"""),49.0) | B50: =IFERROR(__xludf.DUMMYFUNCTION("""COMPUTED_VALUE"""),3.28000157E8) | C50: =IFERROR(__xludf.DUMMYFUNCTION("""COMPUTED_VALUE"""),"VIVI NABIYA PUTRI") | D50: =IFERROR(__xludf.DUMMYFUNCTION("""COMPUTED_VALUE"""),"PACKER") | E50: =IFERROR(__xludf.DUMMYFUNCTION("""COMPUTED_VALUE"""),"PRODUCTION")
A51: =IFERROR(__xludf.DUMMYFUNCTION("""COMPUTED_VALUE"""),50.0) | B51: =IFERROR(__xludf.DUMMYFUNCTION("""COMPUTED_VALUE"""),3.28000161E8) | C51: =IFERROR(__xludf.DUMMYFUNCTION("""COMPUTED_VALUE"""),"NURUL NAJAH") | D51: =IFERROR(__xludf.DUMMYFUNCTION("""COMPUTED_VALUE"""),"QC PRODUKSI") | E51: =IFERROR(__xludf.DUMMYFUNCTION("""COMPUTED_VALUE"""),"QUALITY AND RESEARCH & DEVELOPMENT")
A52: =IFERROR(__xludf.DUMMYFUNCTION("""COMPUTED_VALUE"""),51.0) | B52: =IFERROR(__xludf.DUMMYFUNCTION("""COMPUTED_VALUE"""),3.28000164E8) | C52: =IFERROR(__xludf.DUMMYFUNCTION("""COMPUTED_VALUE"""),"RANI") | D52: =IFERROR(__xludf.DUMMYFUNCTION("""COMPUTED_VALUE"""),"QC PRODUKSI") | E52: =IFERROR(__xludf.DUMMYFUNCTION("""COMPUTED_VALUE"""),"QUALITY AND RESEARCH & DEVELOPMENT")
A53: =IFERROR(__xludf.DUMMYFUNCTION("""COMPUTED_VALUE"""),52.0) | B53: =IFERROR(__xludf.DUMMYFUNCTION("""COMPUTED_VALUE"""),3.28000173E8) | C53: =IFERROR(__xludf.DUMMYFUNCTION("""COMPUTED_VALUE"""),"RIFQI FADIILAH") | D53: =IFERROR(__xludf.DUMMYFUNCTION("""COMPUTED_VALUE"""),"OPERATOR PRODUCTION") | E53: =IFERROR(__xludf.DUMMYFUNCTION("""COMPUTED_VALUE"""),"PRODUCTION")
A54: =IFERROR(__xludf.DUMMYFUNCTION("""COMPUTED_VALUE"""),53.0) | B54: =IFERROR(__xludf.DUMMYFUNCTION("""COMPUTED_VALUE"""),3.28000175E8) | C54: =IFERROR(__xludf.DUMMYFUNCTION("""COMPUTED_VALUE"""),"FADILLAH RAMADHAN") | D54: =IFERROR(__xludf.DUMMYFUNCTION("""COMPUTED_VALUE"""),"OPERATOR PRODUCTION") | E54: =IFERROR(__xludf.DUMMYFUNCTION("""COMPUTED_VALUE"""),"PRODUCTION")
A55: =IFERROR(__xludf.DUMMYFUNCTION("""COMPUTED_VALUE"""),54.0) | B55: =IFERROR(__xludf.DUMMYFUNCTION("""COMPUTED_VALUE"""),3.28000178E8) | C55: =IFERROR(__xludf.DUMMYFUNCTION("""COMPUTED_VALUE"""),"BAMBANG ARTIAN HERLAMBANG") | D55: =IFERROR(__xludf.DUMMYFUNCTION("""COMPUTED_VALUE"""),"OPERATOR PRODUCTION") | E55: =IFERROR(__xludf.DUMMYFUNCTION("""COMPUTED_VALUE"""),"PRODUCTION")
A56: =IFERROR(__xludf.DUMMYFUNCTION("""COMPUTED_VALUE"""),55.0) | B56: =IFERROR(__xludf.DUMMYFUNCTION("""COMPUTED_VALUE"""),3.28000179E8) | C56: =IFERROR(__xludf.DUMMYFUNCTION("""COMPUTED_VALUE"""),"MUHAMMAD NOFALDI RADHITIA") | D56: =IFERROR(__xludf.DUMMYFUNCTION("""COMPUTED_VALUE"""),"OPERATOR PRODUCTION") | E56: =IFERROR(__xludf.DUMMYFUNCTION("""COMPUTED_VALUE"""),"PRODUCTION")
A57: =IFERROR(__xludf.DUMMYFUNCTION("""COMPUTED_VALUE"""),56.0) | B57: =IFERROR(__xludf.DUMMYFUNCTION("""COMPUTED_VALUE"""),3.2800018E8) | C57: =IFERROR(__xludf.DUMMYFUNCTION("""COMPUTED_VALUE"""),"OKTAVIO KUSUMA") | D57: =IFERROR(__xludf.DUMMYFUNCTION("""COMPUTED_VALUE"""),"OPERATOR PRODUCTION") | E57: =IFERROR(__xludf.DUMMYFUNCTION("""COMPUTED_VALUE"""),"PRODUCTION")
A58: =IFERROR(__xludf.DUMMYFUNCTION("""COMPUTED_VALUE"""),57.0) | B58: =IFERROR(__xludf.DUMMYFUNCTION("""COMPUTED_VALUE"""),3.28000185E8) | C58: =IFERROR(__xludf.DUMMYFUNCTION("""COMPUTED_VALUE"""),"FAJAR NURSYAMSI") | D58: =IFERROR(__xludf.DUMMYFUNCTION("""COMPUTED_VALUE"""),"OPERATOR PRODUCTION") | E58: =IFERROR(__xludf.DUMMYFUNCTION("""COMPUTED_VALUE"""),"PRODUCTION")
A59: =IFERROR(__xludf.DUMMYFUNCTION("""COMPUTED_VALUE"""),58.0) | B59: =IFERROR(__xludf.DUMMYFUNCTION("""COMPUTED_VALUE"""),3.28000191E8) | C59: =IFERROR(__xludf.DUMMYFUNCTION("""COMPUTED_VALUE"""),"MIRANTI AZAHRA") | D59: =IFERROR(__xludf.DUMMYFUNCTION("""COMPUTED_VALUE"""),"PACKER") | E59: =IFERROR(__xludf.DUMMYFUNCTION("""COMPUTED_VALUE"""),"PRODUCTION")
A60: =IFERROR(__xludf.DUMMYFUNCTION("""COMPUTED_VALUE"""),59.0) | B60: =IFERROR(__xludf.DUMMYFUNCTION("""COMPUTED_VALUE"""),3.28000197E8) | C60: =IFERROR(__xludf.DUMMYFUNCTION("""COMPUTED_VALUE"""),"TINI IRNAWATI") | D60: =IFERROR(__xludf.DUMMYFUNCTION("""COMPUTED_VALUE"""),"QC PRODUKSI") | E60: =IFERROR(__xludf.DUMMYFUNCTION("""COMPUTED_VALUE"""),"QUALITY AND RESEARCH & DEVELOPMENT")
A61: =IFERROR(__xludf.DUMMYFUNCTION("""COMPUTED_VALUE"""),60.0) | B61: =IFERROR(__xludf.DUMMYFUNCTION("""COMPUTED_VALUE"""),3.280002E8) | C61: =IFERROR(__xludf.DUMMYFUNCTION("""COMPUTED_VALUE"""),"CITRA AMEYLIA") | D61: =IFERROR(__xludf.DUMMYFUNCTION("""COMPUTED_VALUE"""),"PACKER") | E61: =IFERROR(__xludf.DUMMYFUNCTION("""COMPUTED_VALUE"""),"PRODUCTION")
A62: =IFERROR(__xludf.DUMMYFUNCTION("""COMPUTED_VALUE"""),61.0) | B62: =IFERROR(__xludf.DUMMYFUNCTION("""COMPUTED_VALUE"""),3.28000201E8) | C62: =IFERROR(__xludf.DUMMYFUNCTION("""COMPUTED_VALUE"""),"SITI ANNISA MAULINA") | D62: =IFERROR(__xludf.DUMMYFUNCTION("""COMPUTED_VALUE"""),"PACKER") | E62: =IFERROR(__xludf.DUMMYFUNCTION("""COMPUTED_VALUE"""),"PRODUCTION")
A63: =IFERROR(__xludf.DUMMYFUNCTION("""COMPUTED_VALUE"""),62.0) | B63: =IFERROR(__xludf.DUMMYFUNCTION("""COMPUTED_VALUE"""),3.28000207E8) | C63: =IFERROR(__xludf.DUMMYFUNCTION("""COMPUTED_VALUE"""),"MUHAMMAD ALVIANSYAH ZULFIKAR") | D63: =IFERROR(__xludf.DUMMYFUNCTION("""COMPUTED_VALUE"""),"OPERATOR PRODUCTION") | E63: =IFERROR(__xludf.DUMMYFUNCTION("""COMPUTED_VALUE"""),"PRODUCTION")
A64: =IFERROR(__xludf.DUMMYFUNCTION("""COMPUTED_VALUE"""),63.0) | B64: =IFERROR(__xludf.DUMMYFUNCTION("""COMPUTED_VALUE"""),3.28000216E8) | C64: =IFERROR(__xludf.DUMMYFUNCTION("""COMPUTED_VALUE"""),"MUHAMAD ADAM YANUAR") | D64: =IFERROR(__xludf.DUMMYFUNCTION("""COMPUTED_VALUE"""),"ENGINEERING ADMIN") | E64: =IFERROR(__xludf.DUMMYFUNCTION("""COMPUTED_VALUE"""),"ENGINEERING")
A65: =IFERROR(__xludf.DUMMYFUNCTION("""COMPUTED_VALUE"""),64.0) | B65: =IFERROR(__xludf.DUMMYFUNCTION("""COMPUTED_VALUE"""),3.28000219E8) | C65: =IFERROR(__xludf.DUMMYFUNCTION("""COMPUTED_VALUE"""),"WINDY MEILANI") | D65: =IFERROR(__xludf.DUMMYFUNCTION("""COMPUTED_VALUE"""),"PACKER") | E65: =IFERROR(__xludf.DUMMYFUNCTION("""COMPUTED_VALUE"""),"PRODUCTION")
A66: =IFERROR(__xludf.DUMMYFUNCTION("""COMPUTED_VALUE"""),65.0) | B66: =IFERROR(__xludf.DUMMYFUNCTION("""COMPUTED_VALUE"""),3.28000225E8) | C66: =IFERROR(__xludf.DUMMYFUNCTION("""COMPUTED_VALUE"""),"MUHAMAD RIZAL") | D66: =IFERROR(__xludf.DUMMYFUNCTION("""COMPUTED_VALUE"""),"OPERATOR PRODUCTION") | E66: =IFERROR(__xludf.DUMMYFUNCTION("""COMPUTED_VALUE"""),"PRODUCTION")
A67: =IFERROR(__xludf.DUMMYFUNCTION("""COMPUTED_VALUE"""),66.0) | B67: =IFERROR(__xludf.DUMMYFUNCTION("""COMPUTED_VALUE"""),3.28000226E8) | C67: =IFERROR(__xludf.DUMMYFUNCTION("""COMPUTED_VALUE"""),"PAISYAL ZULFAZILA IBRAHIM") | D67: =IFERROR(__xludf.DUMMYFUNCTION("""COMPUTED_VALUE"""),"QC INCOMING") | E67: =IFERROR(__xludf.DUMMYFUNCTION("""COMPUTED_VALUE"""),"QUALITY AND RESEARCH & DEVELOPMENT")
A68: =IFERROR(__xludf.DUMMYFUNCTION("""COMPUTED_VALUE"""),67.0) | B68: =IFERROR(__xludf.DUMMYFUNCTION("""COMPUTED_VALUE"""),3.28000228E8) | C68: =IFERROR(__xludf.DUMMYFUNCTION("""COMPUTED_VALUE"""),"JULIANTORO SONJAYA") | D68: =IFERROR(__xludf.DUMMYFUNCTION("""COMPUTED_VALUE"""),"OPERATOR PRODUCTION") | E68: =IFERROR(__xludf.DUMMYFUNCTION("""COMPUTED_VALUE"""),"PRODUCTION")
A69: =IFERROR(__xludf.DUMMYFUNCTION("""COMPUTED_VALUE"""),68.0) | B69: =IFERROR(__xludf.DUMMYFUNCTION("""COMPUTED_VALUE"""),3.2800023E8) | C69: =IFERROR(__xludf.DUMMYFUNCTION("""COMPUTED_VALUE"""),"MUHAMAD AKBAR FAUZAN") | D69: =IFERROR(__xludf.DUMMYFUNCTION("""COMPUTED_VALUE"""),"ADMIN TSP") | E69: =IFERROR(__xludf.DUMMYFUNCTION("""COMPUTED_VALUE"""),"PRODUCTION")
A70: =IFERROR(__xludf.DUMMYFUNCTION("""COMPUTED_VALUE"""),69.0) | B70: =IFERROR(__xludf.DUMMYFUNCTION("""COMPUTED_VALUE"""),3.28000231E8) | C70: =IFERROR(__xludf.DUMMYFUNCTION("""COMPUTED_VALUE"""),"MARA MAULANA") | D70: =IFERROR(__xludf.DUMMYFUNCTION("""COMPUTED_VALUE"""),"PACKER") | E70: =IFERROR(__xludf.DUMMYFUNCTION("""COMPUTED_VALUE"""),"PRODUCTION")
A71: =IFERROR(__xludf.DUMMYFUNCTION("""COMPUTED_VALUE"""),70.0) | B71: =IFERROR(__xludf.DUMMYFUNCTION("""COMPUTED_VALUE"""),3.28000235E8) | C71: =IFERROR(__xludf.DUMMYFUNCTION("""COMPUTED_VALUE"""),"ROSALIA PUTRI") | D71: =IFERROR(__xludf.DUMMYFUNCTION("""COMPUTED_VALUE"""),"QC PRODUKSI") | E71: =IFERROR(__xludf.DUMMYFUNCTION("""COMPUTED_VALUE"""),"QUALITY AND RESEARCH & DEVELOPMENT")
A72: =IFERROR(__xludf.DUMMYFUNCTION("""COMPUTED_VALUE"""),71.0) | B72: =IFERROR(__xludf.DUMMYFUNCTION("""COMPUTED_VALUE"""),3.2800024E8) | C72: =IFERROR(__xludf.DUMMYFUNCTION("""COMPUTED_VALUE"""),"RAHAJENG TRI NUGRAENI") | D72: =IFERROR(__xludf.DUMMYFUNCTION("""COMPUTED_VALUE"""),"PACKER") | E72: =IFERROR(__xludf.DUMMYFUNCTION("""COMPUTED_VALUE"""),"PRODUCTION")
A73: =IFERROR(__xludf.DUMMYFUNCTION("""COMPUTED_VALUE"""),72.0) | B73: =IFERROR(__xludf.DUMMYFUNCTION("""COMPUTED_VALUE"""),3.28000246E8) | C73: =IFERROR(__xludf.DUMMYFUNCTION("""COMPUTED_VALUE"""),"DWI FITRIANI") | D73: =IFERROR(__xludf.DUMMYFUNCTION("""COMPUTED_VALUE"""),"PACKER") | E73: =IFERROR(__xludf.DUMMYFUNCTION("""COMPUTED_VALUE"""),"PRODUCTION")
A74: =IFERROR(__xludf.DUMMYFUNCTION("""COMPUTED_VALUE"""),73.0) | B74: =IFERROR(__xludf.DUMMYFUNCTION("""COMPUTED_VALUE"""),3.28000251E8) | C74: =IFERROR(__xludf.DUMMYFUNCTION("""COMPUTED_VALUE"""),"DEDE SAMAN NURSAMSI ") | D74: =IFERROR(__xludf.DUMMYFUNCTION("""COMPUTED_VALUE"""),"CHECKER") | E74: =IFERROR(__xludf.DUMMYFUNCTION("""COMPUTED_VALUE"""),"LOGISTIC")
A75: =IFERROR(__xludf.DUMMYFUNCTION("""COMPUTED_VALUE"""),74.0) | B75: =IFERROR(__xludf.DUMMYFUNCTION("""COMPUTED_VALUE"""),3.28000253E8) | C75: =IFERROR(__xludf.DUMMYFUNCTION("""COMPUTED_VALUE"""),"DONI SUBHADA") | D75: =IFERROR(__xludf.DUMMYFUNCTION("""COMPUTED_VALUE"""),"OPERATOR PRODUCTION") | E75: =IFERROR(__xludf.DUMMYFUNCTION("""COMPUTED_VALUE"""),"PRODUCTION")
A76: =IFERROR(__xludf.DUMMYFUNCTION("""COMPUTED_VALUE"""),75.0) | B76: =IFERROR(__xludf.DUMMYFUNCTION("""COMPUTED_VALUE"""),3.28000254E8) | C76: =IFERROR(__xludf.DUMMYFUNCTION("""COMPUTED_VALUE"""),"ARI MUHAMAD RIDWAN ") | D76: =IFERROR(__xludf.DUMMYFUNCTION("""COMPUTED_VALUE"""),"OPERATOR FORKLIFT") | E76: =IFERROR(__xludf.DUMMYFUNCTION("""COMPUTED_VALUE"""),"LOGISTIC")
A77: =IFERROR(__xludf.DUMMYFUNCTION("""COMPUTED_VALUE"""),76.0) | B77: =IFERROR(__xludf.DUMMYFUNCTION("""COMPUTED_VALUE"""),3.28000255E8) | C77: =IFERROR(__xludf.DUMMYFUNCTION("""COMPUTED_VALUE"""),"FAHRI") | D77: =IFERROR(__xludf.DUMMYFUNCTION("""COMPUTED_VALUE"""),"OPERATOR PRODUCTION") | E77: =IFERROR(__xludf.DUMMYFUNCTION("""COMPUTED_VALUE"""),"PRODUCTION")
A78: =IFERROR(__xludf.DUMMYFUNCTION("""COMPUTED_VALUE"""),77.0) | B78: =IFERROR(__xludf.DUMMYFUNCTION("""COMPUTED_VALUE"""),3.28000256E8) | C78: =IFERROR(__xludf.DUMMYFUNCTION("""COMPUTED_VALUE"""),"MIFTAHUS SALAM") | D78: =IFERROR(__xludf.DUMMYFUNCTION("""COMPUTED_VALUE"""),"OPERATOR FORKLIFT") | E78: =IFERROR(__xludf.DUMMYFUNCTION("""COMPUTED_VALUE"""),"LOGISTIC")
A79: =IFERROR(__xludf.DUMMYFUNCTION("""COMPUTED_VALUE"""),78.0) | B79: =IFERROR(__xludf.DUMMYFUNCTION("""COMPUTED_VALUE"""),3.28000257E8) | C79: =IFERROR(__xludf.DUMMYFUNCTION("""COMPUTED_VALUE"""),"AGUNG BAGASKARA") | D79: =IFERROR(__xludf.DUMMYFUNCTION("""COMPUTED_VALUE"""),"OPERATOR FORKLIFT") | E79: =IFERROR(__xludf.DUMMYFUNCTION("""COMPUTED_VALUE"""),"LOGISTIC")
A80: =IFERROR(__xludf.DUMMYFUNCTION("""COMPUTED_VALUE"""),79.0) | B80: =IFERROR(__xludf.DUMMYFUNCTION("""COMPUTED_VALUE"""),3.2800026E8) | C80: =IFERROR(__xludf.DUMMYFUNCTION("""COMPUTED_VALUE"""),"ALI RAMDHAN") | D80: =IFERROR(__xludf.DUMMYFUNCTION("""COMPUTED_VALUE"""),"OPERATOR PRODUCTION") | E80: =IFERROR(__xludf.DUMMYFUNCTION("""COMPUTED_VALUE"""),"PRODUCTION")
A81: =IFERROR(__xludf.DUMMYFUNCTION("""COMPUTED_VALUE"""),80.0) | B81: =IFERROR(__xludf.DUMMYFUNCTION("""COMPUTED_VALUE"""),3.28000261E8) | C81: =IFERROR(__xludf.DUMMYFUNCTION("""COMPUTED_VALUE"""),"ARANIKITA BERU SIBIRO ") | D81: =IFERROR(__xludf.DUMMYFUNCTION("""COMPUTED_VALUE"""),"ADMIN EKSPEDISI") | E81: =IFERROR(__xludf.DUMMYFUNCTION("""COMPUTED_VALUE"""),"LOGISTIC")
A82: =IFERROR(__xludf.DUMMYFUNCTION("""COMPUTED_VALUE"""),81.0) | B82: =IFERROR(__xludf.DUMMYFUNCTION("""COMPUTED_VALUE"""),3.28000262E8) | C82: =IFERROR(__xludf.DUMMYFUNCTION("""COMPUTED_VALUE"""),"JUJUN JUNAEDI") | D82: =IFERROR(__xludf.DUMMYFUNCTION("""COMPUTED_VALUE"""),"OPERATOR FORKLIFT") | E82: =IFERROR(__xludf.DUMMYFUNCTION("""COMPUTED_VALUE"""),"LOGISTIC")
A83: =IFERROR(__xludf.DUMMYFUNCTION("""COMPUTED_VALUE"""),82.0) | B83: =IFERROR(__xludf.DUMMYFUNCTION("""COMPUTED_VALUE"""),3.28000263E8) | C83: =IFERROR(__xludf.DUMMYFUNCTION("""COMPUTED_VALUE"""),"MAGIE MAGHFIRA") | D83: =IFERROR(__xludf.DUMMYFUNCTION("""COMPUTED_VALUE"""),"ADMIN WFG") | E83: =IFERROR(__xludf.DUMMYFUNCTION("""COMPUTED_VALUE"""),"LOGISTIC")
A84: =IFERROR(__xludf.DUMMYFUNCTION("""COMPUTED_VALUE"""),83.0) | B84: =IFERROR(__xludf.DUMMYFUNCTION("""COMPUTED_VALUE"""),3.28000265E8) | C84: =IFERROR(__xludf.DUMMYFUNCTION("""COMPUTED_VALUE"""),"NELSON MANDELA ") | D84: =IFERROR(__xludf.DUMMYFUNCTION("""COMPUTED_VALUE"""),"UTILITY, ELECTRICITY & MHE MAINTENANCE") | E84: =IFERROR(__xludf.DUMMYFUNCTION("""COMPUTED_VALUE"""),"ENGINEERING")
A85: =IFERROR(__xludf.DUMMYFUNCTION("""COMPUTED_VALUE"""),84.0) | B85: =IFERROR(__xludf.DUMMYFUNCTION("""COMPUTED_VALUE"""),3.28000271E8) | C85: =IFERROR(__xludf.DUMMYFUNCTION("""COMPUTED_VALUE"""),"NURYANA") | D85: =IFERROR(__xludf.DUMMYFUNCTION("""COMPUTED_VALUE"""),"OPERATOR FORKLIFT") | E85: =IFERROR(__xludf.DUMMYFUNCTION("""COMPUTED_VALUE"""),"LOGISTIC")
A86: =IFERROR(__xludf.DUMMYFUNCTION("""COMPUTED_VALUE"""),85.0) | B86: =IFERROR(__xludf.DUMMYFUNCTION("""COMPUTED_VALUE"""),3.28000273E8) | C86: =IFERROR(__xludf.DUMMYFUNCTION("""COMPUTED_VALUE"""),"RAMDANI") | D86: =IFERROR(__xludf.DUMMYFUNCTION("""COMPUTED_VALUE"""),"PACKER") | E86: =IFERROR(__xludf.DUMMYFUNCTION("""COMPUTED_VALUE"""),"PRODUCTION")
A87: =IFERROR(__xludf.DUMMYFUNCTION("""COMPUTED_VALUE"""),86.0) | B87: =IFERROR(__xludf.DUMMYFUNCTION("""COMPUTED_VALUE"""),3.28000277E8) | C87: =IFERROR(__xludf.DUMMYFUNCTION("""COMPUTED_VALUE"""),"ERNA SUSNENTI") | D87: =IFERROR(__xludf.DUMMYFUNCTION("""COMPUTED_VALUE"""),"ADMIN RF") | E87: =IFERROR(__xludf.DUMMYFUNCTION("""COMPUTED_VALUE"""),"PRODUCTION")
A88: =IFERROR(__xludf.DUMMYFUNCTION("""COMPUTED_VALUE"""),87.0) | B88: =IFERROR(__xludf.DUMMYFUNCTION("""COMPUTED_VALUE"""),3.28000278E8) | C88: =IFERROR(__xludf.DUMMYFUNCTION("""COMPUTED_VALUE"""),"VERA NATASYA PUTRI") | D88: =IFERROR(__xludf.DUMMYFUNCTION("""COMPUTED_VALUE"""),"PACKER") | E88: =IFERROR(__xludf.DUMMYFUNCTION("""COMPUTED_VALUE"""),"PRODUCTION")
A89: =IFERROR(__xludf.DUMMYFUNCTION("""COMPUTED_VALUE"""),88.0) | B89: =IFERROR(__xludf.DUMMYFUNCTION("""COMPUTED_VALUE"""),3.28000283E8) | C89: =IFERROR(__xludf.DUMMYFUNCTION("""COMPUTED_VALUE"""),"TAUFIK MUSTOPA") | D89: =IFERROR(__xludf.DUMMYFUNCTION("""COMPUTED_VALUE"""),"EHS SUPPORT") | E89: =IFERROR(__xludf.DUMMYFUNCTION("""COMPUTED_VALUE"""),"ENGINEERING")
A90: =IFERROR(__xludf.DUMMYFUNCTION("""COMPUTED_VALUE"""),89.0) | B90: =IFERROR(__xludf.DUMMYFUNCTION("""COMPUTED_VALUE"""),3.28000285E8) | C90: =IFERROR(__xludf.DUMMYFUNCTION("""COMPUTED_VALUE"""),"M. YOGA PAMUNGKAS") | D90: =IFERROR(__xludf.DUMMYFUNCTION("""COMPUTED_VALUE"""),"OPERATOR PRODUCTION") | E90: =IFERROR(__xludf.DUMMYFUNCTION("""COMPUTED_VALUE"""),"PRODUCTION")
A91: =IFERROR(__xludf.DUMMYFUNCTION("""COMPUTED_VALUE"""),90.0) | B91: =IFERROR(__xludf.DUMMYFUNCTION("""COMPUTED_VALUE"""),3.28000287E8) | C91: =IFERROR(__xludf.DUMMYFUNCTION("""COMPUTED_VALUE"""),"FIRDA AINUN RAHMANNISA") | D91: =IFERROR(__xludf.DUMMYFUNCTION("""COMPUTED_VALUE"""),"ENGINEERING ADMIN") | E91: =IFERROR(__xludf.DUMMYFUNCTION("""COMPUTED_VALUE"""),"ENGINEERING")
A92: =IFERROR(__xludf.DUMMYFUNCTION("""COMPUTED_VALUE"""),91.0) | B92: =IFERROR(__xludf.DUMMYFUNCTION("""COMPUTED_VALUE"""),3.28000288E8) | C92: =IFERROR(__xludf.DUMMYFUNCTION("""COMPUTED_VALUE"""),"ANDIKA AL AQBAR") | D92: =IFERROR(__xludf.DUMMYFUNCTION("""COMPUTED_VALUE"""),"OPERATOR PRODUCTION") | E92: =IFERROR(__xludf.DUMMYFUNCTION("""COMPUTED_VALUE"""),"PRODUCTION")
A93: =IFERROR(__xludf.DUMMYFUNCTION("""COMPUTED_VALUE"""),92.0) | B93: =IFERROR(__xludf.DUMMYFUNCTION("""COMPUTED_VALUE"""),3.28000291E8) | C93: =IFERROR(__xludf.DUMMYFUNCTION("""COMPUTED_VALUE"""),"R. ANISA DWI FEBRIANA") | D93: =IFERROR(__xludf.DUMMYFUNCTION("""COMPUTED_VALUE"""),"PACKER") | E93: =IFERROR(__xludf.DUMMYFUNCTION("""COMPUTED_VALUE"""),"PRODUCTION")
A94: =IFERROR(__xludf.DUMMYFUNCTION("""COMPUTED_VALUE"""),93.0) | B94: =IFERROR(__xludf.DUMMYFUNCTION("""COMPUTED_VALUE"""),3.28000294E8) | C94: =IFERROR(__xludf.DUMMYFUNCTION("""COMPUTED_VALUE"""),"BAMBANG IRAWAN") | D94: =IFERROR(__xludf.DUMMYFUNCTION("""COMPUTED_VALUE"""),"OPERATOR PRODUCTION") | E94: =IFERROR(__xludf.DUMMYFUNCTION("""COMPUTED_VALUE"""),"PRODUCTION")
A95: =IFERROR(__xludf.DUMMYFUNCTION("""COMPUTED_VALUE"""),94.0) | B95: =IFERROR(__xludf.DUMMYFUNCTION("""COMPUTED_VALUE"""),3.28000297E8) | C95: =IFERROR(__xludf.DUMMYFUNCTION("""COMPUTED_VALUE"""),"AMALIATUS SHIDQIA") | D95: =IFERROR(__xludf.DUMMYFUNCTION("""COMPUTED_VALUE"""),"PACKER") | E95: =IFERROR(__xludf.DUMMYFUNCTION("""COMPUTED_VALUE"""),"PRODUCTION")
A96: =IFERROR(__xludf.DUMMYFUNCTION("""COMPUTED_VALUE"""),95.0) | B96: =IFERROR(__xludf.DUMMYFUNCTION("""COMPUTED_VALUE"""),3.28000298E8) | C96: =IFERROR(__xludf.DUMMYFUNCTION("""COMPUTED_VALUE"""),"SILFANNY OKTAVIA WIGUNA") | D96: =IFERROR(__xludf.DUMMYFUNCTION("""COMPUTED_VALUE"""),"QC PRODUKSI") | E96: =IFERROR(__xludf.DUMMYFUNCTION("""COMPUTED_VALUE"""),"QUALITY AND RESEARCH & DEVELOPMENT")
A97: =IFERROR(__xludf.DUMMYFUNCTION("""COMPUTED_VALUE"""),96.0) | B97: =IFERROR(__xludf.DUMMYFUNCTION("""COMPUTED_VALUE"""),3.28000299E8) | C97: =IFERROR(__xludf.DUMMYFUNCTION("""COMPUTED_VALUE"""),"RATU THYARA REVA KHARINA") | D97: =IFERROR(__xludf.DUMMYFUNCTION("""COMPUTED_VALUE"""),"PACKER") | E97: =IFERROR(__xludf.DUMMYFUNCTION("""COMPUTED_VALUE"""),"PRODUCTION")
A98: =IFERROR(__xludf.DUMMYFUNCTION("""COMPUTED_VALUE"""),97.0) | B98: =IFERROR(__xludf.DUMMYFUNCTION("""COMPUTED_VALUE"""),3.280003E8) | C98: =IFERROR(__xludf.DUMMYFUNCTION("""COMPUTED_VALUE"""),"EGA ANGGARA") | D98: =IFERROR(__xludf.DUMMYFUNCTION("""COMPUTED_VALUE"""),"GLUE MACHINE MAINTENANCE") | E98: =IFERROR(__xludf.DUMMYFUNCTION("""COMPUTED_VALUE"""),"ENGINEERING")
A99: =IFERROR(__xludf.DUMMYFUNCTION("""COMPUTED_VALUE"""),98.0) | B99: =IFERROR(__xludf.DUMMYFUNCTION("""COMPUTED_VALUE"""),3.28000301E8) | C99: =IFERROR(__xludf.DUMMYFUNCTION("""COMPUTED_VALUE"""),"CINDY PERMATASARI") | D99: =IFERROR(__xludf.DUMMYFUNCTION("""COMPUTED_VALUE"""),"ADMIN WRM") | E99: =IFERROR(__xludf.DUMMYFUNCTION("""COMPUTED_VALUE"""),"LOGISTIC")
A100: =IFERROR(__xludf.DUMMYFUNCTION("""COMPUTED_VALUE"""),99.0) | B100: =IFERROR(__xludf.DUMMYFUNCTION("""COMPUTED_VALUE"""),3.28000302E8) | C100: =IFERROR(__xludf.DUMMYFUNCTION("""COMPUTED_VALUE"""),"ALFIA NURULLITA") | D100: =IFERROR(__xludf.DUMMYFUNCTION("""COMPUTED_VALUE"""),"PACKER") | E100: =IFERROR(__xludf.DUMMYFUNCTION("""COMPUTED_VALUE"""),"PRODUCTION")
...

Sheet MITRA KERJA
A1: NIK | B1: Nama Karyawan | C1: Jenis Kekaryawanan | D1: Department | E1: Posisi | F1: Tanggal Scan IRIS | G1: ID IRIS | H1: Data Enrollment | I1: Status Perubahan Perbedaan Data
A2: 428000004 | B2: ADI MUZAKI | C2: Mitra Kerja | D2: HRGA | E2: GA Vendor | F2: 2025-5-13 | G2: 0000122823 | I2: Completed
A3: 428000006 | B3: BAGAS JUAN PRATAMA | C3: Mitra Kerja | D3: HRGA | E3: GA Vendor | F3: 2025-5-5 | G3: 0000122123 | I3: -
A4: 428000011 | B4: DINO DRAJAT | C4: Mitra Kerja | D4: HRGA | E4: GA Vendor | F4: 2025-5-9 | G4: 0000122639 | I4: -
A5: 428000012 | B5: RIDKI MAULANA | C5: Mitra Kerja | D5: HRGA | E5: GA Vendor | F5: 2025-5-10 | G5: 0000122722 | I5: -
A6: 428000014 | B6: ADITYA SAPUTRA | C6: Mitra Kerja | D6: HRGA | E6: GA Vendor | F6: 2025-5-5 | G6: 0000122106 | I6: -
A7: 428000015 | B7: MOCHAMMAD AJAR NURJI | C7: Mitra Kerja | D7: HRGA | E7: GA Vendor | F7: 2025-5-5 | G7: 0000122108 | I7: -
A8: 428000020 | B8: MUSLIM | C8: Mitra Kerja | D8: HRGA | E8: GA Vendor | F8: 2025-5-5 | G8: 0000122121 | I8: -
A9: 428000021 | B9: CARI IRAWAN | C9: Mitra Kerja | D9: HRGA | E9: GA Vendor | F9: 2022-9-6 | G9: 0000055031 | I9: -
A10: 428000024 | B10: ADI MAULANA | C10: Mitra Kerja | D10: HRGA | E10: GA Vendor | F10: 2025-5-8 | G10: 0000122597 | I10: -
A11: 428000030 | B11: ERDI HERDIANSYAH | C11: Mitra Kerja | D11: HRGA | E11: GA Vendor | F11: 2025-5-8 | G11: 0000122592 | I11: -
A12: 428000031 | B12: SARIP HIDAYAT | C12: Mitra Kerja | D12: HRGA | E12: GA Vendor | F12: 2025-5-6 | G12: 0000122300 | I12: -
A13: 428000032 | B13: HERI HOERUDIN | C13: Mitra Kerja | D13: HRGA | E13: GA Vendor | F13: 2025-5-13 | G13: 0000122814 | I13: Completed
... A35: 428000069 | B35: GITHA FAHSYA APRILIYUNIARNI JUANDI | C35: Mitra Kerja | D35: HRGA | E35: GA Vendor | F35: 2025-5-5 | G35: 0000122098 | I35: -
A36: 428000070 | B36: ATEP HIDAYAT | C36: Mitra Kerja | D36: HRGA | E36: GA Vendor
A37: 428000071 | B37: DADI KURNIADI | C37: Mitra Kerja | D37: HRGA | E37: GA Vendor | F37: 2025-5-6 | G37: 0000122287 | I37: -
A38: 428000073 | B38: FIKRI YANDIKA RAMADHAN | C38: Mitra Kerja | D38: HRGA | E38: GA Vendor | F38: 2025-5-28 | G38: 0000123565 | I38: -
A39: 428000074 | B39: SUNARYO | C39: Mitra Kerja | D39: HRGA | E39: GA Vendor | F39: 2025-7-5 | G39: 0000125311 | I39: -
A40: 428000075 | B40: DINA VEBRIANTI | C40: Mitra Kerja | D40: HRGA | E40: GA Vendor | F40: 2025-7-5 | G40: 0000125307 | I40: -
A41: 428000076 | B41: ELFAN TAUFIK S | C41: Mitra Kerja | D41: HRGA | E41: GA Vendor | F41: 2025-7-5 | G41: 0000125322 | I41: To Be Corrected
A42: 428000077 | B42: EKA PRADITA | C42: Mitra Kerja | D42: HRGA | E42: GA Vendor | F42: 2025-7-5 | G42: 0000125315 | I42: -
A43: 428000078 | B43: ARIF MAULANA Y | C43: Mitra Kerja | D43: HRGA | E43: GA Vendor | F43: 2025-7-5 | G43: 0000125314 | I43: To Be Corrected
A44: 428000079 | B44: TAOPIK HIDAYAT | C44: Mitra Kerja | D44: HRGA | E44: GA Vendor | F44: 2025-7-5 | G44: 0000125318 | I44: -
A45: 428000080 | B45: ROHIM | C45: Mitra Kerja | D45: HRGA | E45: GA Vendor | F45: 2025-7-5 | G45: 0000125309 | I45: -
A46: 428000081 | B46: M TANTAN T | C46: Mitra Kerja | D46: HRGA | E46: GA Vendor | F46: 2025-7-5 | G46: 0000125308 | I46: To Be Corrected
A47: 428000083 | B47: RIKI SONJAYA | C47: Mitra Kerja | D47: HRGA | E47: GA Vendor | F47: 2025-7-5 | G47: 0000125313 | I47: -
A48: 428000084 | B48: EKA SETIAWAN | C48: Mitra Kerja | D48: HRGA | E48: GA Vendor | F48: 2025-7-5 | G48: 0000125312 | I48: -
... A84: 528000132 | B84: Giopani | C84: Mitra Kerja | D84: LOG | E84: WRM Harian | F84: 2025-5-10 | G84: 0000122717 | I84: Completed
A85: 528000144 | B85: Jodi Hanafi | C85: Mitra Kerja | D85: LOG | E85: WRM Harian
A86: 528000146 | B86: Deny Afrizal | C86: Mitra Kerja | D86: PROD | E86: Produksi Harian | F86: 2025-5-14 | G86: 0000122873 | I86: To Be Corrected
A87: 528000149 | B87: Tio Fernanda | C87: Mitra Kerja | D87: LOG | E87: WRM Harian | F87: 2025-5-10 | G87: 0000122720 | I87: Completed
A88: 528000155 | B88: Dea Amelia | C88: Mitra Kerja | D88: PROD | E88: Produksi Harian
A89: 528000158 | B89: Eva Nurjanah | C89: Mitra Kerja | D89: PROD | E89: Produksi Harian | F89: 2025-5-16 | G89: 0000123074 | I89: Completed
A90: 528000194 | B90: Tanti Haryanti | C90: Mitra Kerja | D90: PROD | E90: Produksi Borongan
A91: 528000195 | B91: Rahma Sariwati | C91: Mitra Kerja | D91: PROD | E91: Produksi Harian | F91: 2025-5-9 | G91: 0000122648 | I91: -
A92: 528000196 | B92: Ropika Handayani | C92: Mitra Kerja | D92: PROD | E92: Produksi Harian | F92: 2025-5-9 | G92: 0000122672 | I92: Completed
A93: 528000198 | B93: Herlan Darus Maulana | C93: Mitra Kerja | D93: ENG | E93: Engineering Harian
A94: 528000199 | B94: Giparel Hamdani | C94: Mitra Kerja | D94: LOG | E94: WRM Harian | F94: 2025-5-9 | G94: 0000122692 | I94: -
A95: 528000201 | B95: Zahwa Amelia Choerunissa | C95: Mitra Kerja | D95: PROD | E95: Produksi Harian | F95: 2025-5-19 | G95: 0000123127 | I95: -
A96: 528000202 | B96: Asep Saepudin | C96: Mitra Kerja | D96: LOG | E96: WRM Harian
A97: 528000203 | B97: Yudha Ramdhan Putra | C97: Mitra Kerja | D97: ENG | E97: Engineering Harian | F97: 2025-5-19 | G97: 0000123166 | I97: -
A98: 528000205 | B98: Alvino Sofyan | C98: Mitra Kerja | D98: PROD | E98: Produksi Harian | F98: 2025-5-20 | G98: 0000123261 | I98: To Be Corrected
A99: 528000206 | B99: Dika Wardiansyah | C99: Mitra Kerja | D99: LOG | E99: WRM Harian
A100: 528000209 | B100: Rivaldo Permana | C100: Mitra Kerja | D100: LOG | E100: WRM Harian | F100: 2025-6-14 | G100: 0000124491 | I100: -
A101: 528000210 | B101: Muhamad Aldi Agustiana | C101: Mitra Kerja | D101: PROD | E101: Produksi Harian | F101: 2025-7-12 | G101: 0000125766 | I101: -
A102: 528000211 | B102: Seftian Effendi | C102: Mitra Kerja | D102: HRGA | E102: GA Harian | F102: 2025-7-14 | G102: 0000125839 | I102: -
A103: 528000212 | B103: Rizal Fauzi | C103: Mitra Kerja | D103: PROD | E103: Produksi Harian | F103: 2025-7-14 | G103: 0000125840 | I103: -
A104: 528000214 | B104: Dio Juliana | C104: Mitra Kerja | D104: PROD | E104: Produksi Harian | F104: 2025-7-26 | G104: 0000126401 | I104: -
A105: 528000216 | B105: Aidil Akbar | C105: Mitra Kerja | D105: PROD | E105: Produksi Harian
A106: 528000217 | B106: Intan Citra Lestari | C106: Mitra Kerja | D106: PROD | E106: Produksi Harian | F106: 2025-7-26 | G106: 0000126405 | I106: -
A107: 528000218 | B107: Dian Nurfitriyanti | C107: Mitra Kerja | D107: PROD | E107: Produksi Harian | F107: 2025-7-26 | G107: 0000126406 | I107: -
A108: 528000219 | B108: Hamzah Maulana | C108: Mitra Kerja | D108: PROD | E108: Produksi Harian | F108: 2025-7-26 | G108: 0000126407 | I108: -
A109: 528000220 | B109: Riki Sugiana | C109: Mitra Kerja | D109: PROD | E109: Produksi Harian
A110: 528000221 | B110: Indra Hadiyana | C110: Mitra Kerja | D110: HRGA | E110: GA Harian | F110: 2025-7-26 | G110: 0000126408 | I110: -
A111: 528000222 | B111: Fitria Nurainun | C111: Mitra Kerja | D111: PROD | E111: Produksi Harian | F111: 2025-7-26 | G111: 0000126412 | I111: -
A112: 528000223 | B112: Aris Sugiana | C112: Mitra Kerja | D112: PROD | E112: Produksi Harian | F112: 2025-7-26 | G112: 0000126413 | I112: -
A113: 528000224 | B113: Thoriq Waraprada Khoiri | C113: Mitra Kerja | D113: PROD | E113: Produksi Harian | F113: 2025-7-26 | G113: 0000126415 | I113: -
A114: 528000225 | B114: Saepul Rizki | C114: Mitra Kerja | D114: PROD | E114: Produksi Harian | F114: 2025-7-26 | G114: 0000126418 | I114: -
A115: 528000226 | B115: Hamdad Barizi | C115: Mitra Kerja | D115: PROD | E115: Produksi Harian | F115: 2025-7-26 | G115: 0000126420 | I115: -
A116: 528000227 | B116: Deri Gunawan | C116: Mitra Kerja | D116: PROD | E116: Produksi Harian | F116: 2025-7-26 | G116: 0000126423 | I116: -
A117: 528000228 | B117: Banyu Resmi Putri | C117: Mitra Kerja | D117: PROD | E117: Produksi Harian | F117: 2025-7-26 | G117: 0000126425 | I117: -
A118: 528000229 | B118: Naila Ainun Nisa | C118: Mitra Kerja | D118: PROD | E118: Produksi Harian | F118: 2025-7-26 | G118: 0000126427 | I118: -
A119: 528000230 | B119: Siti Juwita Apriliyanti | C119: Mitra Kerja | D119: PROD | E119: Produksi Harian | F119: 2025-7-26 | G119: 0000126429 | I119: -
A120: 528000231 | B120: Hilman Baehaqi | C120: Mitra Kerja | D120: PROD | E120: Produksi Harian | F120: 2025-7-26 | G120: 0000126431 | I120: -
A121: 528000232 | B121: Agung Aji Suhada | C121: Mitra Kerja | D121: LOG | E121: WRM Harian | F121: 2025-7-26 | G121: 0000126432 | I121: -
... A128: 528000239 | B128: Yenni Padilah | C128: Mitra Kerja | D128: PROD | E128: Produksi Harian | F128: 2025-7-26 | G128: 0000126439 | I128: -
A129: 528000240 | B129: Elsandra Cahyana Putri | C129: Mitra Kerja | D129: PROD | E129: Produksi Harian
A130: 528000241 | B130: Balia Nurafif Bilah | C130: Mitra Kerja | D130: PROD | E130: Produksi Harian | F130: 2025-8-18 | G130: 0000127570 | I130: To Be Corrected
A131: 528000242 | B131: Erik Sugiana | C131: Mitra Kerja | D131: HRGA | E131: HRD Vendor | F131: 2025-7-26 | G131: 0000126454 | I131: -
A132: 528000243 | B132: Akmal komaludin | C132: Mitra Kerja | D132: PROD | E132: Produksi Harian
A133: 528000244 | B133: Rodian Rifai | C133: Mitra Kerja | D133: PROD | E133: Produksi Harian | F133: 2025-8-25 | G133: 0000127847 | I133: -
A134: 528000245 | B134: Mutiyana | C134: Mitra Kerja | D134: PROD | E134: Produksi Harian
A135: 528000246 | B135: Shakila Salsa Bila | C135: Mitra Kerja | D135: PROD | E135: Produksi Harian
A136: 528000247 | B136: Sindy Nopita Sari | C136: Mitra Kerja | D136: PROD | E136: Produksi Harian | F136: 2025-8-25 | G136: 0000127842 | I136: -
A137: 528000248 | B137: Roka Jaya Salka Mulya | C137: Mitra Kerja | D137: PROD | E137: Produksi Harian | F137: 2025-8-25 | G137: 0000127855 | I137: To Be Corrected
A138: 528000249 | B138: Fitri Febrian Rasya | C138: Mitra Kerja | D138: PROD | E138: Produksi Harian | F138: 2025-8-25 | G138: 0000127852 | I138: To Be Corrected
A139: 528000250 | B139: Mokhamad Rifki | C139: Mitra Kerja | D139: PROD | E139: Produksi Harian | F139: 2025-8-25 | G139: 0000127857 | I139: To Be Corrected
A140: 528000251 | B140: Salya Nugraha | C140: Mitra Kerja | D140: PROD | E140: Produksi Harian | F140: 2025-8-25 | G140: 0000127856 | I140: To Be Corrected
A141: 528000252 | B141: Adrian Pratama Putra | C141: Mitra Kerja | D141: LOG | E141: WRM Harian | F141: 2025-8-25 | G141: 0000127858 | I141: To Be Corrected
A142: 528000253 | B142: Pawad Sukurillah | C142: Mitra Kerja | D142: PROD | E142: Produksi Harian | F142: 2025-8-25 | G142: 0000127865 | I142: -
A143: 528000254 | B143: M. Difa Ramdani | C143: Mitra Kerja | D143: PROD | E143: Produksi Harian | F143: 2025-8-25 | G143: 0000127886 | I143: -
A144: 528000255 | B144: Muhamad Ezi | C144: Mitra Kerja | D144: PROD | E144: Produksi Harian | F144: 2025-8-25 | G144: 0000127882 | I144: To Be Corrected
A145: 528000256 | B145: Rasianah | C145: Mitra Kerja | D145: PROD | E145: Produksi Harian | F145: 2025-8-25 | G145: 0000127877 | I145: To Be Corrected
A146: 528000257 | B146: Neng Purwanti | C146: Mitra Kerja | D146: PROD | E146: Produksi Harian | F146: 2025-8-25 | G146: 0000127892 | I146: -
A147: 528000258 | B147: Yoga Permana | C147: Mitra Kerja | D147: PROD | E147: Produksi Harian | F147: 2025-8-25 | G147: 0000127896 | I147: To Be Corrected
... A156: 528000268 | B156: Santi Susilawati | C156: Mitra Kerja | D156: PROD | E156: Produksi Harian | F156: 2025-11-3 | G156: 0000131435 | I156: -
A157: 528000269 | B157: Sri Ajeng Juliyanti | C157: Mitra Kerja | D157: PROD | E157: Produksi Harian
A158: 528000270 | B158: Febri Najmudin | C158: Mitra Kerja | D158: LOG | E158: WRM Harian | F158: 2025-11-3 | G158: 0000131437 | I158: -
A159: 528000271 | B159: Fardi Luci | C159: Mitra Kerja | D159: PROD | E159: Produksi Harian
A160: 528000272 | B160: Randi Rahman | C160: Mitra Kerja | D160: PROD | E160: Produksi Harian | F160: 2026-3-7 | G160: 0000136719 | I160: -
A161: 528000273 | B161: Asep Mulyana | C161: Mitra Kerja | D161: PROD | E161: Produksi Harian | F161: 2026-3-7 | G161: 0000136715 | I161: -
A162: 528000274 | B162: Zepri | C162: Mitra Kerja | D162: PROD | E162: Produksi Harian | F162: 2024-10-8 | G162: 0000109078 | I162: -
A163: 528000275 | B163: Muhammad Fikri Al-Bukhori | C163: Mitra Kerja | D163: PROD | E163: Produksi Harian | F163: 2026-3-7 | G163: 0000136713 | I163: -
A164: 528000276 | B164: Fitri Febrian Rasya | C164: Mitra Kerja | D164: PROD | E164: Produksi Harian
A165: 528000277 | B165: Jorgha Febrian Koswata | C165: Mitra Kerja | D165: PROD | E165: Produksi Harian | F165: 2026-3-7 | G165: 0000136714 | I165: -
A166: 528000278 | B166: Ernita Listiana | C166: Mitra Kerja | D166: PROD | E166: Produksi Harian | F166: 2026-3-7 | G166: 0000136718 | I166: -
A167: 528000279 | B167: Mahdalena Dalfa Riani | C167: Mitra Kerja | D167: PROD | E167: Produksi Harian | F167: 2026-3-7 | G167: 0000136717 | I167: -
A168: 528000280 | B168: Dandi Hilman Kelana | C168: Mitra Kerja | D168: PROD | E168: Produksi Harian | F168: 2026-3-7 | G168: 0000136720 | I168: -
A169: 528000281 | B169: Rendi Ramdani | C169: Mitra Kerja | D169: PROD | E169: Produksi Harian | F169: 2026-5-2 | G169: 0000138095 | I169: -
A170: 528000282 | B170: Defa Desfiana | C170: Mitra Kerja | D170: PROD | E170: Produksi Harian | F170: 2026-5-2 | G170: 0000138096 | I170: -
...

Sheet STAFF NON AKTIF
A1: =IFERROR(__xludf.DUMMYFUNCTION("QUERY(IMPORTRANGE(""https://docs.google.com/spreadsheets/d/1FEoklqOOGVEuHVDC9BVeaIu8tA3fqheZAT3eO9syd2Y/edit?gid=380216187#gid=380216187"", ""NON AKTIF!A:AN""), ""SELECT Col1,Col2,Col3,Col23,Col24"")"),"#REF!")

Sheet REGISTRASI SAAT KELUAR PABRIK
A1: NO KARTU MK | B1: NIK | C1: NAMA | D1: TANGGAL | E1: JAM KELUAR | F1: SHIFT | G1: NO LOKER
A2: MK0090 | B2: 528000069 | C2: Jajang Ardiansyah | D2: 46164.417 | E2: 0.43875 | F2: Shift 1
A3: MK00112 | B3: 528000016 | C3: Randi Apriyanto | D3: 46170.417 | E3: 0.59494213 | F3: Shift 1
A4: MK00112 | B4: 528000059 | C4: N. Santika Dewi | D4: 46170.417 | E4: 0.60777778 | F4: Shift 1
A5: MK00126 | B5: 528000052 | C5: Mustopa | D5: 46170.417 | E5: 0.6103588 | F5: Shift 1
A6: MK00093 | B6: 528000090 | C6: Suganda | D6: 46171.417 | E6: 0.25300926 | F6: Shift 3
A7: MK00082 | B7: 528000241 | C7: Balia Nurafif Bilah | D7: 46171.417 | E7: 0.25396991 | F7: Shift 3
A8: MK00136 | B8: 528000274 | C8: Zepri | D8: 46171.417 | E8: 0.2552662 | F8: Shift 3
A9: MK00085 | B9: 528000290 | C9: Eval Pranata | D9: 46171.417 | E9: 0.25560185 | F9: Shift 3
A10: MK00116 | B10: 528000244 | C10: Rodian Rifai | D10: 46171.417 | E10: 0.25616898 | F10: Shift 3
A11: MK00138 | B11: 528000273 | C11: Asep Mulyana | D11: 46171.417 | E11: 0.25662037 | F11: Shift 3
A12: MK00155 | B12: 528000212 | C12: Rizal Fauzi | D12: 46171.417 | E12: 0.27362269 | F12: Shift 3
A13: MK00136 | B13: 528000351 | C13: Mulyana | D13: 46171.417 | E13: 0.54587963 | F13: Shift 1
... A73: MK00109 | B73: 528000262 | C73: Ndari Dwiwanti | D73: 46143.417 | E73: 0.25289352 | F73: Shift 3
A74: MK00154 | B74: 528000052 | C74: Mustopa | D74: 46143.417 | E74: 0.25292824 | F74: Shift 3 | G74: A 10
A75: MK00250 | B75: 528000306 | C75: Windy Olivia | D75: 46143.417 | E75: 0.25299769 | F75: Shift 3
A76: MK00150 | B76: 528000283 | C76: Purwanda Sugiri | D76: 46143.417 | E76: 0.25320602 | F76: Shift 3
A77: MK00126 | B77: 528000266 | C77: M. Syirajatieq | D77: 46143.417 | E77: 0.25326389 | F77: Shift 3
A78: MK00082 | B78: 528000291 | C78: Andrian | D78: 46143.417 | E78: 0.25394676 | F78: Shift 3
A79: MK00156 | B79: 528000195 | C79: Rahma Sariwati | D79: 46143.417 | E79: 0.25416667 | F79: Shift 3
A80: MK00145 | B80: 528000015 | C80: Erwin | D80: 46143.417 | E80: 0.25434028 | F80: Shift 3
A81: MK00056 | B81: 528000301 | C81: Muhammad Mukti Ridwan | D81: 46143.417 | E81: 0.25741898 | F81: Shift 3
A82: MK00118 | B82: 528000228 | C82: Banyu Resmi Putri | D82: 46143.417 | E82: 0.33512731 | F82: Shift 1
A83: MK00155 | B83: 528000298 | C83: Desta Cahaya Pratama | D83: 46143.417 | E83: 0.58533565 | F83: Shift 1
A84: MK00181 | B84: 528000299 | C84: Siti Nurjanah | D84: 46143.417 | E84: 0.58649306 | F84: Shift 1
A85: MK00184 | B85: 528000305 | C85: Puji Puspita | D85: 46143.417 | E85: 0.5866088 | F85: Shift 1
A86: MK00116 | B86: 528000098 | C86: Edi Junaedi | D86: 46143.417 | E86: 0.58679398 | F86: Shift 1
... A100: MK00199 | B100: 528000261 | C100: Ergi Ergianto | D100: 46144.417 | E100: 0.25202546 | F100: Shift 3
A101: MK00085 | B101: 528000052 | C101: Mustopa | D101: 46144.417 | E101: 0.25244213 | F101: Shift 3 | G101: A 10
A102: MK00192 | B102: 528000283 | C102: Purwanda Sugiri | D102: 46144.417 | E102: 0.25263889 | F102: Shift 3
A103: MK00093 | B103: 528000291 | C103: Andrian | D103: 46144.417 | E103: 0.25296296 | F103: Shift 3
A104: MK00205 | B104: 528000301 | C104: Muhammad Mukti Ridwan | D104: 46144.417 | E104: 0.25384259 | F104: Shift 3
A105: MK00154 | B105: 528000203 | C105: Yudha Ramdhan Putra | D105: 46144.417 | E105: 0.33010417 | F105: Shift 3
A106: MK00118 | B106: 528000015 | C106: Erwin | D106: 46144.417 | E106: 0.33042824 | F106: Shift 3
A107: MK528000144 | B107: 528000144 | C107: Jodi Hanafi | D107: 46144.417 | E107: 0.33180556 | F107: Shift 3
A108: MK00150 | B108: 528000144 | C108: Jodi Hanafi | D108: 46144.417 | E108: 0.33418981 | F108: Shift 1
A109: MK0155 | B109: 528000212 | C109: Rizal Fauzi | D109: 46144.417 | E109: 0.56311343 | F109: Shift 1
A110: MK00148 | B110: 528000201 | C110: Zahwa Amelia Choerunissa | D110: 46144.417 | E110: 0.56861111 | F110: Shift 1
A111: MK00113 | B111: 528000099 | C111: Siti Nurawaliah | D111: 46144.417 | E111: 0.57015046 | F111: Shift 1
A112: MK00207 | B112: 528000286 | C112: Imelda Amelia | D112: 46144.417 | E112: 0.57025463 | F112: Shift 1
A113: MK00138 | B113: 528000296 | C113: Nurdin | D113: 46144.417 | E113: 0.57505787 | F113: Shift 1
... A175: MK00155 | B175: 528000301 | C175: Muhammad Mukti Ridwan | D175: 46147.417 | E175: 0.2562037 | F175: Shift 3
A176: 1000210 | B176: 528000069 | C176: Jajang Ardiansyah | D176: 46147.417 | E176: 0.29865741 | F176: Shift 3 | G176: FORCE_RELEASE
A177: MK00210 | B177: 528000069 | C177: Jajang Ardiansyah | D177: 46147.417 | E177: 0.31771991 | F177: Shift 3 | G177: 89
A178: MK00151 | B178: 528000203 | C178: Yudha Ramdhan Putra | D178: 46147.417 | E178: 0.37591435 | F178: Shift 1
A179: MK00181 | B179: 528000286 | C179: Imelda Amelia | D179: 46147.417 | E179: 0.56462963 | F179: Shift 1
A180: MK00246 | B180: 528000212 | C180: Rizal Fauzi | D180: 46147.417 | E180: 0.58070602 | F180: Shift 1
A181: MK00154 | B181: 528000297 | C181: Muhamad Budiana | D181: 46147.417 | E181: 0.58666667 | F181: Shift 1
A182: MK00249 | B182: 528000279 | C182: Mahdalena Dalfa Riani | D182: 46147.417 | E182: 0.58766204 | F182: Shift 1
A183: MK00126 | B183: 628000064 | C183: Silva Alypia | D183: 46147.417 | E183: 0.59043981 | F183: Shift 1
A184: MK00112 | B184: 528000351 | C184: Mulyana | D184: 46147.417 | E184: 0.66712963 | F184: Shift 2
A185: MK00209 | B185: 528000282 | C185: Defa Desfiana | D185: 46147.417 | E185: 0.66744213 | F185: Shift 2 | G185: 23c
A186: MK00155 | B186: 528000265 | C186: Muhammad Haerul Rozikin | D186: 46147.417 | E186: 0.66917824 | F186: Shift 2
A187: MK00192 | B187: 528000287 | C187: Muhamad Angga Ramdani | D187: 46147.417 | E187: 0.66978009 | F187: Shift 2
A188: 128000267 | B188: 528000267 | C188: Bagas Patulloh | D188: 46147.417 | E188: 0.67091435 | F188: Shift 2
A189: MK00109 | B189: 528000349 | C189: Anas Abdul Fatah | D189: 46147.417 | E189: 0.67475694 | F189: Shift 2
A190: MK00046 | B190: 528000232 | C190: Agung Aji Suhada | D190: 46147.417 | E190: 0.71028935 | F190: Shift 2
A191: MA00145 | B191: 528000348 | C191: Saepuloh Ardiansah | D191: 46147.417 | E191: 0.71061343 | F191: Shift 2
A192: MK00118 | B192: 528000274 | C192: Zepri | D192: 46147.417 | E192: 0.91854167 | F192: Shift 2
A193: MK00082 | B193: 528000241 | C193: Balia Nurafif Bilah | D193: 46147.417 | E193: 0.9190162 | F193: Shift 2
A194: MK00116 | B194: 528000290 | C194: Eval Pranata | D194: 46147.417 | E194: 0.91975694 | F194: Shift 2
A195: MK00156 | B195: 528000228 | C195: Banyu Resmi Putri | D195: 46147.417 | E195: 0.92097222 | F195: Shift 2
A196: MK00200 | B196: 528000201 | C196: Zahwa Amelia Choerunissa | D196: 46147.417 | E196: 0.9221412 | F196: Shift 2
A197: MK00181 | B197: 528000286 | C197: Imelda Amelia | D197: 46147.417 | E197: 0.9221875 | F197: Shift 2
A198: MK00136 | B198: 528000099 | C198: Siti Nurawaliah | D198: 46147.417 | E198: 0.9225463 | F198: Shift 2
A199: MK00141 | B199: 528000244 | C199: Rodian Rifai | D199: 46147.417 | E199: 0.92991898 | F199: Shift 2
A200: MK00205 | B200: 528000267 | C200: Bagas Patulloh | D200: 46178.417 | E200: 0.0026967593 | F200: Shift 3
... A237: MK00181 | B237: 528000302 | C237: Henkey gumilar | D237: 46208.417 | E237: 0.25670139 | F237: Shift 3
A238: MK00221 | B238: 628000061 | C238: Nayla Fadillah Exwantoro | D238: 46208.417 | E238: 0.26763889 | F238: Shift 3 | G238: 19E
A239: MK00156 | B239: 528000238 | C239: Indah Lusiana | D239: 46208.417 | E239: 0.57810185 | F239: Shift 1
A240: MK000184 | B240: 528000291 | C240: Andrian | D240: 46208.417 | E240: 0.57927083 | F240: Shift 1
A241: MK00126 | B241: 528000297 | C241: Muhamad Budiana | D241: 46208.417 | E241: 0.58734954 | F241: Shift 1
A242: MK00249 | B242: 528000279 | C242: Mahdalena Dalfa Riani | D242: 46208.417 | E242: 0.58996528 | F242: Shift 1
A243: MK00145 | B243: 528000015 | C243: Erwin | D243: 46208.417 | E243: 0.70670139 | F243: Shift 2
A244: MK00205 | B244: 528000348 | C244: Saepuloh Ardiansah | D244: 46208.417 | E244: 0.73703704 | F244: Shift 2
A245: MK00112 | B245: 528000270 | C245: Febri Najmudin | D245: 46208.417 | E245: 0.90762731 | F245: Shift 2
A246: MK00192 | B246: 528000261 | C246: Ergi Ergianto | D246: 46208.417 | E246: 0.9184838 | F246: Shift 2
A247: MK00155 | B247: 528000262 | C247: Ndari Dwiwanti | D247: 46208.417 | E247: 0.91864583 | F247: Shift 2
A248: MK00141 | B248: 528000195 | C248: Rahma Sariwati | D248: 46208.417 | E248: 0.91914352 | F248: Shift 2
A249: MK00150 | B249: 528000266 | C249: M. Syirajatieq | D249: 46208.417 | E249: 0.91935185 | F249: Shift 2
A250: MK00250 | B250: 528000238 | C250: Indah Lusiana | D250: 46208.417 | E250: 0.91986111 | F250: Shift 2
... A275: MK00186 | B275: 528000149 | C275: Tio Fernanda | D275: 46149.417 | E275: 0.66399306 | F275: Shift 1
A276: MK00181 | B276: 528000282 | C276: Defa Desfiana | D276: 46149.417 | E276: 0.66884259 | F276: Shift 2 | G276: 23c
A277: MK00158 | B277: 528000267 | C277: Bagas Patulloh | D277: 46149.417 | E277: 0.66914352 | F277: Shift 2
A278: MK00154 | B278: 528000351 | C278: Mulyana | D278: 46149.417 | E278: 0.66962963 | F278: Shift 2
A279: MK00136 | B279: 528000287 | C279: Muhamad Angga Ramdani | D279: 46149.417 | E279: 0.6709375 | F279: Shift 2
A280: MK00113 | B280: 528000055 | C280: Dika Prasetya | D280: 46149.417 | E280: 0.67216435 | F280: Shift 2
A281: MK00209 | B281: 528000265 | C281: Muhammad Haerul Rozikin | D281: 46149.417 | E281: 0.67244213 | F281: Shift 2
A282: MK00151 | B282: 528000273 | C282: Asep Mulyana | D282: 46149.417 | E282: 0.67321759 | F282: Shift 2
A283: MK00249 | B283: 528000349 | C283: Anas Abdul Fatah | D283: 46149.417 | E283: 0.67515046 | F283: Shift 2
A284: MK00118 | B284: 528000232 | C284: Agung Aji Suhada | D284: 46149.417 | E284: 0.71127315 | F284: Shift 2
A285: MK00192 | B285: 528000292 | C285: Aditia Nugraha | D285: 46149.417 | E285: 0.71185185 | F285: Shift 2
A286: MK00085 | B286: 528000203 | C286: Yudha Ramdhan Putra | D286: 46149.417 | E286: 0.71229167 | F286: Shift 2
A287: MK00205 | B287: 528000348 | C287: Saepuloh Ardiansah | D287: 46149.417 | E287: 0.87668981 | F287: Shift 2
A288: MK00212 | B288: 528000132 | C288: Giopani | D288: 46149.417 | E288: 0.87806713 | F288: Shift 2
... A309: MK00151 | B309: 528000265 | C309: Muhammad Haerul Rozikin | D309: 46150.417 | E309: 0.66802083 | F309: Shift 2
A310: MK00230 | B310: 528000282 | C310: Defa Desfiana | D310: 46150.417 | E310: 0.66820602 | F310: Shift 2 | G310: 23C
A311: MK00200 | B311: 528000287 | C311: Muhamad Angga Ramdani | D311: 46150.417 | E311: 0.66913194 | F311: Shift 2
A312: MK00141 | B312: 528000055 | C312: Dika Prasetya | D312: 46150.417 | E312: 0.67086806 | F312: Shift 2
A313: MK00112 | B313: 528000273 | C313: Asep Mulyana | D313: 46150.417 | E313: 0.67113426 | F313: Shift 2
...

Sheet ABSEN IN OUT MK
A1: TANGGAL | B1: NIK | C1: NAMA | D1: DEPARTEMEN | E1: JABATAN | F1: JAM MASUK | G1: JAM KELUAR | H1: STATUS | I1: NO KARTU MK | J1: NO LOKER
A2: 07/03/2026 | B2: 528000052 | C2: Mustopa | D2: PROD | E2: Produksi Harian | F2: 21:05:27 | H2: DI DALAM | I2: MK00154
A3: 07/03/2026 | B3: 528000262 | C3: Ndari Dwiwanti | D3: PROD | E3: Produksi Harian | F3: 21:47:19 | H3: DI DALAM | I3: MK00088
A4: 07/03/2026 | B4: 528000283 | C4: Purwanda Sugiri | D4: LOG | E4: WRM Harian | F4: 21:53:45 | H4: DI DALAM | I4: MK00218
A5: 07/03/2026 | B5: 528000291 | C5: Andrian | D5: PROD | E5: Produksi Harian | F5: 21:53:13 | H5: DI DALAM | I5: MK00249
A6: 07/03/2026 | B6: 528000323 | C6: Dian Hamidah | D6: PROD | E6: Produksi Harian | F6: 21:42:05 | H6: DI DALAM | I6: MK00181
A7: 07/03/2026 | B7: 528000336 | C7: Ali Nurhanafi | D7: PROD | E7: Produksi Harian | F7: 21:03:29 | H7: DI DALAM | I7: MK00185
A8: 07/03/2026 | B8: 528000358 | C8: Lulu Agustin | D8: PROD | E8: Produksi Harian | F8: 21:46:43 | H8: DI DALAM | I8: MK00235
A9: 07/03/2026 | B9: 528000360 | C9: Hendra Permana | D9: ENG | E9: Engineering Harian | F9: 21:54:40 | H9: DI DALAM | I9: MK00208 | J9: 8E
A10: 08/03/2026 | B10: 528000040 | C10: Agus Suryaman | D10: PROD | E10: Produksi Harian | F10: 08:51:01 | G10: 22:12:34 | H10: SELESAI | I10: MK00141
A11: 08/03/2026 | B11: 528000052 | C11: Mustopa | D11: PROD | E11: Produksi Harian | G11: 21:04:56 | H11: KELUAR TANPA MASUK | I11: MK00160
A12: 08/03/2026 | B12: 528000090 | C12: Suganda | D12: PROD | E12: Produksi Harian | F12: 13:53:31 | G12: 22:04:42 | H12: SELESAI | I12: MK00250
A13: 08/03/2026 | B13: 528000144 | C13: Jodi Hanafi | D13: LOG | E13: WRM Harian | F13: 15:50:17 | G13: 15:49:57 | H13: SELESAI | I13: MK00221
A14: 08/03/2026 | B14: 528000149 | C14: Tio Fernanda | D14: LOG | E14: WRM Harian | F14: 15:50:30 | H14: DI DALAM | I14: MK0130
A15: 08/03/2026 | B15: 528000201 | C15: Zahwa Amelia Choerunissa | D15: PROD | E15: Produksi Harian | F15: 13:42:00 | G15: 22:04:08 | H15: SELESAI | I15: MK00192
A16: 08/03/2026 | B16: 528000212 | C16: Rizal Fauzi | D16: PROD | E16: Produksi Harian | F16: 14:00:49 | H16: DI DALAM | I16: MK00156
A17: 08/03/2026 | B17: 528000232 | C17: Agung Aji Suhada | D17: LOG | E17: WRM Harian | F17: 08:40:25 | G17: 17:13:43 | H17: SELESAI | I17: MK00150
A18: 08/03/2026 | B18: 528000241 | C18: Balia Nurafif Bilah | D18: PROD | E18: Produksi Harian | F18: 13:54:59 | G18: 22:04:03 | H18: SELESAI | I18: MK00217
A19: 08/03/2026 | B19: 528000261 | C19: Ergi Ergianto | D19: HRGA | E19: GA Harian | G19: 08:04:03 | H19: KELUAR TANPA MASUK | I19: MK00202
A20: 08/03/2026 | B20: 528000262 | C20: Ndari Dwiwanti | D20: PROD | E20: Produksi Harian | G20: 21:46:59 | H20: KELUAR TANPA MASUK | I20: MK00113
A21: 08/03/2026 | B21: 528000265 | C21: Muhammad Haerul Rozikin | D21: LOG | E21: WRM Harian | G21: 16:05:06 | H21: KELUAR TANPA MASUK | I21: MK00154
A22: 08/03/2026 | B22: 528000267 | C22: Bagas Patulloh | D22: LOG | E22: WRM Harian | F22: 08:03:42 | G22: 17:46:36 | H22: SELESAI | I22: MK00093
A23: 08/03/2026 | B23: 528000273 | C23: Asep Mulyana | D23: PROD | E23: Produksi Harian | F23: 13:50:06 | G23: 22:01:43 | H23: SELESAI | I23: MK00116
A24: 08/03/2026 | B24: 528000274 | C24: Zepri | D24: PROD | E24: Produksi Harian | F24: 13:55:07 | G24: 22:03:22 | H24: SELESAI | I24: MK00008
A25: 08/03/2026 | B25: 528000279 | C25: Mahdalena Dalfa Riani | D25: PROD | E25: Produksi Harian | G25: 14:07:32 | H25: KELUAR TANPA MASUK | I25: MK00208
A26: 08/03/2026 | B26: 528000282 | C26: Defa Desfiana | D26: PROD | E26: Produksi Harian | G26: 16:01:50 | H26: KELUAR TANPA MASUK | I26: MK00210 | J26: 32c
A27: 08/03/2026 | B27: 528000286 | C27: Imelda Amelia | D27: PROD | E27: Produksi Harian | F27: 13:43:02 | G27: 22:08:26 | H27: SELESAI | I27: MK00230
A28: 08/03/2026 | B28: 528000289 | C28: Adit Supriyadi | D28: PROD | E28: Produksi Harian | F28: 13:45:13 | H28: DI DALAM | I28: MK00145
A29: 08/03/2026 | B29: 528000290 | C29: Eval Pranata | D29: PROD | E29: Produksi Harian | F29: 13:59:53 | G29: 22:04:49 | H29: SELESAI | I29: MK00109
A30: 08/03/2026 | B30: 528000291 | C30: Andrian | D30: PROD | E30: Produksi Harian | G30: 21:45:50 | H30: KELUAR TANPA MASUK | I30: MK00082
A31: 08/03/2026 | B31: 528000300 | C31: Lia pitaloka | D31: PROD | E31: Produksi Harian | G31: 14:06:53 | H31: KELUAR TANPA MASUK | I31: MK00138
A32: 08/03/2026 | B32: 528000310 | C32: Fachrul Rozzi Suryana | D32: LOG | E32: WRM Harian | F32: 07:54:31 | G32: 16:04:00 | H32: SELESAI | I32: MK00181 | J32: 33E
A33: 08/03/2026 | B33: 528000335 | C33: Rizal Saepuloh | D33: LOG | E33: WRM Harian | F33: 16:03:11 | H33: DI DALAM | I33: MK00204
A34: 08/03/2026 | B34: 528000337 | C34: Ahmad Zaldi Firdaus | D34: PROD | E34: Produksi Harian | F34: 20:49:51 | H34: DI DALAM | I34: MK00209
A35: 08/03/2026 | B35: 528000339 | C35: Muhamad Ripai'i | D35: HRGA | E35: GA Harian | F35: 13:42:41 | G35: 22:40:20 | H35: SELESAI | I35: MK00136
A36: 08/03/2026 | B36: 528000348 | C36: Saepuloh Ardiansah | D36: LOG | E36: WRM Harian | F36: 08:55:10 | G36: 22:11:19 | H36: SELESAI | I36: MK00205
A37: 08/03/2026 | B37: 528000349 | C37: Anas Abdul Fatah | D37: LOG | E37: WFG Harian | F37: 09:47:06 | G37: 18:16:40 | H37: SELESAI | I37: MK00185
A38: 08/03/2026 | B38: 528000351 | C38: Mulyana | D38: PROD | E38: Produksi Harian | F38: 07:51:45 | G38: 16:03:06 | H38: SELESAI | I38: MK00209
A39: 08/03/2026 | B39: 528000358 | C39: Lulu Agustin | D39: PROD | E39: Produksi Harian | G39: 08:05:13 | H39: KELUAR TANPA MASUK | I39: MK00213
A40: 08/03/2026 | B40: 628000064 | C40: Silva Alypia | D40: PROD | E40: Produksi Borongan | G40: 14:05:15 | H40: KELUAR TANPA MASUK | I40: MK00108
A41: 07/04/2026 | B41: 528000015 | C41: Erwin | D41: LOG | E41: WRM Harian | F41: 21:41:35 | H41: DI DALAM | I41: MK00213
A42: 07/04/2026 | B42: 528000052 | C42: Mustopa | D42: PROD | E42: Produksi Harian | G42: 06:06:03 | H42: KELUAR TANPA MASUK | I42: MK00154
A43: 07/04/2026 | B43: 528000144 | C43: Jodi Hanafi | D43: LOG | E43: WRM Harian | G43: 00:04:01 | H43: KELUAR TANPA MASUK | I43: MK00221
A44: 07/04/2026 | B44: 528000149 | C44: Tio Fernanda | D44: LOG | E44: WRM Harian | G44: 00:03:41 | H44: KELUAR TANPA MASUK | I44: MK0130
A45: 07/04/2026 | B45: 528000212 | C45: Rizal Fauzi | D45: PROD | E45: Produksi Harian | G45: 02:09:04 | H45: KELUAR TANPA MASUK | I45: MK00156
A46: 07/04/2026 | B46: 528000262 | C46: Ndari Dwiwanti | D46: PROD | E46: Produksi Harian | G46: 06:05:15 | H46: KELUAR TANPA MASUK | I46: MK00088
A47: 07/04/2026 | B47: 528000283 | C47: Purwanda Sugiri | D47: LOG | E47: WRM Harian | G47: 06:05:09 | H47: KELUAR TANPA MASUK | I47: MK00218
A48: 07/04/2026 | B48: 528000289 | C48: Adit Supriyadi | D48: PROD | E48: Produksi Harian | G48: 05:59:00 | H48: KELUAR TANPA MASUK | I48: MK00145
A49: 07/04/2026 | B49: 528000291 | C49: Andrian | D49: PROD | E49: Produksi Harian | G49: 06:04:42 | H49: KELUAR TANPA MASUK | I49: MK00249
A50: 07/04/2026 | B50: 528000298 | C50: Desta Cahaya Pratama | D50: PROD | E50: Produksi Harian | F50: 21:43:14 | H50: DI DALAM | I50: MK00235
A51: 07/04/2026 | B51: 528000299 | C51: Siti Nurjanah | D51: PROD | E51: Produksi Harian | F51: 21:42:35 | H51: DI DALAM | I51: MK00209
A52: 07/04/2026 | B52: 528000302 | C52: Henkey gumilar | D52: PROD | E52: Produksi Harian | F52: 21:57:23 | H52: DI DALAM | I52: MK00095
A53: 07/04/2026 | B53: 528000305 | C53: Puji Puspita | D53: PROD | E53: Produksi Harian | F53: 21:34:25 | H53: DI DALAM | I53: MK00108
A54: 07/04/2026 | B54: 528000309 | C54: Ilham Ramadhan | D54: LOG | E54: WRM Harian | F54: 21:32:55 | H54: DI DALAM | I54: MK00145
A55: 07/04/2026 | B55: 528000313 | C55: Muhamad Rifki | D55: PROD | E55: Produksi Harian | F55: 21:45:18 | H55: DI DALAM | I55: MK00185
A56: 07/04/2026 | B56: 528000318 | C56: Bayu Padli Sepriyana | D56: LOG | E56: WRM Harian | F56: 21:38:49 | H56: DI DALAM | I56: MK00230
A57: 07/04/2026 | B57: 528000323 | C57: Dian Hamidah | D57: PROD | E57: Produksi Harian | G57: 06:07:06 | H57: KELUAR TANPA MASUK | I57: MK00181
A58: 07/04/2026 | B58: 528000335 | C58: Rizal Saepuloh | D58: LOG | E58: WRM Harian | G58: 00:00:15 | H58: KELUAR TANPA MASUK | I58: MK00204
A59: 07/04/2026 | B59: 528000336 | C59: Ali Nurhanafi | D59: PROD | E59: Produksi Harian | G59: 06:07:44 | H59: KELUAR TANPA MASUK | I59: MK00185
A60: 07/04/2026 | B60: 528000337 | C60: Ahmad Zaldi Firdaus | D60: PROD | E60: Produksi Harian | G60: 06:08:22 | H60: KELUAR TANPA MASUK | I60: MK00209
A61: 07/04/2026 | B61: 528000340 | C61: Muhammad Wildan Adithya | D61: PROD | E61: Produksi Harian | F61: 21:03:01 | H61: DI DALAM | I61: MK00220
A62: 07/04/2026 | B62: 528000358 | C62: Lulu Agustin | D62: PROD | E62: Produksi Harian | G62: 06:05:44 | H62: KELUAR TANPA MASUK | I62: MK00235
A63: 07/04/2026 | B63: 528000360 | C63: Hendra Permana | D63: ENG | E63: Engineering Harian | G63: 06:04:38 | H63: KELUAR TANPA MASUK | I63: MK00208 | J63: 8E
A64: 07/04/2026 | B64: 528000361 | C64: Denada Munggarani | D64: PROD | E64: Produksi Harian | F64: 21:30:07 | H64: DI DALAM | I64: MK00109
A65: 07/04/2026 | B65: 628000091 | C65: Devita Handayani | D65: PROD | E65: Produksi Borongan | F65: 21:33:44 | H65: DI DALAM | I65: MK00138
A66: 08/04/2026 | B66: 528000015 | C66: Erwin | D66: LOG | E66: WRM Harian | G66: 21:41:05 | H66: KELUAR TANPA MASUK | I66: MK00123
A67: 08/04/2026 | B67: 528000040 | C67: Agus Suryaman | D67: PROD | E67: Produksi Harian | F67: 08:21:06 | G67: 17:04:58 | H67: SELESAI | I67: MK00141
A68: 08/04/2026 | B68: 528000090 | C68: Suganda | D68: PROD | E68: Produksi Harian | F68: 13:54:55 | G68: 22:06:08 | H68: SELESAI | I68: MK00184
A69: 08/04/2026 | B69: 528000144 | C69: Jodi Hanafi | D69: LOG | E69: WRM Harian | F69: 15:41:22 | H69: DI DALAM | I69: MK00221
A70: 08/04/2026 | B70: 528000201 | C70: Zahwa Amelia Choerunissa | D70: PROD | E70: Produksi Harian | F70: 13:39:36 | G70: 22:02:28 | H70: SELESAI | I70: MK00136
A71: 08/04/2026 | B71: 528000212 | C71: Rizal Fauzi | D71: PROD | E71: Produksi Harian | F71: 14:00:06 | H71: DI DALAM | I71: MK00154
A72: 08/04/2026 | B72: 528000228 | C72: Banyu Resmi Putri | D72: PROD | E72: Produksi Harian | F72: 13:41:27 | G72: 22:03:46 | H72: SELESAI | I72: MK00212
A73: 08/04/2026 | B73: 528000232 | C73: Agung Aji Suhada | D73: LOG | E73: WRM Harian | F73: 08:38:47 | H73: DI DALAM | I73: MK00150
A74: 08/04/2026 | B74: 528000265 | C74: Muhammad Haerul Rozikin | D74: LOG | E74: WRM Harian | F74: 05:56:50 | G74: 14:04:13 | H74: SELESAI | I74: MK00192
A75: 08/04/2026 | B75: 528000267 | C75: Bagas Patulloh | D75: LOG | E75: WRM Harian | F75: 08:00:34 | G75: 17:13:36 | H75: SELESAI | I75: MK00093
A76: 08/04/2026 | B76: 528000273 | C76: Asep Mulyana | D76: PROD | E76: Produksi Harian | F76: 13:52:24 | G76: 22:00:37 | H76: SELESAI | I76: MK00085
A77: 08/04/2026 | B77: 528000279 | C77: Mahdalena Dalfa Riani | D77: PROD | E77: Produksi Harian | F77: 06:00:12 | G77: 14:06:35 | H77: SELESAI | I77: MK00145
A78: 08/04/2026 | B78: 528000282 | C78: Defa Desfiana | D78: PROD | E78: Produksi Harian | F78: 05:44:52 | G78: 14:10:15 | H78: SELESAI | I78: MK00108 | J78: 4b
A79: 08/04/2026 | B79: 528000286 | C79: Imelda Amelia | D79: PROD | E79: Produksi Harian | F79: 13:40:29 | G79: 22:05:59 | H79: SELESAI | I79: MK00143
A80: 08/04/2026 | B80: 528000288 | C80: Dede gunawan | D80: PROD | E80: Produksi Harian | F80: 09:47:48 | G80: 09:46:54 | H80: SELESAI | I80: MK00250
A81: 08/04/2026 | B81: 528000289 | C81: Adit Supriyadi | D81: PROD | E81: Produksi Harian | F81: 13:50:32 | G81: 22:03:14 | H81: SELESAI | I81: MK00186
A82: 08/04/2026 | B82: 528000290 | C82: Eval Pranata | D82: PROD | E82: Produksi Harian | F82: 13:59:17 | G82: 22:05:55 | H82: SELESAI | I82: MK00181
A83: 08/04/2026 | B83: 528000300 | C83: Lia pitaloka | D83: PROD | E83: Produksi Harian | F83: 05:57:54 | G83: 09:16:36 | H83: SELESAI | I83: MK00250
A84: 08/04/2026 | B84: 528000309 | C84: Ilham Ramadhan | D84: LOG | E84: WRM Harian | G84: 21:40:16 | H84: KELUAR TANPA MASUK | I84: MK00145
A85: 08/04/2026 | B85: 528000310 | C85: Fachrul Rozzi Suryana | D85: LOG | E85: WRM Harian | F85: 06:02:34 | G85: 14:04:03 | H85: SELESAI | I85: MK00095
A86: 08/04/2026 | B86: 528000335 | C86: Rizal Saepuloh | D86: LOG | E86: WRM Harian | F86: 16:04:01 | H86: DI DALAM | I86: MK00204
A87: 08/04/2026 | B87: 528000339 | C87: Muhamad Ripai'i | D87: HRGA | E87: GA Harian | F87: 13:12:54 | G87: 22:43:24 | H87: SELESAI | I87: MK00208
A88: 08/04/2026 | B88: 528000348 | C88: Saepuloh Ardiansah | D88: LOG | E88: WRM Harian | F88: 08:28:29 | G88: 19:37:30 | H88: SELESAI | I88: MK00205
A89: 08/04/2026 | B89: 528000349 | C89: Anas Abdul Fatah | D89: LOG | E89: WFG Harian | F89: 09:43:07 | G89: 18:11:49 | H89: SELESAI | I89: MK00213
A90: 08/04/2026 | B90: 528000351 | C90: Mulyana | D90: PROD | E90: Produksi Harian | F90: 07:54:53 | G90: 16:00:46 | H90: SELESAI | I90: MK00218
A91: 08/04/2026 | B91: 528000359 | C91: M. Iqbal Maulana. S | D91: LOG | E91: WRM Harian | F91: 13:55:23 | G91: 22:04:57 | H91: SELESAI | I91: MK00008
A92: 08/04/2026 | B92: 628000064 | C92: Silva Alypia | D92: PROD | E92: Produksi Borongan | F92: 05:49:42 | G92: 14:05:42 | H92: SELESAI | I92: MK00109
A93: 29/04/2026 | B93: 528000015 | C93: Erwin | D93: LOG | E93: WRM Harian | F93: 21:57:36 | H93: DI DALAM | I93: MK00145
A94: 29/04/2026 | B94: 528000052 | C94: Mustopa | D94: PROD | E94: Produksi Harian | F94: 21:12:14 | G94: 06:04:29 | H94: SELESAI | I94: MK00154
A95: 29/04/2026 | B95: 528000195 | C95: Rahma Sariwati | D95: PROD | E95: Produksi Harian | F95: 21:43:39 | H95: DI DALAM | I95: MK00156
A96: 29/04/2026 | B96: 528000201 | C96: Zahwa Amelia Choerunissa | D96: PROD | E96: Produksi Harian | G96: 05:49:11 | H96: KELUAR TANPA MASUK | I96: MK00156
A97: 29/04/2026 | B97: 528000261 | C97: Ergi Ergianto | D97: HRGA | E97: GA Harian | F97: 21:52:43 | G97: 06:03:53 | H97: SELESAI | I97: MK00158
A98: 29/04/2026 | B98: 528000262 | C98: Ndari Dwiwanti | D98: PROD | E98: Produksi Harian | F98: 21:36:09 | G98: 06:09:14 | H98: SELESAI | I98: MK00109
A99: 29/04/2026 | B99: 528000266 | C99: M. Syirajatieq | D99: LOG | E99: WFG Harian | F99: 21:36:47 | G99: 06:02:23 | H99: SELESAI | I99: MK00126
A100: 29/04/2026 | B100: 528000283 | C100: Purwanda Sugiri | D100: LOG | E100: WRM Harian | F100: 21:54:42 | G100: 06:05:09 | H100: SELESAI | I100: MK00150
...

Sheet REGISTRASI MASUK KELUAR AREA KE
A1: NO KARTU MK | B1: INOUT | C1: TANGGAL | D1: JAM CATAT | E1: NIK | F1: NAMA | G1: TUJUAN | H1: CATATAN
G2: TOILET
G3: ISTRIHAHAT
G4: SHOLAT
G5: KLINIK
A6: MK00160 | B6: IN | C6: 46166.417 | D6: 0.71859954 | E6: 628000039 | F6: Nani Maryani | G6: HRD & GA
A7: MK00160 | B7: OUT | C7: 46166.417 | D7: 0.71930556 | E7: 628000039 | F7: Nani Maryani | G7: HRD & GA
A8: MK00160 | B8: IN | C8: 46166.417 | D8: 0.71960648 | E8: 628000039 | F8: Nani Maryani | G8: HRD & GA | H8: Toilet
A9: MK00112 | B9: IN | C9: 46170.417 | D9: 0.59342593 | E9: 528000016 | F9: Randi Apriyanto | G9: LOG
A10: MK00154 | B10: IN | C10: 46196.417 | D10: 0.63871528 | E10: 528000290 | F10: Eval Pranata | G10: Produksi | H10: Istirahat
A11: MK00154 | B11: OUT | C11: 46196.417 | D11: 0.63952546 | E11: 528000290 | F11: Eval Pranata | G11: Produksi | H11: Pekerjaan
A12: MK00154 | B12: IN | C12: 46196.417 | D12: 0.64038194 | E12: 528000290 | F12: Eval Pranata | G12: Produksi | H12: Pekerjaan
A13: MK00154 | B13: OUT | C13: 46196.417 | D13: 0.64390046 | E13: 528000290 | F13: Eval Pranata | G13: Produksi | H13: Toilet
A14: MK00154 | B14: IN | C14: 46196.417 | D14: 0.6446412 | E14: 528000290 | F14: Eval Pranata | G14: Produksi | H14: Pekerjaan
A15: MK00154 | B15: OUT | C15: 46196.417 | D15: 0.67167824 | E15: 528000290 | F15: Eval Pranata | G15: Produksi | H15: Sholat
A16: 428000104 | B16: IN | C16: 46196.417 | D16: 0.67827546 | E16: 428000104 | F16: BELLA NURLAILLA. AP | G16: Produksi
A17: MK00154 | B17: IN | C17: 46196.417 | D17: 0.68052083 | E17: 528000290 | F17: Eval Pranata | G17: Produksi | H17: Pekerjaan
A18: MK00154 | B18: OUT | C18: 46196.417 | D18: 0.69427083 | E18: 528000290 | F18: Eval Pranata | G18: Produksi | H18: Istirahat
A19: MK00150 | B19: IN | C19: 46196.417 | D19: 0.70960648 | E19: 528000241 | F19: Balia Nurafif Bilah | G19: Produksi | H19: Istirahat
A20: MK00150 | B20: OUT | C20: 46196.417 | D20: 0.71211806 | E20: 528000241 | F20: Balia Nurafif Bilah | G20: Produksi | H20: Istirahat
A21: MK00154 | B21: IN | C21: 46196.417 | D21: 0.71565972 | E21: 528000290 | F21: Eval Pranata | G21: Produksi | H21: Pekerjaan
A22: MK00150 | B22: IN | C22: 46196.417 | D22: 0.73483796 | E22: 528000241 | F22: Balia Nurafif Bilah | G22: Produksi | H22: Pekerjaan
A23: MK00192 | B23: IN | C23: 46196.417 | D23: 0.77207176 | E23: 528000099 | F23: Siti Nurawaliah | G23: Produksi | H23: Istirahat
A24: MK00192 | B24: OUT | C24: 46196.417 | D24: 0.77234954 | E24: 528000099 | F24: Siti Nurawaliah | G24: Produksi | H24: Istirahat
A25: MK00154 | B25: OUT | C25: 46196.417 | D25: 0.77336806 | E25: 528000290 | F25: Eval Pranata | G25: Produksi | H25: Sholat
A26: MK00154 | B26: IN | C26: 46196.417 | D26: 0.78018519 | E26: 528000290 | F26: Eval Pranata | G26: Produksi | H26: Pekerjaan
A27: MK00203 | B27: IN | C27: 46196.417 | D27: 0.78725694 | E27: 528000286 | F27: Imelda Amelia | G27: Produksi | H27: Istirahat
A28: MK00203 | B28: OUT | C28: 46196.417 | D28: 0.78743056 | E28: 528000286 | F28: Imelda Amelia | G28: Produksi | H28: Istirahat
... A73: MK00126 | B73: OUT | C73: 46197.417 | D73: 0.44258102 | E73: 528000254 | F73: M. Difa Ramdani | G73: Produksi | H73: Istirahat
A74: MK00126 | B74: IN | C74: 46197.417 | D74: 0.46815972 | E74: 528000254 | F74: M. Difa Ramdani | G74: Produksi
A75: MK00141 | B75: OUT | C75: 46197.417 | D75: 0.48946759 | E75: 528000265 | F75: Muhammad Haerul Rozikin | G75: Produksi
A76: MK00208 | B76: OUT | C76: 46197.417 | D76: 0.50460648 | E76: 528000282 | F76: Defa Desfiana | G76: Produksi
A77: MK00126 | B77: OUT | C77: 46197.417 | D77: 0.52984954 | E77: 528000254 | F77: M. Difa Ramdani | G77: Produksi
A78: MK00158 | B78: IN | C78: 46197.417 | D78: 0.53157407 | E78: 628000064 | F78: Silva Alypia | G78: Produksi
A79: MK00158 | B79: OUT | C79: 46197.417 | D79: 0.53180556 | E79: 628000064 | F79: Silva Alypia | G79: Produksi | H79: Sholat
A80: MK00230 | B80: IN | C80: 46197.417 | D80: 0.53221065 | E80: 528000279 | F80: Mahdalena Dalfa Riani | G80: Produksi | H80: Sholat
A81: MK00230 | B81: OUT | C81: 46197.417 | D81: 0.53240741 | E81: 528000279 | F81: Mahdalena Dalfa Riani | G81: Produksi | H81: Sholat
A82: MK00126 | B82: IN | C82: 46197.417 | D82: 0.53696759 | E82: 528000254 | F82: M. Difa Ramdani | G82: Produksi | H82: Sholat
A83: MK00230 | B83: IN | C83: 46197.417 | D83: 0.53890046 | E83: 528000279 | F83: Mahdalena Dalfa Riani | G83: Produksi | H83: Sholat
A84: MK00158 | B84: IN | C84: 46197.417 | D84: 0.53924769 | E84: 628000064 | F84: Silva Alypia | G84: Produksi | H84: Sholat
A85: MK00154 | B85: OUT | C85: 46197.417 | D85: 0.68101852 | E85: 528000201 | F85: Zahwa Amelia Choerunissa | G85: Produksi
A86: MK00154 | B86: IN | C86: 46197.417 | D86: 0.68650463 | E86: 528000201 | F86: Zahwa Amelia Choerunissa | G86: Produksi
A87: 328000589 | B87: IN | C87: 46197.417 | D87: 0.6878588 | E87: 328000589 | F87: DEA PERMATASARI | G87: Produksi
A88: MK00093 | B88: IN | C88: 46197.417 | D88: 0.7180787 | E88: 528000090 | F88: Suganda | G88: Produksi | H88: Istirahat
A89: MK00093 | B89: OUT | C89: 46197.417 | D89: 0.71850694 | E89: 528000090 | F89: Suganda | G89: Produksi | H89: Istirahat
A90: MK00250 | B90: IN | C90: 46197.417 | D90: 0.72314815 | E90: 528000274 | F90: Zepri | G90: Produksi | H90: Istirahat
A91: MK00250 | B91: OUT | C91: 46197.417 | D91: 0.72337963 | E91: 528000274 | F91: Zepri | G91: Produksi | H91: Istirahat
A92: MK00213 | B92: OUT | C92: 46197.417 | D92: 0.72413194 | E92: 528000290 | F92: Eval Pranata | G92: Produksi | H92: Istirahat
A93: MK00202 | B93: OUT | C93: 46197.417 | D93: 0.72489583 | E93: 528000241 | F93: Balia Nurafif Bilah | G93: Produksi | H93: Istirahat
A94: MK00093 | B94: IN | C94: 46197.417 | D94: 0.74486111 | E94: 528000090 | F94: Suganda | G94: Produksi
A95: MK00250 | B95: IN | C95: 46197.417 | D95: 0.74668981 | E95: 528000274 | F95: Zepri | G95: Produksi
A96: MK00213 | B96: IN | C96: 46197.417 | D96: 0.74704861 | E96: 528000290 | F96: Eval Pranata | G96: Produksi
A97: MK00202 | B97: IN | C97: 46197.417 | D97: 0.74865741 | E97: 528000241 | F97: Balia Nurafif Bilah | G97: Produksi
A98: MK00090 | B98: OUT | C98: 46197.417 | D98: 0.75795139 | E98: 528000099 | F98: Siti Nurawaliah | G98: Produksi
A99: MK00181 | B99: IN | C99: 46197.417 | D99: 0.76239583 | E99: 528000299 | F99: Siti Nurjanah | G99: Produksi
A100: MK00235 | B100: OUT | C100: 46197.417 | D100: 0.77071759 | E100: 528000286 | F100: Imelda Amelia | G100: Produksi
A101: MK00154 | B101: OUT | C101: 46197.417 | D101: 0.77456019 | E101: 528000201 | F101: Zahwa Amelia Choerunissa | G101: Produksi
A102: MK00181 | B102: OUT | C102: 46197.417 | D102: 0.77929398 | E102: 528000299 | F102: Siti Nurjanah | G102: Produksi
A103: MK00090 | B103: IN | C103: 46197.417 | D103: 0.77949074 | E103: 528000099 | F103: Siti Nurawaliah | G103: Produksi
A104: MK00181 | B104: IN | C104: 46197.417 | D104: 0.77981481 | E104: 528000299 | F104: Siti Nurjanah | G104: Produksi
A105: MK00235 | B105: IN | C105: 46197.417 | D105: 0.79259259 | E105: 528000286 | F105: Imelda Amelia | G105: Produksi
... A107: MK00235 | B107: OUT | C107: 46197.417 | D107: 0.79998843 | E107: 528000286 | F107: Imelda Amelia | G107: Produksi
A108: MK00235 | B108: OUT | C108: 46197.417 | D108: 0.80087963 | E108: 528000286 | F108: Imelda Amelia | G108: Produksi | H108: Pekerjaan
A109: MK00235 | B109: IN | C109: 46197.417 | D109: 0.8028588 | E109: 528000286 | F109: Imelda Amelia | G109: Produksi | H109: Toilet
A110: MK00235 | B110: OUT | C110: 46197.417 | D110: 0.80362269 | E110: 528000286 | F110: Imelda Amelia | G110: Produksi | H110: Pekerjaan
A111: MK00085 | B111: OUT | C111: 46197.417 | D111: 0.82208333 | E111: 528000244 | F111: Rodian Rifai | G111: Produksi | H111: Pekerjaan
A112: MK00085 | B112: IN | C112: 46197.417 | D112: 0.84689815 | E112: 528000244 | F112: Rodian Rifai | G112: Produksi | H112: Pekerjaan
A113: MK00093 | B113: OUT | C113: 46197.417 | D113: 0.88612269 | E113: 528000090 | F113: Suganda | G113: Produksi | H113: Toilet
A114: MK00093 | B114: IN | C114: 46197.417 | D114: 0.88663194 | E114: 528000090 | F114: Suganda | G114: Produksi | H114: Pekerjaan
A115: MK00134 | B115: IN | C115: 46198.417 | D115: 0.010960648 | E115: 528000203 | F115: Yudha Ramdhan Putra | G115: Produksi | H115: Toilet
A116: MK00203 | B116: OUT | C116: 46198.417 | D116: 0.025891204 | E116: 528000302 | F116: Henkey gumilar | G116: Produksi | H116: Istirahat
A117: MK00203 | B117: IN | C117: 46198.417 | D117: 0.050983796 | E117: 528000302 | F117: Henkey gumilar | G117: Produksi | H117: Pekerjaan
A118: MK00230 | B118: OUT | C118: 46198.417 | D118: 0.052407407 | E118: 528000299 | F118: Siti Nurjanah | G118: Produksi | H118: Istirahat
A119: MK00221 | B119: IN | C119: 46198.417 | D119: 0.058668981 | E119: 628000061 | F119: Nayla Fadillah Exwantoro | G119: Produksi | H119: Istirahat
... A124: MK00221 | B124: IN | C124: 46198.417 | D124: 0.080034722 | E124: 628000061 | F124: Nayla Fadillah Exwantoro | G124: Produksi | H124: Pekerjaan
A125: MK00154 | B125: OUT | C125: 46198.417 | D125: 0.35578704 | E125: 628000064 | F125: Silva Alypia | G125: Produksi
A126: MK00154 | B126: IN | C126: 46198.417 | D126: 0.35774306 | E126: 628000064 | F126: Silva Alypia | G126: Produksi | H126: Toilet
A127: MK00221 | B127: OUT | C127: 46198.417 | D127: 0.39207176 | E127: 528000090 | F127: Suganda | G127: Produksi
A128: MK00221 | B128: IN | C128: 46198.417 | D128: 0.39293981 | E128: 528000090 | F128: Suganda | G128: Produksi | H128: Pekerjaan
A129: 328000540 | B129: IN | C129: 46198.417 | D129: 0.39509259 | E129: 328000540 | F129: RAJESTY SUCIPTA MAHESA DWI | G129: Produksi | H129: Toilet
A130: MK00221 | B130: OUT | C130: 46198.417 | D130: 0.40341435 | E130: 528000090 | F130: Suganda | G130: Produksi | H130: Pekerjaan
A131: MK00221 | B131: IN | C131: 46198.417 | D131: 0.40482639 | E131: 528000090 | F131: Suganda | G131: Produksi | H131: Istirahat
A132: MK00221 | B132: OUT | C132: 46198.417 | D132: 0.40510417 | E132: 528000090 | F132: Suganda | G132: Produksi | H132: Istirahat
A133: MK00221 | B133: IN | C133: 46198.417 | D133: 0.40555556 | E133: 528000090 | F133: Suganda | G133: Produksi | H133: Pekerjaan
A134: MK00154 | B134: OUT | C134: 46198.417 | D134: 0.46100694 | E134: 628000064 | F134: Silva Alypia | G134: Produksi | H134: Toilet
A135: MK00154 | B135: IN | C135: 46198.417 | D135: 0.46246528 | E135: 628000064 | F135: Silva Alypia | G135: Produksi | H135: Toilet
A136: MK00154 | B136: OUT | C136: 46198.417 | D136: 0.48890046 | E136: 628000064 | F136: Silva Alypia | G136: Produksi | H136: Istirahat
A137: MK00154 | B137: IN | C137: 46198.417 | D137: 0.48921296 | E137: 628000064 | F137: Silva Alypia | G137: Produksi | H137: Istirahat
A138: MK00085 | B138: OUT | C138: 46198.417 | D138: 0.48956019 | E138: 528000279 | F138: Mahdalena Dalfa Riani | G138: Produksi | H138: Istirahat
A139: MK00085 | B139: IN | C139: 46198.417 | D139: 0.50861111 | E139: 528000279 | F139: Mahdalena Dalfa Riani | G139: Produksi | H139: Istirahat
A140: MK00154 | B140: OUT | C140: 46198.417 | D140: 0.50923611 | E140: 628000064 | F140: Silva Alypia | G140: Produksi | H140: Istirahat
A141: MK00090 | B141: OUT | C141: 46198.417 | D141: 0.51065972 | E141: 528000300 | F141: Lia pitaloka | G141: Produksi
A142: MK00154 | B142: IN | C142: 46198.417 | D142: 0.54678241 | E142: 628000064 | F142: Silva Alypia | G142: Produksi | H142: Sholat
A143: MK00145 | B143: OUT | C143: 46198.417 | D143: 0.71422454 | E143: 528000241 | F143: Balia Nurafif Bilah | G143: Produksi | H143: Istirahat
A144: MK00156 | B144: OUT | C144: 46198.417 | D144: 0.72438657 | E144: 528000274 | F144: Zepri | G144: Produksi | H144: Istirahat
A145: MK00141 | B145: OUT | C145: 46198.417 | D145: 0.72460648 | E145: 528000290 | F145: Eval Pranata | G145: Produksi | H145: Istirahat
A146: MK00145 | B146: IN | C146: 46198.417 | D146: 0.74123843 | E146: 528000241 | F146: Balia Nurafif Bilah | G146: Produksi | H146: Istirahat
A147: MK00141 | B147: IN | C147: 46198.417 | D147: 0.74280093 | E147: 528000290 | F147: Eval Pranata | G147: Produksi | H147: Istirahat
A148: MK00156 | B148: IN | C148: 46198.417 | D148: 0.74453704 | E148: 528000274 | F148: Zepri | G148: Produksi | H148: Istirahat
A149: MK00204 | B149: OUT | C149: 46198.417 | D149: 0.77701389 | E149: 528000099 | F149: Siti Nurawaliah | G149: Produksi | H149: Istirahat
...

Sheet Sheet9
A1: NO | B1: NIK | C1: NAMA | D1: DEPARTMENT | E1: SECTION | F1: GROUP
A2: =IFERROR(__xludf.DUMMYFUNCTION("QUERY('NON STAFF'!A$2:E1000,""select Col1,Col2,Col3,Col6,Col7,Col10 where Col6='Production'"",0) "),"#VALUE!")

Sheet LOG
A1: Jumlah Karyawan Department Logistic
A2: 2024
A3: Section | B3: January | C3: February | D3: March | E3: April | F3: May | G3: June | H3: July | I3: August | J3: September | K3: October | L3: November | M3: December | N3: HF1 | O3: HF2
A4: WFG | B4: 6 | C4: 6 | D4: 7 | E4: 9 | F4: 9 | G4: 11 | H4: 12 | I4: 10 | J4: 10 | K4: 10 | L4: 11 | M4: 11 | N4: =SUM(B4:G4) | O4: =SUM(H4:M4) | P4: =O4-N4
A5: WRM | B5: 11 | C5: 11 | D5: 12 | E5: 11 | F5: 11 | G5: 11 | H5: 11 | I5: 12 | J5: 11 | K5: 12 | L5: 10 | M5: 11 | N5: =SUM(B5:G5) | O5: =SUM(H5:M5) | P5: =O5-N5
A6: EXPEDISI | B6: 1 | C6: 2 | D6: 3 | E6: 2 | F6: 2 | G6: 1 | H6: 1 | I6: 1 | J6: 1 | K6: 1 | L6: 1 | M6: 1 | N6: =SUM(B6:G6) | O6: =SUM(H6:M6) | P6: =O6-N6
A7: TIMBANGAN | G7: 1 | H7: 2 | I7: 2 | J7: 2 | K7: 2 | L7: 2 | M7: 2 | N7: =SUM(B7:G7) | O7: =SUM(H7:M7) | P7: =O7-N7
A8: TOTAL | B8: =SUM(B4:B7) | C8: =SUM(C4:C7) | D8: =SUM(D4:D7) | E8: =SUM(E4:E7) | F8: =SUM(F4:F7) | G8: =SUM(G4:G7) | H8: =SUM(H4:H7) | I8: =SUM(I4:I7) | ... M8: =SUM(M4:M7) | N8: =SUM(B8:G8) | O8: =SUM(H8:M8) | P8: =O8-N8
A10: 2025
A11: Section | B11: January | C11: February | D11: March | E11: April | F11: May | G11: June | H11: July | I11: August | J11: September | K11: October | L11: November | M11: December | N11: HF1 | O11: HF2
A12: WFG | B12: 12 | C12: 11 | D12: 12 | E12: 11 | F12: 11 | G12: 12 | H12: 13 | I12: 13 | J12: 13 | K12: 14 | L12: 13 | M12: 15 | N12: =SUM(B12:G12) | O12: =SUM(H12:M12) | P12: =O12-N12
A13: WRM | B13: 11 | C13: 10 | D13: 9 | E13: 10 | F13: 10 | G13: 10 | H13: 10 | I13: 12 | J13: 11 | K13: 13 | L13: 14 | M13: 13 | N13: =SUM(B13:G13) | O13: =SUM(H13:M13) | P13: =O13-N13
A14: EXPEDISI | B14: 1 | C14: 1 | D14: 1 | E14: 1 | F14: 1 | G14: 2 | H14: 2 | I14: 2 | J14: 2 | K14: 3 | L14: 2 | M14: 2 | N14: =SUM(B14:G14) | O14: =SUM(H14:M14) | P14: =O14-N14
A15: TIMBANGAN | B15: 2 | C15: 2 | D15: 2 | E15: 2 | F15: 2 | G15: 2 | H15: 3 | I15: 3 | J15: 2 | K15: 2 | L15: 2 | M15: 2 | N15: =SUM(B15:G15) | O15: =SUM(H15:M15) | P15: =O15-N15
A16: WSP | H16: 4 | I16: 4 | J16: 4 | K16: 4 | L16: 4 | M16: 4 | N16: =SUM(B16:G16) | O16: =SUM(H16:M16) | P16: =O16-N16
A17: TOTAL | B17: =SUM(B12:B16) | C17: =SUM(C12:C16) | D17: =SUM(D12:D16) | E17: =SUM(E12:E16) | F17: =SUM(F12:F16) | G17: =SUM(G12:G16) | H17: =SUM(H12:H16) | I17: =SUM(I12:I16) | ... M17: =SUM(M12:M16) | N17: =SUM(B17:G17) | O17: =SUM(H17:M17) | P17: =O17-N17
A20: 2026
A21: Section | B21: January | C21: February | D21: March | E21: April | F21: May | G21: June | H21: July | I21: August | J21: September | K21: October | L21: November | M21: December
A22: WFG | B22: 17 | C22: 16
A23: WRM | B23: 12 | C23: 12
A24: EXPEDISI | B24: 2 | C24: 2
A25: TIMBANGAN | B25: 2 | C25: 3
A26: WSP | B26: 4 | C26: 4
A27: TOTAL | B27: =SUM(B22:B26) | C27: =SUM(C22:C26) | D27: =SUM(D22:D26) | E27: =SUM(E22:E26) | F27: =SUM(F22:F26) | G27: =SUM(G22:G26) | H27: =SUM(H22:H26) | I27: =SUM(I22:I26) | ... M27: =SUM(M22:M26)
A66: WRM 2025 | B66: January | C66: February | D66: March | E66: April | F66: May | G66: June | H66: July | I66: August | J66: September | K66: October | L66: November | M66: December
A67: Jumlah Orang | B67: 11 | C67: 10 | D67: 9 | E67: 10 | F67: 10 | G67: 10 | H67: 10 | I67: 12 | J67: 12 | K67: 12 | L67: 12 | M67: 12
A68: Total Box | B68: 644953 | C68: 568481 | D68: 631846 | E68: 569922 | F68: 624962 | G68: 656671 | H68: 728771 | I68: 717211 | J68: 246867 | K68: 0 | L68: 0 | M68: 0
A69: Baby (Box) | B69: 644953 | C69: 568481 | D69: 631846 | E69: 569922 | F69: 624962 | G69: 645173 | H69: 644284 | I69: 632555 | J69: 213691 | K69: 0 | L69: 0 | M69: 0
A70: Adult (Box) | B70: 0 | C70: 0 | D70: 0 | E70: 0 | F70: 0 | G70: 11498 | H70: 84487 | I70: 84656 | J70: 33176 | K70: 0 | L70: 0 | M70: 0
A71: Total Pallet | B71: 14985 | C71: 13350 | D71: 13945 | E71: 13588 | F71: 14604 | G71: 15322 | H71: 17583 | I71: 18047 | J71: 6512 | K71: 0 | L71: 0 | M71: 0
A72: Baby (Pallet) | B72: 14985 | C72: 13350 | D72: 13945 | E72: 13588 | F72: 14604 | G72: 14946 | H72: 14740 | I72: 14709 | J72: 5229 | K72: 0 | L72: 0 | M72: 0
A73: Adult (Pallet) | B73: 0 | C73: 0 | D73: 0 | E73: 0 | F73: 0 | G73: 376 | H73: 2844 | I73: 3338 | J73: 1283 | K73: 0 | L73: 0 | M73: 0
A74: Box per man | B74: =B68/B67 | C74: =C68/C67 | D74: =D68/D67 | E74: =E68/E67 | F74: =F68/F67 | G74: =G68/G67 | H74: =H68/H67 | I74: =I68/I67 | ... M74: =M68/M67
A75: Pallet per man | B75: =B71/B67 | C75: =C71/C67 | D75: =D71/D67 | E75: =E71/E67 | F75: =F71/F67 | G75: =G71/G67 | H75: =H71/H67 | I75: =I71/I67 | ... M75: =M71/M67
B76: =B75/25 | C76: =C75/25 | D76: =D75/25 | E76: =E75/25 | F76: =F75/25 | G76: =G75/25 | H76: =H75/25 | I76: =I75/25 | ... M76: =M75/25
A78: WFG 2025 | B78: January | C78: February | D78: March | E78: April | F78: May | G78: June | H78: July | I78: August | J78: September | K78: October | L78: November | M78: December
A79: Jumlah Orang | B79: 12 | C79: 11 | D79: 12 | E79: 11 | F79: 11 | G79: 12 | H79: 13 | I79: 13 | J79: 13 | K79: 13 | L79: 13 | M79: 13
A80: Total Box
A81: Baby (Box)
A82: Adult (Box)
A83: Total Pallet
A84: Baby (Pallet)
A85: Adult (Pallet)
A86: Box per man
A87: Pallet per man
A88: 24-01 | B88: {=TRANSPOSE(B8:M8)}
A89: 24-02 | B89: 19
A90: 24-03 | B90: 22
A91: 24-04 | B91: 22
A92: 24-05 | B92: 22
A93: 24-06 | B93: 24
A94: 24-07 | B94: 26
A95: 24-08 | B95: 25
A96: 24-09 | B96: 24
A97: 24-10 | B97: 25
A98: 24-11 | B98: 24
A99: 24-12 | B99: 25
A100: 25-01 | B100: {=TRANSPOSE(B17:M17)}
A101: 25-02 | B101: 24
A102: 25-03 | B102: 24
A103: 25-04 | B103: 24
A104: 25-05 | B104: 24
A105: 25-06 | B105: 26
A106: 25-07 | B106: 32
A107: 25-08 | B107: 34
A108: 25-09 | B108: 32
A109: 25-10 | B109: 36
A110: 25-11 | B110: 35
A111: 25-12 | B111: 36

Sheet PROD
A1: Jumlah Karyawan Department PROD
A2: 2024
A3: Section | B3: January | C3: February | D3: March | E3: April | F3: May | G3: June | H3: July | I3: August | J3: September | K3: October | L3: November | M3: December
A4: BHP | B4: 141 | C4: 140 | D4: 140 | E4: 138 | F4: 140 | G4: 141 | H4: 142 | I4: 140 | J4: 141 | K4: 146 | L4: 140 | M4: 139
A5: HPY
A6: TOTAL | B6: =SUM(B4:B5) | C6: =SUM(C4:C5) | D6: =SUM(D4:D5) | E6: =SUM(E4:E5) | F6: =SUM(F4:F5) | G6: =SUM(G4:G5) | H6: =SUM(H4:H5) | I6: =SUM(I4:I5) | ... M6: =SUM(M4:M5)
A8: 2025
A9: Section | B9: January | C9: February | D9: March | E9: April | F9: May | G9: June | H9: July | I9: August | J9: September | K9: October | L9: November | M9: December
A10: BHP | B10: 139 | C10: 138 | D10: 136 | E10: 139 | F10: 152 | G10: 135 | H10: 139 | I10: 139 | J10: 133 | K10: 137 | L10: 133 | M10: 147
A11: HPY | G11: 29 | H11: 34 | I11: 36 | J11: 43 | K11: 43 | L11: 41 | M11: 51
A12: TOTAL | B12: =SUM(B10:B11) | C12: =SUM(C10:C11) | D12: =SUM(D10:D11) | E12: =SUM(E10:E11) | F12: =SUM(F10:F11) | G12: =SUM(G10:G11) | H12: =SUM(H10:H11) | I12: =SUM(I10:I11) | ... M12: =SUM(M10:M11)
A14: 2026
A15: Section | B15: January | C15: February | D15: March | E15: April | F15: May | G15: June | H15: July | I15: August | J15: September | K15: October | L15: November | M15: December
A16: BHP | B16: 152 | C16: 191
A17: HPY | B17: 45 | C17: 45
A18: TOTAL | B18: =SUM(B16:B17) | C18: =SUM(C16:C17) | D18: =SUM(D16:D17) | E18: =SUM(E16:E17) | F18: =SUM(F16:F17) | G18: =SUM(G16:G17) | H18: =SUM(H16:H17) | I18: =SUM(I16:I17) | ... M18: =SUM(M16:M17)

Sheet STAFF PROD DES 24
A1: DATA STAFF AKTIF PER DESEMBER 24 - PT DAM
A3: NO | B3: NIK | C3: Nama | D3: CC | E3: Dept | F3: JABATAN
A4: 1 | B4: 128000001 | C4: Iman Nurchaedi S. | D4: 111102 | E4: Production | F4: Plant Manager
A5: 2 | B5: 128000010 | C5: Dendy Saputra | D5: 111102 | E5: Production | F5: Line Leader
A6: 3 | B6: 128000012 | C6: Evita | D6: 111102 | E6: Production | F6: Production Chief SPV 1
A7: 4 | B7: 128000022 | C7: Hendra Setiawan | D7: 111102 | E7: Production | F7: Production Engineer
A8: 5 | B8: 128000029 | C8: Angga Setyawan | D8: 111102 | E8: Production | F8: Shift Leader
A9: 6 | B9: 128000030 | C9: Kelik Aji Sambudi | D9: 111102 | E9: Production | F9: Shift Leader
A10: 7 | B10: 128000031 | C10: Abdu Fuad Arrazy | D10: 111102 | E10: Production | F10: Shift Leader
A11: 8 | B11: 128000039 | C11: Saka Marga Redi | D11: 111102 | E11: Production | F11: Line Leader
A12: 9 | B12: 128000040 | C12: Gilang Anugerah Hernanda | D12: 111102 | E12: Production | F12: Line Leader
A13: 10 | B13: 128000041 | C13: Alief Akbar Rafsanzani | D13: 111102 | E13: Production | F13: Shift Leader
A14: 11 | B14: 128000042 | C14: Ahmad Afrizal | D14: 111102 | E14: Production | F14: Line Leader
A15: 12 | B15: 128000070 | C15: Bey Muhammad | D15: 111102 | E15: Production | F15: Line Leader
A16: 13 | B16: 128000071 | C16: Febri Wira Wijaya | D16: 111102 | E16: Production | F16: Line Leader

Sheet STAFF NONPROD DES 24
A1: DATA STAFF AKTIF PER DESEMBER 24 - PT DAM
A3: NO | B3: NIK | C3: Nama | D3: CC | E3: Dept | F3: JABATAN
A4: 1 | B4: 128000003 | C4: Andre Santosa | D4: 121101 | E4: Engineering | F4: Engineering Deputy Manager
A5: 2 | B5: 128000049 | C5: Ragil Febriansyah | D5: 331101 | E5: Engineering | F5: Staff ITE
A6: 3 | B6: 128000027 | C6: Gembong Hagung Harsanto | D6: 121101 | E6: Engineering | F6: Engineering Chief Spv 1
A7: 4 | B7: 128000032 | C7: Ardi Akbar Rian Saputra | D7: 121101 | E7: Engineering | F7: Sr. Staff Machine & Glue Maintenance And Workshop Assembly
A8: 5 | B8: 128000033 | C8: Susep Triwibowo | D8: 121101 | E8: Engineering | F8: Sr. Staff Machine Maintenance & Utility Shift
A9: 6 | B9: 128000036 | C9: Novan Satyawardhana | D9: 121101 | E9: Engineering | F9: Sr. Staff Machine Maintenance & Utility Shift
A10: 7 | B10: 128000057 | C10: Taufik Hidayatulloh | D10: 121101 | E10: Engineering | F10: Staff Utility & Facility Maintenance
A11: 8 | B11: 128000058 | C11: Stefanus Suprianto | D11: 121101 | E11: Engineering | F11: Staff Maintenance Planner & WSP
A12: 9 | B12: 128000059 | C12: Muhamad Maftuh Ihsan | D12: 121101 | E12: Engineering | F12: Sr. Staff EHS
A13: 10 | B13: 128000063 | C13: Reynaldi Pratama | D13: 121101 | E13: Engineering | F13: Sr. Staff Machine Maintenance & Utility Shift
A14: 11 | B14: 128000064 | C14: Toni Kurniawan | D14: 121101 | E14: Engineering | F14: Staff Machine Maintenance & Utility Shift
A15: 12 | B15: 128000060 | C15: Christalia Sarah | D15: 311101 | E15: Finance & Accounting | F15: Accounting Officer
... A40: 37 | B40: 128000013 | C40: Aminulloh | D40: 121104 | E40: Logistic | F40: Staff Warehouse Sparepart

Sheet Prod Mesin 1
B1: NON STAFF MESIN 1 | M1: STAFF MESIN 1
A2: No | B2: NIK | C2: Nama | D2: Departmen | E2: Section | F2: Jabatan | G2: Jenis Kelamin | H2: Pendidikan | I2: BPJS KES | J2: BPJS TK | L2: No | M2: NIK | N2: Nama | O2: Departmen | P2: Section | Q2: Jabatan | R2: Jenis Kelamin | S2: Pendidikan | T2: BPJS KES | U2: BPJS TK
A3: 1 | B3: 328000019 | C3: Dadang Saputra | D3: Production | E3: Production Diapers | F3: Operator Produksi | G3: =VLOOKUP(B3,Sheet5!B:K,10,0) | H3: =VLOOKUP(B3,Sheet5!B:AA,26,0) | I3: 0000481312416 | J3: 23145801447 | K3: 16 | L3: 1 | M3: 128000088 | N3: Tyas Muhammad Hafizh | O3: Production | P3: Production Diapers | Q3: Line Leader | R3: L | S3: S1 | T3: 0001620928236
A4: 2 | B4: 328000020 | C4: Agus Gunawan | D4: Production | E4: Production Diapers | F4: Operator Produksi | G4: =VLOOKUP(B4,Sheet5!B:K,10,0) | H4: =VLOOKUP(B4,Sheet5!B:AA,26,0) | I4: 0000481572088 | J4: 23145801504 | L4: 2 | M4: 128000090 | N4: Ryandra Diotama Subagja | O4: Production | P4: Production Diapers | Q4: Line Leader | R4: L | S4: D4 | T4: 0001538830034
A5: 3 | B5: 328000022 | C5: Azhar Aizad Alfaridzi | D5: Production | E5: Production Diapers | F5: Operator Produksi | G5: =VLOOKUP(B5,Sheet5!B:K,10,0) | H5: =VLOOKUP(B5,Sheet5!B:AA,26,0) | I5: 0001633523084 | J5: 23145801652 | L5: 3 | M5: 128000091 | N5: Dava Raihan Pranoto | O5: Production | P5: Production Diapers | Q5: Line Leader | R5: L | S5: D3 | T5: 0002263293213
A6: 4 | B6: 328000023 | C6: Kepin Nugraha | D6: Production | E6: Production Diapers | F6: Operator Produksi | G6: =VLOOKUP(B6,Sheet5!B:K,10,0) | H6: =VLOOKUP(B6,Sheet5!B:AA,26,0) | I6: 0002394923444 | J6: 23145801710
A7: 5 | B7: 328000027 | C7: Gigin Ginanjar | D7: Production | E7: Production Diapers | F7: Operator Produksi | G7: =VLOOKUP(B7,Sheet5!B:K,10,0) | H7: =VLOOKUP(B7,Sheet5!B:AA,26,0) | I7: 0002441918799 | J7: 23145801520
A8: 6 | B8: 328000028 | C8: Tisna Ginanjar | D8: Production | E8: Production Diapers | F8: Operator Produksi | G8: =VLOOKUP(B8,Sheet5!B:K,10,0) | H8: =VLOOKUP(B8,Sheet5!B:AA,26,0) | I8: 0001182631015 | J8: 23145801678
A9: 7 | B9: 328000036 | C9: Fesal Fauzan | D9: Production | E9: Production Diapers | F9: Operator Produksi | G9: =VLOOKUP(B9,Sheet5!B:K,10,0) | H9: =VLOOKUP(B9,Sheet5!B:AA,26,0) | I9: 0001523374593 | J9: 23145801561
A10: 8 | B10: 328000037 | C10: Kurniadi | D10: Production | E10: Production Diapers | F10: Operator Produksi | G10: =VLOOKUP(B10,Sheet5!B:K,10,0) | H10: =VLOOKUP(B10,Sheet5!B:AA,26,0) | I10: 0002177064821 | J10: 23145801439
A11: 9 | B11: 328000063 | C11: Rizki Agung | D11: Production | E11: Production Diapers | F11: Operator Produksi | G11: =VLOOKUP(B11,Sheet5!B:K,10,0) | H11: =VLOOKUP(B11,Sheet5!B:AA,26,0) | I11: 0001185075988 | J11: 23165961121
A12: 10 | B12: 328000083 | C12: Aldi Sutrisna | D12: Production | E12: Production Diapers | F12: Operator Produksi | G12: =VLOOKUP(B12,Sheet5!B:K,10,0) | H12: =VLOOKUP(B12,Sheet5!B:AA,26,0) | I12: 0001882085027 | J12: 23165960776
A13: 11 | B13: 328000134 | C13: Asep Septiana | D13: Production | E13: Production Diapers | F13: Operator Produksi | G13: =VLOOKUP(B13,Sheet5!B:K,10,0) | H13: =VLOOKUP(B13,Sheet5!B:AA,26,0) | I13: 0001181591021 | J13: 23191184151
A14: 12 | B14: 328000137 | C14: Muhammad Aldy Ramadhan | D14: Production | E14: Production Diapers | F14: Operator Produksi | G14: =VLOOKUP(B14,Sheet5!B:K,10,0) | H14: =VLOOKUP(B14,Sheet5!B:AA,26,0) | I14: 0001821988473 | J14: 23191184276
A15: 13 | B15: 328000178 | C15: Bambang Artian Herlambang | D15: Production | E15: Production Diapers | F15: Operator Produksi | G15: =VLOOKUP(B15,Sheet5!B:K,10,0) | H15: =VLOOKUP(B15,Sheet5!B:AA,26,0) | I15: 0000480941021 | J15: 24003656063
A16: 14 | B16: 328000260 | C16: Ali Ramdhan | D16: Production | E16: Production Diapers | F16: Operator Produksi | G16: =VLOOKUP(B16,Sheet5!B:K,10,0) | H16: =VLOOKUP(B16,Sheet5!B:AA,26,0) | I16: 0002394923657 | J16: 24096022694
A17: 15 | B17: 328000325 | C17: Mohamad Aldiawan | D17: Production | E17: Production Diapers | F17: Operator Produksi | G17: =VLOOKUP(B17,Sheet5!B:K,10,0) | H17: =VLOOKUP(B17,Sheet5!B:AA,26,0) | I17: 0001427573024 | J17: 25047993123 | M17: SMA | N17: 76
A18: 16 | B18: 328000319 | C18: Ari Pebrianto | D18: Production | E18: Production Diapers | F18: Operator Produksi | G18: =VLOOKUP(B18,Sheet5!B:K,10,0) | H18: =VLOOKUP(B18,Sheet5!B:AA,26,0) | I18: 0000482051722 | J18: 25047993149
A19: 17 | B19: 328000041 | C19: Bunga Adelya | D19: Production | E19: Production Diapers | F19: Packer | G19: =VLOOKUP(B19,Sheet5!B:K,10,0) | H19: =VLOOKUP(B19,Sheet5!B:AA,26,0) | I19: 0001659877817 | J19: 23165960602 | K19: 24
A20: 18 | B20: 328000042 | C20: Cindy Amelia | D20: Production | E20: Production Diapers | F20: Packer | G20: =VLOOKUP(B20,Sheet5!B:K,10,0) | H20: =VLOOKUP(B20,Sheet5!B:AA,26,0) | I20: 0002394908763 | J20: 23165960909
A21: 19 | B21: 328000043 | C21: Andini Novia Ramadani | D21: Production | E21: Production Diapers | F21: Packer | G21: =VLOOKUP(B21,Sheet5!B:K,10,0) | H21: =VLOOKUP(B21,Sheet5!B:AA,26,0) | I21: 0000481262567 | J21: 23165961170
A22: 20 | B22: 328000219 | C22: Windy Meilani | D22: Production | E22: Production Diapers | F22: Packer | G22: =VLOOKUP(B22,Sheet5!B:K,10,0) | H22: =VLOOKUP(B22,Sheet5!B:AA,26,0) | I22: 0001889780433 | J22: 24044646016
A23: 21 | B23: 328000246 | C23: Dwi Fitriyani | D23: Production | E23: Production Diapers | F23: Packer | G23: =VLOOKUP(B23,Sheet5!B:K,10,0) | H23: =VLOOKUP(B23,Sheet5!B:AA,26,0) | I23: 0001479043596 | J23: 23165960826
A24: 22 | B24: 328000266 | C24: Devi Pebriani | D24: Production | E24: Production Diapers | F24: Packer | G24: =VLOOKUP(B24,Sheet5!B:K,10,0) | H24: =VLOOKUP(B24,Sheet5!B:AA,26,0) | I24: 0001437682386 | J24: 24111973616
A25: 23 | B25: 328000272 | C25: Akbar Saepuloh | D25: Production | E25: Production Diapers | F25: Packer | G25: =VLOOKUP(B25,Sheet5!B:K,10,0) | H25: =VLOOKUP(B25,Sheet5!B:AA,26,0) | I25: 0002394923973 | J25: 24126527597
A26: 24 | B26: 328000289 | C26: Karya | D26: Production | E26: Production Diapers | F26: Packer | G26: =VLOOKUP(B26,Sheet5!B:K,10,0) | H26: =VLOOKUP(B26,Sheet5!B:AA,26,0) | I26: 0000481647644 | J26: 24162489884
A27: 25 | B27: 328000296 | C27: Rahma Indira Azhara | D27: Production | E27: Production Diapers | F27: Packer | G27: =VLOOKUP(B27,Sheet5!B:K,10,0) | H27: =VLOOKUP(B27,Sheet5!B:AA,26,0) | I27: 0001010118734 | J27: 24203133095
A28: 26 | B28: 328000299 | C28: Ratu Thyara Reva Kharina | D28: Production | E28: Production Diapers | F28: Packer | G28: =VLOOKUP(B28,Sheet5!B:K,10,0) | H28: =VLOOKUP(B28,Sheet5!B:AA,26,0) | I28: 0003637625387 | J28: 25003406532
A29: 27 | B29: 328000328 | C29: Oktavia Eka Damayanti | D29: Production | E29: Production Diapers | F29: Packer | G29: =VLOOKUP(B29,Sheet5!B:K,10,0) | H29: =VLOOKUP(B29,Sheet5!B:AA,26,0) | I29: 0001833654712 | J29: 25060609077
A30: 28 | B30: 328000342 | C30: Fitri | D30: Production | E30: Production Diapers | F30: Packer | G30: =VLOOKUP(B30,Sheet5!B:K,10,0) | H30: =VLOOKUP(B30,Sheet5!B:AA,26,0) | I30: 0001661917847 | J30: 25060609200
A31: 29 | B31: 328000352 | C31: Yasmin Annisa Alkhoiriyah | D31: Production | E31: Production Diapers | F31: Packer | G31: =VLOOKUP(B31,Sheet5!B:K,10,0) | H31: =VLOOKUP(B31,Sheet5!B:AA,26,0) | I31: 0001314865078 | J31: 25060609309
... A39: 37 | B39: 328000395 | C39: Anisa Rahma Aulia | D39: Production | E39: Production Diapers | F39: Packer | G39: =VLOOKUP(B39,Sheet5!B:K,10,0) | H39: =VLOOKUP(B39,Sheet5!B:AA,26,0) | I39: 0003340821273 | J39: 25097052267
A40: 38 | B40: 328000400 | C40: M Karsim Septian | D40: Production | E40: Production Diapers | F40: Packer | G40: =VLOOKUP(B40,Sheet5!B:K,10,0) | H40: =VLOOKUP(B40,Sheet5!B:AA,26,0) | I40: 0001861520174
A41: 39 | B41: 328000406 | C41: Firlie Nurfebriany Firmansyah | D41: Production | E41: Production Diapers | F41: Packer | G41: =VLOOKUP(B41,Sheet5!B:K,10,0) | H41: =VLOOKUP(B41,Sheet5!B:AA,26,0) | I41: 0003042186118
A42: 40 | B42: 328000417 | C42: Raja Aditia | D42: Production | E42: Production Diapers | F42: Packer | G42: =VLOOKUP(B42,Sheet5!B:K,10,0) | H42: =VLOOKUP(B42,Sheet5!B:AA,26,0) | I42: 0001876764688
A43: 41 | B43: 328000241 | C43: Jihan Noerhalija | D43: Quality and Research & Development | E43: QC - Diapers | F43: =VLOOKUP(B43,'NON STAFF'!B:E,7,0) | G43: =VLOOKUP(B43,Sheet5!B:K,10,0) | H43: =VLOOKUP(B43,Sheet5!B:AA,26,0) | I43: =VLOOKUP(B43,Sheet5!AD:AH,5,0) | J43: =VLOOKUP(B43,Sheet5!AD:AG,4,0)
A44: 42 | B44: 328000314 | C44: Lulut Sonia | D44: Quality and Research & Development | E44: QC - Diapers | F44: =VLOOKUP(B44,'NON STAFF'!B:E,7,0) | G44: =VLOOKUP(B44,Sheet5!B:K,10,0) | H44: =VLOOKUP(B44,Sheet5!B:AA,26,0) | I44: =VLOOKUP(B44,Sheet5!AD:AH,5,0) | J44: =VLOOKUP(B44,Sheet5!AD:AG,4,0)
A45: 43 | B45: 328000305 | C45: Suryani Sihite | D45: Quality and Research & Development | E45: QC - Diapers | F45: =VLOOKUP(B45,'NON STAFF'!B:E,7,0) | G45: =VLOOKUP(B45,Sheet5!B:K,10,0) | H45: =VLOOKUP(B45,Sheet5!B:AA,26,0) | I45: =VLOOKUP(B45,Sheet5!AD:AH,5,0) | J45: =VLOOKUP(B45,Sheet5!AD:AG,4,0)
A46: 44 | B46: 328000106 | C46: Fany Febryaniwardoyo | D46: Quality and Research & Development | E46: QC - Diapers | F46: =VLOOKUP(B46,'NON STAFF'!B:E,7,0) | G46: =VLOOKUP(B46,Sheet5!B:K,10,0) | H46: =VLOOKUP(B46,Sheet5!B:AA,26,0) | I46: =VLOOKUP(B46,Sheet5!AD:AH,5,0) | J46: =VLOOKUP(B46,Sheet5!AD:AG,4,0)
A47: 45 | B47: 328000151 | C47: Suci Alfina F | D47: Quality and Research & Development | E47: QC - Diapers | F47: =VLOOKUP(B47,'NON STAFF'!B:E,7,0) | G47: =VLOOKUP(B47,Sheet5!B:K,10,0) | H47: =VLOOKUP(B47,Sheet5!B:AA,26,0) | I47: =VLOOKUP(B47,Sheet5!AD:AH,5,0) | J47: =VLOOKUP(B47,Sheet5!AD:AG,4,0)
A48: 46 | B48: 328000040 | C48: Asep Kamaludin | D48: Quality and Research & Development | E48: QC - Diapers | F48: =VLOOKUP(B48,'NON STAFF'!B:E,7,0) | G48: =VLOOKUP(B48,Sheet5!B:K,10,0) | H48: =VLOOKUP(B48,Sheet5!B:AA,26,0) | I48: =VLOOKUP(B48,Sheet5!AD:AH,5,0) | J48: =VLOOKUP(B48,Sheet5!AD:AG,4,0)
A49: 47 | B49: 328000066 | C49: Nadila Naziwa Sopian | D49: Quality and Research & Development | E49: QC - Diapers | F49: =VLOOKUP(B49,'NON STAFF'!B:E,7,0) | G49: =VLOOKUP(B49,Sheet5!B:K,10,0) | H49: =VLOOKUP(B49,Sheet5!B:AA,26,0) | I49: =VLOOKUP(B49,Sheet5!AD:AH,5,0) | J49: =VLOOKUP(B49,Sheet5!AD:AG,4,0)
A50: 48 | B50: 328000068 | C50: Nadine Riezki Ghefira | D50: Quality and Research & Development | E50: QC - Diapers | F50: =VLOOKUP(B50,'NON STAFF'!B:E,7,0) | G50: =VLOOKUP(B50,Sheet5!B:K,10,0) | H50: =VLOOKUP(B50,Sheet5!B:AA,26,0) | I50: =VLOOKUP(B50,Sheet5!AD:AH,5,0) | J50: =VLOOKUP(B50,Sheet5!AD:AG,4,0)
A51: 49 | B51: 328000039 | C51: Desty Marliani | D51: Quality and Research & Development | E51: QC - Diapers | F51: =VLOOKUP(B51,'NON STAFF'!B:E,7,0) | G51: =VLOOKUP(B51,Sheet5!B:K,10,0) | H51: =VLOOKUP(B51,Sheet5!B:AA,26,0) | I51: =VLOOKUP(B51,Sheet5!AD:AH,5,0) | J51: =VLOOKUP(B51,Sheet5!AD:AG,4,0)
A52: 50 | B52: 328000011 | C52: Deni Kusnadi | D52: Logistic | E52: Warehouse Sparepart | F52: Admin WSP | G52: =VLOOKUP(B52,Sheet5!B:K,10,0) | H52: =VLOOKUP(B52,Sheet5!B:AA,26,0) | I52: =VLOOKUP(B52,Sheet5!AD:AH,5,0) | J52: =VLOOKUP(B52,Sheet5!AD:AG,4,0)
A53: 51 | B53: 328000016 | C53: Ramdan Abdullah | D53: Logistic | E53: Timbangan | F53: Admin Timbangan | G53: =VLOOKUP(B53,Sheet5!B:K,10,0) | H53: =VLOOKUP(B53,Sheet5!B:AA,26,0) | I53: =VLOOKUP(B53,Sheet5!AD:AH,5,0) | J53: =VLOOKUP(B53,Sheet5!AD:AG,4,0)
A54: 52 | B54: 328000017 | C54: Dadi Setiadi | D54: Logistic | E54: Warehouse Raw Material | F54: Operator Forklift | G54: =VLOOKUP(B54,Sheet5!B:K,10,0) | H54: =VLOOKUP(B54,Sheet5!B:AA,26,0) | I54: =VLOOKUP(B54,Sheet5!AD:AH,5,0) | J54: =VLOOKUP(B54,Sheet5!AD:AG,4,0)
A55: 53 | B55: 328000018 | C55: Nevany Putri | D55: Logistic | E55: Warehouse Raw Material | F55: Admin WRM | G55: =VLOOKUP(B55,Sheet5!B:K,10,0) | H55: =VLOOKUP(B55,Sheet5!B:AA,26,0) | I55: =VLOOKUP(B55,Sheet5!AD:AH,5,0) | J55: =VLOOKUP(B55,Sheet5!AD:AG,4,0)
A56: 54 | B56: 328000052 | C56: Dimas Nugroho | D56: Logistic | E56: Warehouse Sparepart | F56: Admin WSP | G56: =VLOOKUP(B56,Sheet5!B:K,10,0) | H56: =VLOOKUP(B56,Sheet5!B:AA,26,0) | I56: =VLOOKUP(B56,Sheet5!AD:AH,5,0) | J56: =VLOOKUP(B56,Sheet5!AD:AG,4,0)
A57: 55 | B57: 328000080 | C57: Ilham Paoji Muharom | D57: Logistic | E57: Warehouse Raw Material | F57: Operator Forklift | G57: =VLOOKUP(B57,Sheet5!B:K,10,0) | H57: =VLOOKUP(B57,Sheet5!B:AA,26,0) | I57: =VLOOKUP(B57,Sheet5!AD:AH,5,0) | J57: =VLOOKUP(B57,Sheet5!AD:AG,4,0)
A58: 56 | B58: 328000081 | C58: M. Qori Almahmud | D58: Logistic | E58: Warehouse Sparepart | F58: Admin WSP | G58: =VLOOKUP(B58,Sheet5!B:K,10,0) | H58: =VLOOKUP(B58,Sheet5!B:AA,26,0) | I58: =VLOOKUP(B58,Sheet5!AD:AH,5,0) | J58: =VLOOKUP(B58,Sheet5!AD:AG,4,0)
A59: 57 | B59: 328000086 | C59: Aria Permana Zidane | D59: Logistic | E59: Warehouse Raw Material | F59: PIC Area | G59: =VLOOKUP(B59,Sheet5!B:K,10,0) | H59: =VLOOKUP(B59,Sheet5!B:AA,26,0) | I59: =VLOOKUP(B59,Sheet5!AD:AH,5,0) | J59: =VLOOKUP(B59,Sheet5!AD:AG,4,0)
A60: 58 | B60: 328000097 | C60: Yogi Rudianto | D60: Logistic | E60: Warehouse Raw Material | F60: Admin WRM | G60: =VLOOKUP(B60,Sheet5!B:K,10,0) | H60: =VLOOKUP(B60,Sheet5!B:AA,26,0) | I60: =VLOOKUP(B60,Sheet5!AD:AH,5,0) | J60: =VLOOKUP(B60,Sheet5!AD:AG,4,0)
A61: 59 | B61: 328000100 | C61: Fikrie Abi Hasan | D61: Logistic | E61: Warehouse Sparepart | F61: Admin WSP | G61: =VLOOKUP(B61,Sheet5!B:K,10,0) | H61: =VLOOKUP(B61,Sheet5!B:AA,26,0) | I61: =VLOOKUP(B61,Sheet5!AD:AH,5,0) | J61: =VLOOKUP(B61,Sheet5!AD:AG,4,0)
A62: 60 | B62: 328000148 | C62: Muhammad Alfikri | D62: Logistic | E62: Warehouse Finish Good | F62: Checker | G62: =VLOOKUP(B62,Sheet5!B:K,10,0) | H62: =VLOOKUP(B62,Sheet5!B:AA,26,0) | I62: =VLOOKUP(B62,Sheet5!AD:AH,5,0) | J62: =VLOOKUP(B62,Sheet5!AD:AG,4,0)
A63: 61 | B63: 328000237 | C63: Muhamad Gaman | D63: Logistic | E63: Warehouse Raw Material | F63: Operator Forklift | G63: =VLOOKUP(B63,Sheet5!B:K,10,0) | H63: =VLOOKUP(B63,Sheet5!B:AA,26,0) | I63: =VLOOKUP(B63,Sheet5!AD:AH,5,0) | J63: =VLOOKUP(B63,Sheet5!AD:AG,4,0)
... A82: 80 | B82: 328000419 | C82: Cecep Sukma Wijaya | D82: Logistic | E82: Warehouse Finish Good | F82: Operator Forklift | G82: =VLOOKUP(B82,Sheet5!B:K,10,0) | H82: =VLOOKUP(B82,Sheet5!B:AA,26,0) | I82: =VLOOKUP(B82,Sheet5!AD:AH,5,0) | J82: =VLOOKUP(B82,Sheet5!AD:AG,4,0)
B89: Jenis Kelamin | C89: Total
B90: Laki-laki | C90: =COUNTIF('Prod Mesin 1'!$G$2:$G$93,"L")
B91: Perempuan | C91: =COUNTIF('Prod Mesin 1'!$G$3:$G$94,"P")
B92: Jumlah | C92: =SUM(C43:C91)
B94: Jabatan | C94: Total
B95: Packer | C95: =COUNTIF('Prod Mesin 1'!$F$2:$F$100,"Packer")
B96: Operator Production | C96: =COUNTIF('Prod Mesin 1'!$F$2:$F$101,"Operator Produksi")
B97: QC - Diapers | C97: =COUNTIF('Prod Mesin 1'!$E$2:$E$101,"QC - Diapers")
B98: Logistic | C98: =COUNTIF('Prod Mesin 1'!$D$2:$D$101,"Logistic")
B99: Jumlah | C99: =SUM(C95:C98)
B102: Pendidikan | C102: Total
B103: SMK | C103: =COUNTIF('Prod Mesin 1'!$H$2:$H$106,"SMK")
B104: SMA | C104: =COUNTIF('Prod Mesin 1'!$H$2:$H$106,"SMA")
B105: D1 | C105: =COUNTIF('Prod Mesin 1'!$H$2:$H$106,"D1")
B106: D2 | C106: =COUNTIF('Prod Mesin 1'!$H$2:$H$106,"D2")
B107: D3 | C107: =COUNTIF('Prod Mesin 1'!$H$2:$H$106,"D3")
B108: D4 | C108: =COUNTIF('Prod Mesin 1'!$H$2:$H$106,"D4")
B109: S1 | C109: =COUNTIF('Prod Mesin 1'!$H$2:$H$106,"S1")
B110: S2 | C110: =COUNTIF('Prod Mesin 1'!$H$2:$H$106,"S2")
B111: Jumlah | C111: =SUM(C103:C110)

Sheet ENG
A1: Jumlah Karyawan Department ENG
A2: 2024
A3: Section | B3: January | C3: February | D3: March | E3: April | F3: May | G3: June | H3: July | I3: August | J3: September | K3: October | L3: November | M3: December
A4: ENG | B4: 13 | C4: 14 | D4: 14 | E4: 14 | F4: 13 | G4: 13 | H4: 14 | I4: 13 | J4: 14 | K4: 14 | L4: 14 | M4: 15
A5: WSP | B5: 4 | C5: 4 | D5: 4 | E5: 4 | F5: 4 | G5: 4 | H5: 4 | I5: 4 | J5: 4 | K5: 4 | L5: 4 | M5: 4
A6: TOTAL | B6: =SUM(B4:B5) | C6: =SUM(C4:C5) | D6: =SUM(D4:D5) | E6: =SUM(E4:E5) | F6: =SUM(F4:F5) | G6: =SUM(G4:G5) | H6: =SUM(H4:H5) | I6: =SUM(I4:I5) | ... M6: =SUM(M4:M5)
A8: 2025
A9: Section | B9: January | C9: February | D9: March | E9: April | F9: May | G9: June | H9: July | I9: August | J9: September | K9: October | L9: November | M9: December
A10: ENG | B10: 15 | C10: 14 | D10: 15 | E10: 15 | F10: 19 | G10: 19 | H10: 20 | I10: 20 | J10: 20 | K10: 20 | L10: 23 | M10: 26
A11: WSP | B11: 4 | C11: 4 | D11: 4 | E11: 4 | F11: 4 | G11: 4
A12: TOTAL | B12: =SUM(B10:B11) | C12: =SUM(C10:C11) | D12: =SUM(D10:D11) | E12: =SUM(E10:E11) | F12: =SUM(F10:F11) | G12: =SUM(G10:G11) | H12: =SUM(H10:H11) | I12: =SUM(I10:I11) | ... M12: =SUM(M10:M11)
A14: 2026
A15: Section | B15: January | C15: February | D15: March | E15: April | F15: May | G15: June | H15: July | I15: August | J15: September | K15: October | L15: November | M15: December
A16: ENG | B16: 26 | C16: 28
A17: TOTAL | B17: =SUM(B16) | C17: =SUM(C16) | D17: =SUM(D16) | E17: =SUM(E16) | F17: =SUM(F16) | G17: =SUM(G16) | H17: =SUM(H16) | I17: =SUM(I16) | ... M17: =SUM(M16)

Sheet QC
A1: Jumlah Karyawan Department QC
A2: 2024
A3: Section | B3: January | C3: February | D3: March | E3: April | F3: May | G3: June | H3: July | I3: August | J3: September | K3: October | L3: November | M3: December
A4: BHP | B4: 21 | C4: 21 | D4: 23 | E4: 26 | F4: 26 | G4: 25 | H4: 26 | I4: 25 | J4: 26 | K4: 26 | L4: 25 | M4: 26
A5: HPY
A6: TOTAL | B6: =SUM(B4:B5) | C6: =SUM(C4:C5) | D6: =SUM(D4:D5) | E6: =SUM(E4:E5) | F6: =SUM(F4:F5) | G6: =SUM(G4:G5) | H6: =SUM(H4:H5) | I6: =SUM(I4:I5) | ... M6: =SUM(M4:M5)
A8: 2025
A9: Section | B9: January | C9: February | D9: March | E9: April | F9: May | G9: June | H9: July | I9: August | J9: September | K9: October | L9: November | M9: December
A10: BHP | B10: 31 | C10: 33 | D10: 34 | E10: 35 | F10: 35 | G10: 35 | H10: 30 | I10: 31 | J10: 33 | K10: 32 | L10: 31 | M10: 33
A11: HPY | H11: 3 | I11: 3 | J11: 3 | K11: 3 | L11: 3 | M11: 4
A12: TOTAL | B12: =SUM(B10:B11) | C12: =SUM(C10:C11) | D12: =SUM(D10:D11) | E12: =SUM(E10:E11) | F12: =SUM(F10:F11) | G12: =SUM(G10:G11) | H12: =SUM(H10:H11) | I12: =SUM(I10:I11) | ... M12: =SUM(M10:M11)
A14: 2026
A15: Section | B15: January | C15: February | D15: March | E15: April | F15: May | G15: June | H15: July | I15: August | J15: September | K15: October | L15: November | M15: December
A16: BHP | B16: 44 | C16: 48
A17: HPY | B17: 4 | C17: 4 | H17: 3 | I17: 3 | J17: 3
A18: TOTAL | B18: =SUM(B16:B17) | C18: =SUM(C16:C17) | D18: =SUM(D16:D17) | E18: =SUM(E16:E17) | F18: =SUM(F16:F17) | G18: =SUM(G16:G17) | H18: =SUM(H16:H17) | I18: =SUM(I16:I17) | ... M18: =SUM(M16:M17)

Sheet HR GA
A1: Jumlah Karyawan Department HRGA
A3: 2025
A4: Section | B4: January | C4: February | D4: March | E4: April | F4: May | G4: June | H4: July | I4: August | J4: September | K4: October | L4: November | M4: December
A5: HRGA
A6: HPY
A7: TOTAL | B7: =SUM(B5:B6) | C7: =SUM(C5:C6) | D7: =SUM(D5:D6) | E7: =SUM(E5:E6) | F7: =SUM(F5:F6) | G7: =SUM(G5:G6) | H7: =SUM(H5:H6) | I7: =SUM(I5:I6) | ... M7: =SUM(M5:M6)
A9: 2026
A10: Section | B10: January | C10: February | D10: March | E10: April | F10: May | G10: June | H10: July | I10: August | J10: September | K10: October | L10: November | M10: December
A11: HRGA | B11: 1 | C11: 1 | G11: 1 | H11: 1 | I11: 1 | J11: 1 | K11: 1 | L11: 1 | M11: 1
A12: TOTAL | B12: =SUM(B11) | C12: =SUM(C11) | D12: =SUM(D11) | E12: =SUM(E11) | F12: =SUM(F11) | G12: =SUM(G11) | H12: =SUM(H11) | I12: =SUM(I11) | ... M12: =SUM(M11)

Sheet Sheet7
A1: NIK | B1: Nama | C1: Tgl Masuk | D1: Masa Kerja | E1: Departmen | F1: Section | G1: Jabatan | H1: Jenis Kelamin | I1: PWS | J1: Agama
A2: 328000001 | B2: Rio Gustiawan | C2: 45111 | D2: 2 tahun, 2 bulan, 14 hari | E2: Engineering | F2: Engineering | G2: Utility, Electricity & MHE Maintenance | H2: L | I2: 1ENG4 | J2: ISLAM
A3: 328000004 | B3: Dangis Munggaran | C3: 45166 | D3: 2 tahun, 0 bulan, 21 hari | E3: Engineering | F3: Engineering | G3: Mechanical Machine Maintenance | H3: L | I3: 1ENG2 | J3: ISLAM
A4: 328000005 | B4: Irgi Fauzi | C4: 45166 | D4: 2 tahun, 0 bulan, 21 hari | E4: Engineering | F4: Engineering | G4: Machine Maintenance Shift | H4: L | I4: 4D2 | J4: ISLAM
A5: 328000006 | B5: Rizki | C5: 45166 | D5: 2 tahun, 0 bulan, 21 hari | E5: Engineering | F5: Engineering | G5: Ite Maintenance | H5: L | I5: 1NS1 | J5: ISLAM
A6: 328000008 | B6: Ridho Ramdhan Putra | C6: 45166 | D6: 2 tahun, 0 bulan, 21 hari | E6: Engineering | F6: Engineering | G6: Electricity & Supporting Machine Maintenance | H6: L | I6: 1ENG4 | J6: ISLAM
A7: 328000009 | B7: Rezza Febriana | C7: 45166 | D7: 2 tahun, 0 bulan, 21 hari | E7: Engineering | F7: Engineering | G7: Machine Maintenance Shift | H7: L | I7: 4A2 | J7: ISLAM
A8: 328000010 | B8: Diaz Ghery Juniarsyah | C8: 45166 | D8: 2 tahun, 0 bulan, 21 hari | E8: Engineering | F8: Engineering | G8: Machine Maintenance Shift | H8: L | I8: 4B2 | J8: ISLAM
A9: 328000011 | B9: Deni Kusnadi | C9: 45166 | D9: 2 tahun, 0 bulan, 21 hari | E9: Logistic | F9: Warehouse Sparepart | G9: Admin WSP | H9: L | I9: 4A2 | J9: ISLAM
A10: 328000013 | B10: Adil Sugihartono | C10: 45166 | D10: 2 tahun, 0 bulan, 21 hari | E10: Engineering | F10: Engineering | G10: Fabricator | H10: L | I10: 1ENG3 | J10: ISLAM
A11: 328000016 | B11: Ramdan Abdullah | C11: 45180 | D11: 2 tahun, 0 bulan, 7 hari | E11: Logistic | F11: Timbangan | G11: Admin Timbangan | H11: L | I11: 3D2 | J11: ISLAM
A12: 328000019 | B12: Dadang Saputra | C12: 45180 | D12: 2 tahun, 0 bulan, 7 hari | E12: Production | F12: Production Diapers | G12: Operator Produksi | H12: L | I12: 4B2 | J12: ISLAM
A13: 328000020 | B13: Agus Gunawan | C13: 45180 | D13: 2 tahun, 0 bulan, 7 hari | E13: Production | F13: Production Diapers | G13: Operator Produksi | H13: L | I13: 4A2 | J13: ISLAM
... A132: 328000431 | B132: Sahrul Roy Ramadan | C132: 45919 | D132: #NUM! | E132: Production | F132: Production Diapers | G132: Packer | H132: L | I132: 4B2 | J132: ISLAM
A133: 128000001 | B133: Iman Nurchaedi S. | C133: Production | H133: L | I133: 2NSB1 | J133: Islam
A134: 128000003 | B134: Andre Santosa | C134: Engineering | H134: L | I134: 2NSA1 | J134: Katholik
A135: 128000010 | B135: Dendy Saputra | C135: Production | H135: L | I135: 4C2 | J135: Islam
A136: 128000013 | B136: Aminulloh | C136: Logistic | H136: L | I136: 1NS1 | J136: Islam
A137: 128000017 | B137: Sandi Iswanto | C137: Quality and Research & Development | H137: L | I137: 4A2 | J137: Islam
A138: 128000019 | B138: Yeni Ferianto | C138: Quality and Research & Development | H138: L | I138: 4D2 | J138: Islam
A139: 128000022 | B139: Hendra Setiawan | C139: Production | H139: L | I139: 1NS1 | J139: Islam
A140: 128000023 | B140: Iman Muaimin | C140: Logistic | H140: L | I140: 1NS1 | J140: Islam
A141: 128000024 | B141: Taufik Faturochman | C141: Logistic | H141: L | I141: 1NS1 | J141: Islam
A142: 128000027 | B142: Gembong Hagung Harsanto | C142: Engineering | H142: L | I142: 1NS1 | J142: Islam
A143: 128000029 | B143: Angga Setyawan | C143: Production | H143: L | I143: 4C2 | J143: Islam
A144: 128000030 | B144: Kelik Aji Sambudi | C144: Production | H144: L | I144: 4B2 | J144: Islam
... A176: 128000095 | B176: Ferdiansyah Dwi Pratama | C176: Engineering | H176: L | I176: 1NS1 | J176: Islam

Sheet Pivot Table 3

Sheet Sheet5
A1: No. | B1: NIK | C1: NO KTP | D1: Nama (sesuai KTP) | F1: Sourcing Via | J1: Usia | K1: Jenis Kelamin | L1: Bagian | M1: Group | N1: DEPT | O1: Jabatan | P1: Harian / Borongan | Q1: Alamat KTP | X1: Alamat Domisili | Y1: No. Telepon/ No. HP | Z1: Agama | AA1: Pendidikan | AC1: No. | AD1: NIK | AE1: Nama (sesuai KTP) | AF1: DEPT | AG1: NO. KPJ | AH1: NO. BPJS
E2: Tempat | F2: Join Via | G2: Referensi | H2: Notes | I2: Tanggal | Q2: Alamat KTP | R2: RT | S2: RW | T2: Kode Pos | U2: Kec | V2: Desa | W2: Kabupaten
A3: 1 | B3: 328000001 | C3: 3214031208980001 | D3: RIO GUSTIAWAN | E3: PURWAKARTA | F3: LINK | H3: PT KMJ | I3: 36019 | J3: =DATEDIF(I3, TODAY(), "Y") & " tahun, " & DATEDIF(I3, TODAY(), "YM") & " bulan, " & DATEDIF(I3, TODAY(), "MD") & " hari" | K3: L | L3: ELEKTRIKAL | M3: =VLOOKUP(B3,Sheet21!A:N,14,0) | N3: ENG | O3: Utility, Electricity & MHE Maintenance | P3: HARIAN | Q3: JL KP. BATULAYANG, RT/RW: 006/001, KEL:CIKAOBANDUNG, KEC:JATILUHUR, KAB: PURWAKARTA | R3: 6 | S3: 1 | T3: 17425 | U3: JATILUHUR | V3: CIKAOBANDUNG | W3: PURWAKARTA | X3: JL KP. BATULAYANG, RT/RW: 006/001, KEL:CIKAOBANDUNG, KEC:JATILUHUR, KAB: PURWAKARTA | Y3: 83816355892 | Z3: ISLAM | AA3: SMK | AC3: 1 | AD3: 328000001 | AE3: RIO GUSTIAWAN | AF3: ENGINEERING | AG3: 23108653256 | AH3: 1776133214
A4: =A3+1 | B4: 328000004 | C4: 3214121203980002 | D4: DANGIS MUNGGARAN | E4: PURWAKARTA | F4: SMK 1 PWK | H4: SMKN 1 PURWAKARTA | I4: 35866 | J4: =DATEDIF(I4, TODAY(), "Y") & " tahun, " & DATEDIF(I4, TODAY(), "YM") & " bulan, " & DATEDIF(I4, TODAY(), "MD") & " hari" | K4: L | L4: ENGINEERING | M4: =VLOOKUP(B4,Sheet21!A:N,14,0) | N4: ENG | O4: Mechanical Machine Maintenance | P4: HARIAN | Q4: KP.CISALAK, RT/RW: 016/006, KEL: CILANGKAP, KEC: BABAKANCIKAO, KAB: PURWAKARTA | R4: 16 | S4: 6 | U4: BABAKANCIKAO | V4: CILANGKAP | W4: PURWAKARTA | X4: KP.CISALAK, RT/RW: 016/006, KEL: CILANGKAP, KEC: BABAKANCIKAO, KAB: PURWAKARTA | Y4: 81286184053 | Z4: ISLAM | AA4: SMK | AC4: 2 | AD4: 328000004 | AE4: DANGIS MUNGGARAN | AF4: ENGINEERING | AG4: 23145801371 | AH4: 1662733732
A5: =A4+1 | B5: 328000005 | C5: 3214122203010003 | D5: IRGI FAUZI | E5: PURWAKARTA | F5: SMK 1 PWK | H5: SMKN 1 PURWAKARTA | I5: 36972 | J5: =DATEDIF(I5, TODAY(), "Y") & " tahun, " & DATEDIF(I5, TODAY(), "YM") & " bulan, " & DATEDIF(I5, TODAY(), "MD") & " hari" | K5: L | L5: ENGINEERING | M5: =VLOOKUP(B5,Sheet21!A:N,14,0) | N5: ENG | O5: Machine Maintenance Shift | P5: HARIAN | Q5: KP. WARUNG BUAH, RT/RW 015/006, KEL: HEGARMANAH, KEC: BABAKANCIKAO, KAB: PURWAKARTA | R5: 15 | S5: 6 | U5: BABAKANCIKAO | V5: HEGARMANAH | W5: PURWAKARTA | X5: KP. WARUNG BUAH, RT/RW 015/006, KEL: HEGARMANAH, KEC: BABAKANCIKAO, KAB: PURWAKARTA | Y5: 8814074650 | Z5: ISLAM | AA5: SMK | AC5: 3 | AD5: 328000005 | AE5: IRGI FAUZI | AF5: ENGINEERING | AG5: 23145801637 | AH5: 1523374604
A6: =A5+1 | B6: 328000006 | C6: 3214121502010001 | D6: RIZKI | E6: PURWAKARTA | F6: SMK 1 PWK | H6: SMKN 1 PURWAKARTA | I6: 36937 | J6: =DATEDIF(I6, TODAY(), "Y") & " tahun, " & DATEDIF(I6, TODAY(), "YM") & " bulan, " & DATEDIF(I6, TODAY(), "MD") & " hari" | K6: L | L6: ENGINEERING | M6: =VLOOKUP(B6,Sheet21!A:N,14,0) | N6: ENG | O6: Ite Maintenance | P6: HARIAN | Q6: KP. WARUNG BUAH, RT/RW 004/002, KEL: HEGARMANAH, KEC: BABAKANCIKAO, KAB: PURWAKARTA | R6: 4 | S6: 2 | U6: BABAKANCIKAO | V6: HEGARMANAH | W6: PURWAKARTA | X6: KP. WARUNG BUAH, RT/RW 004/002, KEL: HEGARMANAH, KEC: BABAKANCIKAO, KAB: PURWAKARTA | Y6: 83822668611 | Z6: ISLAM | AA6: SMK | AC6: 4 | AD6: 328000006 | AE6: RIZKI | AF6: ENGINEERING | AG6: 23145801454 | AH6: 2280071349
A7: =A6+1 | B7: 328000008 | C7: 3214121611020008 | D7: RIDHO RAMDHAN PUTRA | E7: PURWAKARTA | F7: SMK 1 PWK | H7: SMKN 1 PURWAKARTA | I7: 37576 | J7: =DATEDIF(I7, TODAY(), "Y") & " tahun, " & DATEDIF(I7, TODAY(), "YM") & " bulan, " & DATEDIF(I7, TODAY(), "MD") & " hari" | K7: L | L7: ENGINEERING | M7: =VLOOKUP(B7,Sheet21!A:N,14,0) | N7: ENG | O7: Electricity & Supporting Machine Maintenance | P7: HARIAN | Q7: KP. WARUNG BUAH, RT/RW 004/002, KEL: HEGARMANAH, KEC: BABAKANCIKAO, KAB: PURWAKARTA | R7: 4 | S7: 2 | U7: BABAKANCIKAO | V7: HEGARMANAH | W7: PURWAKARTA | X7: KP. WARUNG BUAH, RT/RW 004/002, KEL: HEGARMANAH, KEC: BABAKANCIKAO, KAB: PURWAKARTA | Y7: 81383171158 | Z7: ISLAM | AA7: SMK | AC7: 5 | AD7: 328000008 | AE7: RIDHO RAMDHAN PUTRA | AF7: ENGINEERING | AG7: 23145801462 | AH7: 2179461857
A8: =A7+1 | B8: 328000009 | C8: 3214121902010001 | D8: REZZA FEBRIANA | E8: PURWAKARTA | F8: SMK 1 PWK | H8: SMKN 1 PURWAKARTA | I8: 36941 | J8: =DATEDIF(I8, TODAY(), "Y") & " tahun, " & DATEDIF(I8, TODAY(), "YM") & " bulan, " & DATEDIF(I8, TODAY(), "MD") & " hari" | K8: L | L8: ENGINEERING | M8: =VLOOKUP(B8,Sheet21!A:N,14,0) | N8: ENG | O8: Machine Maintenance Shift | P8: HARIAN | Q8: KP. WARUNG BUAH, RT/RW 015/006, KEL: HEGARMANAH, KEC: BABAKANCIKAO, KAB: PURWAKARTA | R8: 15 | S8: 6 | U8: BABAKANCIKAO | V8: HEGARMANAH | W8: PURWAKARTA | X8: KP. WARUNG BUAH, RT/RW 015/006, KEL: HEGARMANAH, KEC: BABAKANCIKAO, KAB: PURWAKARTA | Y8: 83872982687 | Z8: ISLAM | AA8: SMK | AC8: 6 | AD8: 328000009 | AE8: REZZA FEBRIANA | AF8: ENGINEERING | AG8: 23145801496 | AH8: 1010190587
A9: =A8+1 | B9: 328000010 | C9: 3214121606000001 | D9: DIAZ GHERY JUNIARSYAH RAHMAN | E9: PURWAKARTA | F9: SMK 1 PWK | H9: SMKN 1 PURWAKARTA | I9: 36693 | J9: =DATEDIF(I9, TODAY(), "Y") & " tahun, " & DATEDIF(I9, TODAY(), "YM") & " bulan, " & DATEDIF(I9, TODAY(), "MD") & " hari" | K9: L | L9: ENGINEERING | M9: =VLOOKUP(B9,Sheet21!A:N,14,0) | N9: ENG | O9: Machine Maintenance Shift | P9: HARIAN | Q9: KP. WARUNG BUAH, RT/RW 005/006, KEL: HEGARMANAH, KEC: BABAKANCIKAO, KAB: PURWAKARTA | R9: 5 | S9: 6 | U9: BABAKANCIKAO | V9: HEGARMANAH | W9: PURWAKARTA | X9: KP. WARUNG BUAH, RT/RW 005/006, KEL: HEGARMANAH, KEC: BABAKANCIKAO, KAB: PURWAKARTA | Y9: 87827120474 | Z9: ISLAM | AA9: SMK | AC9: 7 | AD9: 328000010 | AE9: DIAZ GHERY JUNIARSYAH RAHMAN | AF9: ENGINEERING | AG9: 23145801546 | AH9: 2394923703
A10: =A9+1 | B10: 328000011 | C10: 3214120211000002 | D10: DENI KUSNADI | E10: PURWAKARTA | F10: SMK 1 PWK | H10: SMKN 1 PURWAKARTA | I10: 36832 | J10: =DATEDIF(I10, TODAY(), "Y") & " tahun, " & DATEDIF(I10, TODAY(), "YM") & " bulan, " & DATEDIF(I10, TODAY(), "MD") & " hari" | K10: L | L10: ENGINEERING | M10: =VLOOKUP(B10,Sheet21!A:N,14,0) | N10: ENG | O10: Admin WSP | P10: HARIAN | Q10: KP. CIKOPAK, RT/RW: 002/001. KEL: MULYAMEKAR, KEC: BABAKANCIKAO, KAB: PURWAKARTA | R10: 2 | S10: 1 | U10: BABAKANCIKAO | V10: MULYAMEKAR | W10: PURWAKARTA | X10: KP. CIKOPAK, RT/RW: 002/001. KEL: MULYAMEKAR, KEC: BABAKANCIKAO, KAB: PURWAKARTA | Y10: 8987463583 | Z10: ISLAM | AA10: SMK | AC10: 8 | AD10: 328000011 | AE10: DENI KUSNADI | AF10: LOGISTIC | AG10: 23145801660 | AH10: 1479299005
A11: =A10+1 | B11: 328000013 | C11: 3214120509990007 | D11: ADIL SUGIHARTONO | E11: PURWAKARTA | F11: TKD | G11: Karang Taruna Hegarmanah | H11: ANAK MANTAN KETUA KARANG TARUNA HEGARMANAH | I11: 36408 | J11: =DATEDIF(I11, TODAY(), "Y") & " tahun, " & DATEDIF(I11, TODAY(), "YM") & " bulan, " & DATEDIF(I11, TODAY(), "MD") & " hari" | K11: L | L11: ENGINEERING | M11: =VLOOKUP(B11,Sheet21!A:N,14,0) | N11: ENG | O11: Fabricator | P11: HARIAN | Q11: KP. WARUNG BUAH, RT/RW 003/002, KEL: HEGARMANAH, KEC: BABAKANCIKAO, KAB: PURWAKARTA | R11: 3 | S11: 2 | U11: BABAKANCIKAO | V11: HEGARMANAH | W11: PURWAKARTA | X11: KP. WARUNG BUAH, RT/RW 003/002, KEL: HEGARMANAH, KEC: BABAKANCIKAO, KAB: PURWAKARTA | Y11: 81994667058 | Z11: ISLAM | AA11: SMK | AC11: 9 | AD11: 328000013 | AE11: ADIL SUGIHARTONO | AF11: ENGINEERING | AG11: 23145801629 | AH11: 2394922779
A12: =A11+1 | B12: 328000016 | C12: 3214122710990001 | D12: RAMDAN ABDULLAH | E12: PURWAKARTA | F12: SMK 1 PWK | H12: SMKN 1 PURWAKARTA | I12: 36460 | J12: =DATEDIF(I12, TODAY(), "Y") & " tahun, " & DATEDIF(I12, TODAY(), "YM") & " bulan, " & DATEDIF(I12, TODAY(), "MD") & " hari" | K12: L | L12: ADMIN TIMBANGAN | M12: =VLOOKUP(B12,Sheet21!A:N,14,0) | N12: LOGISTIK | O12: Admin Timbangan | P12: HARIAN | Q12: KP. PARUNGDADAP, RT/RW: 002/001, KEL: HEGARMANAH, KEC: BABAKANCIKAO, KAB: PURWAKARTA | R12: 2 | S12: 1 | U12: BABAKANCIKAO | V12: HEGARMANAH | W12: PURWAKARTA | X12: KP. PARUNGDADAP, RT/RW: 002/001, KEL: HEGARMANAH, KEC: BABAKANCIKAO, KAB: PURWAKARTA | Y12: 87821754674 | Z12: ISLAM | AA12: SMK | AC12: 10 | AD12: 328000016 | AE12: RAMDAN ABDULLAH | AF12: LOGISTIC | AG12: 23145801587 | AH12: 1659942033
A13: =A12+1 | B13: 328000017 | C13: 3214031512970001 | D13: DADI SETIADI | E13: PURWAKARTA | F13: LINK | H13: PT KMJ | I13: 35779 | J13: =DATEDIF(I13, TODAY(), "Y") & " tahun, " & DATEDIF(I13, TODAY(), "YM") & " bulan, " & DATEDIF(I13, TODAY(), "MD") & " hari" | K13: L | L13: OP FORKLIFT WRM | M13: =VLOOKUP(B13,Sheet21!A:N,14,0) | N13: LOGISTIK | O13: Operator Forklift | P13: HARIAN | Q13: KP. CILULUNGPANG, RT/RW: 012/003, KEL: JATIMEKAR, KEC JATILUHUR, KAB: PURWAKARTA | R13: 12 | S13: 3 | U13: JATILUHUR | V13: JATILUHUR | W13: PURWAKARTA | X13: KP. CILULUNGPANG, RT/RW: 012/003, KEL: JATIMEKAR, KEC JATILUHUR, KAB: PURWAKARTA | Y13: 85860498887 | Z13: ISLAM | AA13: SMK | AC13: 11 | AD13: 328000017 | AE13: DADI SETIADI | AF13: LOGISTIC | AG13: 23145801421 | AH13: 1654456083
A14: =A13+1 | B14: 328000018 | C14: 3214124208040001 | D14: NEVANY PUTRI | E14: PURWAKARTA | F14: SMK 1 PWK | H14: SMKN 1 PURWAKARTA | I14: 38201 | J14: =DATEDIF(I14, TODAY(), "Y") & " tahun, " & DATEDIF(I14, TODAY(), "YM") & " bulan, " & DATEDIF(I14, TODAY(), "MD") & " hari" | K14: P | L14: ADMIN WRM | M14: =VLOOKUP(B14,Sheet21!A:N,14,0) | N14: LOGISTIK | O14: Admin WRM | P14: HARIAN | Q14: KP. HEGARMANAH, RT/RW: 012/005, KEL:HEGARMANAH, KEC: BABAKANCIKAO, KAB: PURWAKARTA | R14: 12 | S14: 5 | U14: BABAKANCIKAO | V14: HEGARMANAH | W14: PURWAKARTA | X14: KP. HEGARMANAH, RT/RW: 012/005, KEL:HEGARMANAH, KEC: BABAKANCIKAO, KAB: PURWAKARTA | Y14: 81992210155 | Z14: ISLAM | AA14: SMK | AC14: 12 | AD14: 328000018 | AE14: NEVANY PUTRI | AF14: LOGISTIC | AG14: 23145801645 | AH14: 1189240209
A15: =A14+1 | B15: 328000019 | C15: 3214121410970002 | D15: DADANG SAPUTRA | E15: PURWAKARTA | F15: SMK 1 PWK | H15: SMKN 1 PURWAKARTA | I15: 35717 | J15: =DATEDIF(I15, TODAY(), "Y") & " tahun, " & DATEDIF(I15, TODAY(), "YM") & " bulan, " & DATEDIF(I15, TODAY(), "MD") & " hari" | K15: L | L15: OP. PRODUKSI | M15: =VLOOKUP(B15,Sheet21!A:N,14,0) | N15: PRODUKSI | O15: Operator Produksi | P15: HARIAN | Q15: KP. KARAJAN, RT/RW: 002/001, KEL: BABAKANCIKAO, KEC: BABAKANCIKAO, KAB: PURWAKARTA | R15: 2 | S15: 1 | U15: BABAKANCIKAO | V15: BABAKANCIKAO | W15: PURWAKARTA | X15: KP. KARAJAN, RT/RW: 002/001, KEL: BABAKANCIKAO, KEC: BABAKANCIKAO, KAB: PURWAKARTA | Y15: 81394594108 | Z15: ISLAM | AA15: SMK | AC15: 13 | AD15: 328000019 | AE15: DADANG SAPUTRA | AF15: PRODUCTION | AG15: 23145801447 | AH15: 481312416
A16: =A15+1 | B16: 328000020 | C16: 3214121608030003 | D16: AGUS GUNAWAN | E16: PURWAKARTA | F16: LINK | H16: PT KMJ | I16: 37849 | J16: =DATEDIF(I16, TODAY(), "Y") & " tahun, " & DATEDIF(I16, TODAY(), "YM") & " bulan, " & DATEDIF(I16, TODAY(), "MD") & " hari" | K16: L | L16: OP. PRODUKSI | M16: =VLOOKUP(B16,Sheet21!A:N,14,0) | N16: PRODUKSI | O16: Operator Produksi | P16: HARIAN | Q16: KP. GANDASARI, RT/RW: 003/001, KEL: CIGELAM, KEC: BABAKANCIKAO, KAB:PURWAKARTA | R16: 3 | S16: 1 | U16: BABAKANCIKAO | V16: CIGELAM | W16: PURWAKARTA | X16: KP. GANDASARI, RT/RW: 003/001, KEL: CIGELAM, KEC: BABAKANCIKAO, KAB:PURWAKARTA | Y16: 82124130479 | Z16: ISLAM | AA16: SMK | AC16: 14 | AD16: 328000020 | AE16: AGUS GUNAWAN | AF16: PRODUCTION | AG16: 23145801504 | AH16: 481572088
A17: =A16+1 | B17: 328000022 | C17: 3214120606040005 | D17: AZHAR AIZAD ALFARIDZI | E17: PURWAKARTA | F17: LINK | H17: PT KMJ | I17: 38144 | J17: =DATEDIF(I17, TODAY(), "Y") & " tahun, " & DATEDIF(I17, TODAY(), "YM") & " bulan, " & DATEDIF(I17, TODAY(), "MD") & " hari" | K17: L | L17: OP. PRODUKSI | M17: =VLOOKUP(B17,Sheet21!A:N,14,0) | N17: PRODUKSI | O17: Operator Produksi | P17: HARIAN | Q17: KP. KRAJAN, RT/RW: 011/003, KEL: MARACANG, KEC: BABAKANCIKAO, KAB: PURWAKARTA | R17: 11 | S17: 3 | U17: BABAKANCIKAO | V17: MARACANG | W17: PURWAKARTA | X17: KP. KRAJAN, RT/RW: 011/003, KEL: MARACANG, KEC: BABAKANCIKAO, KAB: PURWAKARTA | Y17: 81389119714 | Z17: ISLAM | AA17: SMK | AC17: 15 | AD17: 328000022 | AE17: AZHAR AIZAD ALFARIDZI | AF17: PRODUCTION | AG17: 23145801652 | AH17: 1633523084
A18: =A17+1 | B18: 328000023 | C18: 3214120703990001 | D18: KEPIN NUGRAHA | E18: PURWAKARTA | F18: LINK | H18: PT KMJ | I18: 36226 | J18: =DATEDIF(I18, TODAY(), "Y") & " tahun, " & DATEDIF(I18, TODAY(), "YM") & " bulan, " & DATEDIF(I18, TODAY(), "MD") & " hari" | K18: L | L18: OP. PRODUKSI | M18: =VLOOKUP(B18,Sheet21!A:N,14,0) | N18: PRODUKSI | O18: Operator Produksi | P18: HARIAN | Q18: KP. HEGARMANAH, RT/RW: 015/005, KEL:HEGARMANAH, KEC: BABAKANCIKAO, KAB: PURWAKARTA | R18: 15 | S18: 5 | U18: BABAKANCIKAO | V18: HEGARMANAH | W18: PURWAKARTA | X18: KP. HEGARMANAH, RT/RW: 015/005, KEL:HEGARMANAH, KEC: BABAKANCIKAO, KAB: PURWAKARTA | Y18: 81904860627 | Z18: ISLAM | AA18: SMK | AC18: 16 | AD18: 328000023 | AE18: KEPIN NUGRAHA | AF18: PRODUCTION | AG18: 23145801710 | AH18: 2394923444
A19: =A18+1 | B19: 328000024 | C19: 3214121205990002 | D19: ARUL MEILANA | E19: PURWAKARTA | F19: TKD | G19: Pak Wahyudin | H19: ANAKANYA PAK OLAN KARANG TARUNA BABAKANCIKAO | I19: 36292 | J19: =DATEDIF(I19, TODAY(), "Y") & " tahun, " & DATEDIF(I19, TODAY(), "YM") & " bulan, " & DATEDIF(I19, TODAY(), "MD") & " hari" | K19: L | L19: OP. PRODUKSI | M19: =VLOOKUP(B19,Sheet21!A:N,14,0) | N19: PRODUKSI | O19: Operator Produksi | P19: HARIAN | Q19: KP. KRAJAN, RT/RW: 007/003, KEL: BABAKANCIKAO, KEC: BABAKANCIKAO, KAB: PURWAKARTA | R19: 7 | S19: 3 | U19: BABAKANCIKAO | V19: BABAKANCIKAO | W19: PURWAKARTA | X19: KP. KRAJAN, RT/RW: 007/003, KEL: BABAKANCIKAO, KEC: BABAKANCIKAO, KAB: PURWAKARTA | Y19: 85659593830 | Z19: ISLAM | AA19: SMK | AC19: 17 | AD19: 328000024 | AE19: ARUL MEILANA | AF19: PRODUCTION | AG19: 23145801397 | AH19: 1662734698
A20: =A19+1 | B20: 328000026 | C20: 3214122012970003 | D20: DEDE WAHYUDIN | E20: PURWAKARTA | F20: SMK 1 PWK | H20: SMKN 1 PURWAKARTA | I20: 35784 | J20: =DATEDIF(I20, TODAY(), "Y") & " tahun, " & DATEDIF(I20, TODAY(), "YM") & " bulan, " & DATEDIF(I20, TODAY(), "MD") & " hari" | K20: L | L20: OP. PRODUKSI | M20: =VLOOKUP(B20,Sheet21!A:N,14,0) | N20: PRODUKSI | O20: Operator Produksi | P20: HARIAN | Q20: KP. PARUNGDADAP, RT/RW: 002/001, KEL: HEGARMANAH, KEC: BABAKANCIKAO, KAB: PURWAKARTA | R20: 2 | S20: 1 | U20: BABAKANCIKAO | V20: HEGARMANAH | W20: PURWAKARTA | X20: KP. PARUNGDADAP, RT/RW: 002/001, KEL: HEGARMANAH, KEC: BABAKANCIKAO, KAB: PURWAKARTA | Y20: 87805771388 | Z20: ISLAM | AA20: SMK | AC20: 18 | AD20: 328000026 | AE20: DEDE WAHYUDIN | AF20: PRODUCTION | AG20: 23145801611 | AH20: 1661920367
A21: =A20+1 | B21: 328000027 | C21: 3214122710000001 | D21: GIGIN GINANJAR | E21: PURWAKARTA | F21: LINK | H21: PT KMJ | I21: 36826 | J21: =DATEDIF(I21, TODAY(), "Y") & " tahun, " & DATEDIF(I21, TODAY(), "YM") & " bulan, " & DATEDIF(I21, TODAY(), "MD") & " hari" | K21: L | L21: OP. PRODUKSI | M21: =VLOOKUP(B21,Sheet21!A:N,14,0) | N21: PRODUKSI | O21: Operator Produksi | P21: HARIAN | Q21: KP. HEGARMANAH, RT/RW: 009/004, KEL: HEGARMANAH, KEC: BABAKANCIKAO, KAB: PURWAKARTA | R21: 9 | S21: 4 | U21: BABAKANCIKAO | V21: HEGARMANAH | W21: PURWAKARTA | X21: KP. HEGARMANAH, RT/RW: 009/004, KEL: HEGARMANAH, KEC: BABAKANCIKAO, KAB: PURWAKARTA | Y21: 85975256235 | Z21: ISLAM | AA21: SMK | AC21: 19 | AD21: 328000027 | AE21: GIGIN GINANJAR | AF21: PRODUCTION | AG21: 23145801520 | AH21: 2441918799
A22: =A21+1 | B22: 328000028 | C22: 3214120901980005 | D22: TISNA GINANJAR | E22: PURWAKARTA | F22: TKD | G22: Karang Taruna Hegarmanah | H22: DARI SMK 1 PURWAKARTA | I22: 35804 | J22: =DATEDIF(I22, TODAY(), "Y") & " tahun, " & DATEDIF(I22, TODAY(), "YM") & " bulan, " & DATEDIF(I22, TODAY(), "MD") & " hari" | K22: L | L22: OP. PRODUKSI | M22: =VLOOKUP(B22,Sheet21!A:N,14,0) | N22: PRODUKSI | O22: Operator Produksi | P22: HARIAN | Q22: KP. WARUNGBUAH, RT/RW: 003/002, KEL: HEGARMANANAH, KEC: BABAKANCIKAO, KAB: PURWAKARTA | R22: 3 | S22: 2 | U22: BABAKANCIKAO | V22: HEGARMANAH | W22: PURWAKARTA | X22: KP. WARUNGBUAH, RT/RW: 003/002, KEL: HEGARMANANAH, KEC: BABAKANCIKAO, KAB: PURWAKARTA | Y22: 87848729995 | Z22: ISLAM | AA22: SMK | AC22: 20 | AD22: 328000028 | AE22: TISNA GINANJAR | AF22: PRODUCTION | AG22: 23145801678 | AH22: 1182631015
A23: =A22+1 | B23: 328000030 | C23: 3214012312040001 | D23: DAVA PUTRA YUDIANSYAH | E23: PURWAKARTA | F23: TKD | G23: Kades Hegarmanah | H23: MENANTU ANGGOTA BPD HEGARMANAH | I23: 38344 | J23: =DATEDIF(I23, TODAY(), "Y") & " tahun, " & DATEDIF(I23, TODAY(), "YM") & " bulan, " & DATEDIF(I23, TODAY(), "MD") & " hari" | K23: L | L23: OP. PRODUKSI | M23: =VLOOKUP(B23,Sheet21!A:N,14,0) | N23: PRODUKSI | O23: Operator Produksi | P23: HARIAN | Q23: KP. KARANGSARI, RT/RW: 009/002, KEL: CITALANG, KEC: PURWAKARTA, KAB : PURWAKARTA | R23: 9 | S23: 2 | U23: PURWAKARTA | V23: CITALANG | W23: PURWAKARTA | X23: KP. KARANGSARI, RT/RW: 009/002, KEL: CITALANG, KEC: PURWAKARTA, KAB : PURWAKARTA | Y23: 81573273756 | Z23: ISLAM | AA23: SMK | AC23: 21 | AD23: 328000030 | AE23: DAVA PUTRA YUDIANSYAH | AF23: PRODUCTION | AG23: 23145801553 | AH23: 3561017027
A24: =A23+1 | B24: 328000032 | C24: 3214120103010005 | D24: RUBY SUBASTIAN | E24: PURWAKARTA | F24: SMK 1 PWK | H24: SMKN 1 PURWAKARTA | I24: 36951 | J24: =DATEDIF(I24, TODAY(), "Y") & " tahun, " & DATEDIF(I24, TODAY(), "YM") & " bulan, " & DATEDIF(I24, TODAY(), "MD") & " hari" | K24: L | L24: OP. PRODUKSI | M24: =VLOOKUP(B24,Sheet21!A:N,14,0) | N24: PRODUKSI | O24: Operator Produksi | P24: HARIAN | Q24: KP.NAGRAK RT/RW: 002/001, KEL: CICADAS, KEC: BABAKANCIKAO, KAB: PURWAKARTA | R24: 2 | S24: 3 | U24: BABAKANCIKAO | V24: CICADAS | W24: PURWAKARTA | X24: KP.NAGRAK RT/RW: 002/001, KEL: CICADAS, KEC: BABAKANCIKAO, KAB: PURWAKARTA | Y24: 83128938031 | Z24: ISLAM | AA24: SMK | AC24: 22 | AD24: 328000032 | AE24: RUBY SUBASTIAN | AF24: PRODUCTION | AG24: 23145801603 | AH24: 1523375076
A25: =A24+1 | B25: 328000033 | C25: 3214120305040002 | D25: HENDRA | E25: PURWAKARTA | F25: SMK 1 PWK | H25: SMKN 1 PURWAKARTA | I25: 38110 | J25: =DATEDIF(I25, TODAY(), "Y") & " tahun, " & DATEDIF(I25, TODAY(), "YM") & " bulan, " & DATEDIF(I25, TODAY(), "MD") & " hari" | K25: L | L25: OP. PRODUKSI | M25: =VLOOKUP(B25,Sheet21!A:N,14,0) | N25: PRODUKSI | O25: Operator Produksi | P25: HARIAN | Q25: KP. BAYUR, RT/RW: 006/003, KEL: HEGARMANAH, KEC: BABAKANCIKAO, KAB: PURWAKARTA | R25: 6 | S25: 3 | U25: BABAKANCIKAO | V25: HEGARMANAH | W25: PURWAKARTA | X25: KP. BAYUR, RT/RW: 006/003, KEL: HEGARMANAH, KEC: BABAKANCIKAO, KAB: PURWAKARTA | Y25: 83816579615 | Z25: ISLAM | AA25: SMK | AC25: 23 | AD25: 328000033 | AE25: HENDRA | AF25: PRODUCTION | AG25: 23145801405 | AH25: 480652446
A26: =A25+1 | B26: 328000036 | C26: 3214122203010002 | D26: FESAL FAUZAN | E26: PURWAKARTA | F26: SMK 1 PWK | H26: SMKN 1 PURWAKARTA | I26: 37156 | J26: =DATEDIF(I26, TODAY(), "Y") & " tahun, " & DATEDIF(I26, TODAY(), "YM") & " bulan, " & DATEDIF(I26, TODAY(), "MD") & " hari" | K26: L | L26: OP. PRODUKSI | M26: =VLOOKUP(B26,Sheet21!A:N,14,0) | N26: PRODUKSI | O26: Operator Produksi | P26: HARIAN | Q26: KP. WARUNGBUAH, RT/RW: 015/006, KEL: HEGARMANANAH, KEC: BABAKANCIKAO, KAB: PURWAKARTA | R26: 15 | S26: 6 | U26: BABAKANCIKAO | V26: HEGARMANAH | W26: PURWAKARTA | X26: KP. WARUNGBUAH, RT/RW: 015/006, KEL: HEGARMANANAH, KEC: BABAKANCIKAO, KAB: PURWAKARTA | Y26: 881023479878 | Z26: ISLAM | AA26: SMK | AC26: 24 | AD26: 328000036 | AE26: FESAL FAUZAN | AF26: PRODUCTION | AG26: 23145801561 | AH26: 1523374593
A27: =A26+1 | B27: 328000037 | C27: 3214121806050002 | D27: KURNIADI | E27: PURWAKARTA | F27: SMK 1 PWK | H27: SMKN 1 PURWAKARTA | I27: 38551 | J27: =DATEDIF(I27, TODAY(), "Y") & " tahun, " & DATEDIF(I27, TODAY(), "YM") & " bulan, " & DATEDIF(I27, TODAY(), "MD") & " hari" | K27: L | L27: OP. PRODUKSI | M27: =VLOOKUP(B27,Sheet21!A:N,14,0) | N27: PRODUKSI | O27: Operator Produksi | P27: HARIAN | Q27: KP. BAYUR, RT/RW: 007/003, KEL: HEGARMANAH, KEC: BABAKANCIKAO, KAB: PURWAKARTA | R27: 7 | S27: 3 | U27: BABAKANCIKAO | V27: HEGARMANAH | W27: PURWAKARTA | X27: KP. BAYUR, RT/RW: 007/003, KEL: HEGARMANAH, KEC: BABAKANCIKAO, KAB: PURWAKARTA | Y27: 881022424333 | Z27: ISLAM | AA27: SMK | AC27: 25 | AD27: 328000037 | AE27: KURNIADI | AF27: PRODUCTION | AG27: 23145801439 | AH27: 2177064821
A28: =A27+1 | B28: 328000038 | C28: 3214124502040001 | D28: MESTHY PEBRIYANTI | E28: PURWAKARTA | F28: SMK 1 PWK | H28: SMKN 1 PURWAKARTA | I28: 38022 | J28: =DATEDIF(I28, TODAY(), "Y") & " tahun, " & DATEDIF(I28, TODAY(), "YM") & " bulan, " & DATEDIF(I28, TODAY(), "MD") & " hari" | K28: P | L28: QUALITY CONTROL | M28: =VLOOKUP(B28,Sheet21!A:N,14,0) | N28: QC | O28: QC Lab | P28: HARIAN | Q28: KP. BAYUR, RT/RW: 08/03, DESA HEGARMANAH, KEC. BABAKANCIKAO, KAB. PURWAKARTA | R28: 8 | S28: 3 | T28: 41151 | U28: BABAKANCIKAO | V28: HEGARMANAH | W28: PURWAKARTA | X28: JL. INDUSTRI, KP. BAYUR, RT/RW.08/03, HEGARMANAH, BABAKANCIKAO, PURWAKARTA | Y28: 81385652728 | Z28: ISLAM | AA28: SMK | AC28: 26 | AD28: 328000038 | AE28: MESTHY PEBRIYANTI | AF28: QUALITY AND RESEARCH & DEVELOPMENT | AG28: 23165960875 | AH28: 2519570823
A29: =A28+1 | B29: 328000039 | C29: 3216026403000013 | D29: DESTY MARLIANI | E29: BEKASI | F29: LINK | H29: Ex AMG | I29: 36609 | J29: =DATEDIF(I29, TODAY(), "Y") & " tahun, " & DATEDIF(I29, TODAY(), "YM") & " bulan, " & DATEDIF(I29, TODAY(), "MD") & " hari" | K29: P | L29: QUALITY CONTROL | M29: =VLOOKUP(B29,Sheet21!A:N,14,0) | N29: QC | O29: QC Lab | P29: HARIAN | Q29: KP JATI, RT/RW: 003/015, KEL: KEBALEN, KEC: BABELAN KAB: BEKASI | R29: 3 | S29: 15 | U29: BABELAN | V29: KEBALEN | W29: BEKASI | X29: KP JATI, RT/RW: 003/015, KEL: KEBALEN, KEC: BABELAN KAB: BEKASI | Y29: 895602305411 | Z29: ISLAM | AA29: SMA | AC29: 27 | AD29: 328000039 | AE29: DESTY MARLIANI | AF29: QUALITY AND RESEARCH & DEVELOPMENT | AG29: 23165960677 | AH29: 1011888134
A30: =A29+1 | B30: 328000040 | C30: 3205252303960001 | D30: ASEP KAMALUDIN | E30: GARUT | F30: LINK | H30: Ex AMG | I30: 35178 | J30: =DATEDIF(I30, TODAY(), "Y") & " tahun, " & DATEDIF(I30, TODAY(), "YM") & " bulan, " & DATEDIF(I30, TODAY(), "MD") & " hari" | K30: L | L30: QUALITY PATROL | M30: =VLOOKUP(B30,Sheet21!A:N,14,0) | N30: QC | O30: QC Patrol | P30: HARIAN | Q30: KP. CISANGKAL, RT/RW: 001/003, KEL: CIHURIP, KEC: CISANGKAL, KAB: GARUT | R30: 1 | S30: 3 | U30: CISANGKAL | V30: CIHURIP | W30: GARUT | X30: KP. CISANGKAL, RT/RW. 001/003, KEL. CIHURIP, KEL. CISANGKAL, KAB. GARUT | Y30: 81219699174 | Z30: ISLAM | AA30: SMK | AC30: 28 | AD30: 328000040 | AE30: ASEP KAMALUDIN | AF30: QUALITY AND RESEARCH & DEVELOPMENT | AG30: 23165961220 | AH30: 422142884
A31: =A30+1 | B31: 328000041 | C31: 3214015808040007 | D31: BUNGA ADELIYA | E31: PURWAKARTA | F31: TKD | G31: Pak Wahyudin | H31: KEPONAKAN PAK WAHYUDIN | I31: 38217 | J31: =DATEDIF(I31, TODAY(), "Y") & " tahun, " & DATEDIF(I31, TODAY(), "YM") & " bulan, " & DATEDIF(I31, TODAY(), "MD") & " hari" | K31: P | L31: PACKER | M31: =VLOOKUP(B31,Sheet21!A:N,14,0) | N31: PRODUKSI | O31: Packer | P31: HARIAN | Q31: JL.LODAYA KP.BARU, RT/TW: 002/001, KEL: NAGRI TENGAH, KEC: PURWAKARTA, KAB: PURWAKARTA | R31: 2 | S31: 1 | T31: 41115 | U31: PURWAKARTA | V31: NAGRI TENGAH | W31: PURWAKARTA | X31: JL.LODAYA KP.BARU, RT/TW: 002/001, KEL: NAGRI TENGAH, KEC: PURWAKARTA, KAB: PURWAKARTA | Y31: 8997090942 | Z31: ISLAM | AA31: SMA | AC31: 29 | AD31: 328000041 | AE31: BUNGA ADELIYA | AF31: PRODUCTION | AG31: 23165960602 | AH31: 1659877817
A32: =A31+1 | B32: 328000042 | C32: 3214126006040001 | D32: CINDY AMELIA | E32: PURWAKARTA | F32: SMK 1 PWK | H32: SMKN 1 PURWAKARTA | I32: 38158 | J32: =DATEDIF(I32, TODAY(), "Y") & " tahun, " & DATEDIF(I32, TODAY(), "YM") & " bulan, " & DATEDIF(I32, TODAY(), "MD") & " hari" | K32: P | L32: PACKER | M32: =VLOOKUP(B32,Sheet21!A:N,14,0) | N32: PRODUKSI | O32: Packer | P32: HARIAN | Q32: KP. BAYUR, RT/RW: 006/003, KEL: HEGARMANAH, KEC: BABAKANCIKAO, KAB: PURWAKARTA | R32: 6 | S32: 3 | U32: BABAKANCIKAO | V32: HEGARMANAH | W32: PURWAKARTA | X32: KP. BAYUR, RT/RW: 006/003, KEL: HEGARMANAH, KEC: BABAKANCIKAO, KAB: PURWAKARTA | Y32: 89687962574 | Z32: ISLAM | AA32: SMK | AC32: 30 | AD32: 328000042 | AE32: CINDY AMELIA | AF32: PRODUCTION | AG32: 23165960909 | AH32: 2394908763
A33: =A32+1 | B33: 328000043 | C33: 3214126211020002 | D33: ANDINI NOVIA RAMADANI | E33: PURWAKARTA | F33: SMK 1 PWK | H33: SMKN 1 PURWAKARTA | I33: 37582 | J33: =DATEDIF(I33, TODAY(), "Y") & " tahun, " & DATEDIF(I33, TODAY(), "YM") & " bulan, " & DATEDIF(I33, TODAY(), "MD") & " hari" | K33: P | L33: PACKER | M33: =VLOOKUP(B33,Sheet21!A:N,14,0) | N33: PRODUKSI | O33: Packer | P33: HARIAN | Q33: KP. RAWABOLANG, RT/RW:023/007, KEL: MARACANG, KEC: BABKANCIKAO, KAB PURWAKARTA | R33: 23 | S33: 7 | T33: 41151 | U33: BABAKANCIKAO | V33: MARACANG | W33: PURWAKARTA | X33: KP. RAWABOLANG, RT/RW:023/007, KEL: MARACANG, KEC: BABKANCIKAO, KAB PURWAKARTA | Y33: 89616721122 | Z33: ISLAM | AA33: SMK | AC33: 31 | AD33: 328000043 | AE33: ANDINI NOVIA RAMADANI | AF33: PRODUCTION | AG33: 23165961170 | AH33: 481262567
A34: =A33+1 | B34: 328000047 | C34: 3275064402020004 | D34: SITI RACHMAH | E34: BEKASI | F34: LINK | H34: Ex AMG | I34: 37291 | J34: =DATEDIF(I34, TODAY(), "Y") & " tahun, " & DATEDIF(I34, TODAY(), "YM") & " bulan, " & DATEDIF(I34, TODAY(), "MD") & " hari" | K34: P | L34: PACKER | M34: =VLOOKUP(B34,Sheet21!A:N,14,0) | N34: PRODUKSI | O34: Packer | P34: HARIAN | Q34: KA BAHAGIA, RT/RW : 002/004, KEL : PEJUANG, KEC : MEDAN SATRIA KOTA BEKASI | R34: 2 | S34: 4 | U34: MEDAN SATRIA | V34: PEJUANG | W34: KOTA BEKASI | X34: KA BAHAGIA, RT/RW : 002/004, KEL : PEJUANG, KEC : MEDAN SATRIA | Y34: 895323389885 | Z34: ISLAM | AA34: SMK | AC34: 32 | AD34: 328000047 | AE34: SITI RACHMAH | AF34: PRODUCTION | AG34: 23165960768 | AH34: 1622134214
A35: =A34+1 | B35: 328000049 | C35: 3207106701010001 | D35: SRI HERAWATI | E35: CIAMIS | F35: LINK | H35: Ex AMG | I35: 36918 | J35: =DATEDIF(I35, TODAY(), "Y") & " tahun, " & DATEDIF(I35, TODAY(), "YM") & " bulan, " & DATEDIF(I35, TODAY(), "MD") & " hari" | K35: P | L35: PACKER | M35: =VLOOKUP(B35,Sheet21!A:N,14,0) | N35: PRODUKSI | O35: Packer | P35: HARIAN | Q35: DUSUN MANIS, RT/RW: 003/002, KEL: SAGALA HERANG, KEC: PANAWANGAN, KAB: CIAMIS | R35: 3 | S35: 2 | U35: PANAWANGAN | V35: SAGALAHERANG | W35: CIAMIS | X35: DUSUN MANIS, RT/RW: 003/002, KEL: SAGALA HERANG, KEC: PANAWANGAN, KAB: CIAMIS | Y35: 83827774899 | Z35: ISLAM | AA35: SMK | AC35: 33 | AD35: 328000049 | AE35: SRI HERAWATI | AF35: PRODUCTION | AG35: 23165960651 | AH35: 1006199875
A36: =A35+1 | B36: 328000051 | C36: 3303184306020001 | D36: YUNI WULANDARI | E36: PURBALINGGA | F36: LINK | H36: Ex AMG | I36: 37410 | J36: =DATEDIF(I36, TODAY(), "Y") & " tahun, " & DATEDIF(I36, TODAY(), "YM") & " bulan, " & DATEDIF(I36, TODAY(), "MD") & " hari" | K36: P | L36: PACKER | M36: =VLOOKUP(B36,Sheet21!A:N,14,0) | N36: PRODUKSI | O36: Packer | P36: HARIAN | Q36: CONDONG, RT/RW: 007/001, KEL: CONDONG, KEC: KERTANEGARA, KAB: PURBALINGGA | R36: 7 | S36: 1 | U36: KERTANEGARA | V36: CONDONG | W36: PURBALINGGA | X36: CONDONG, RT/RW: 007/001, KEL: CONDONG, KEC: KERTANEGARA, KAB: PURBALINGGA | Y36: 85647858336 | Z36: ISLAM | AA36: SMK | AC36: 34 | AD36: 328000051 | AE36: YUNI WULANDARI | AF36: PRODUCTION | AG36: 23165960982 | AH36: 1017490768
A37: =A36+1 | B37: 328000052 | C37: 3214121105980002 | D37: DIMAS NUGROHO | E37: BEKASI | F37: TKD | G37: Pak Wahyudin | H37: TITIPAN KARANG TARUNA HEGARMANAH | I37: 35926 | J37: =DATEDIF(I37, TODAY(), "Y") & " tahun, " & DATEDIF(I37, TODAY(), "YM") & " bulan, " & DATEDIF(I37, TODAY(), "MD") & " hari" | K37: L | L37: ADMIN WSP | M37: =VLOOKUP(B37,Sheet21!A:N,14,0) | N37: ENG | O37: Admin WSP | P37: HARIAN | Q37: KP. PARUNG DADAP RT/RW:001/001 DESA HEGARMANAH, KEC. BABAKANCIKAO, KAB. PURWAKARTA | R37: 1 | S37: 1 | T37: 41151 | U37: BABAKANCIKAO | V37: HEGARMANAH | W37: PURWAKARTA | X37: KP. PARUNG DADAP RT/RW:001/001 DESA HEGARMANAH, KEC. BABAKANCIKAO, KAB. PURWAKARTA | Y37: 89658115353 | Z37: ISLAM | AA37: SMK | AC37: 35 | AD37: 328000052 | AE37: DIMAS NUGROHO | AF37: LOGISTIC | AG37: 23165960883 | AH37: 1883668983
A38: =A37+1 | B38: 328000053 | C38: 1216064401970002 | D38: VERA PURBA | E38: TOMUAN NAULI | F38: LINK | H38: Ex AMG | I38: 35434 | J38: =DATEDIF(I38, TODAY(), "Y") & " tahun, " & DATEDIF(I38, TODAY(), "YM") & " bulan, " & DATEDIF(I38, TODAY(), "MD") & " hari" | K38: P | L38: ADM PRODUKSI | M38: =VLOOKUP(B38,Sheet21!A:N,14,0) | N38: PRODUKSI | O38: Admin Produksi | P38: HARIAN | Q38: PERUM BUMI HEGAR ASIH CIMAUNG JLN. ANGGREK 3 NO:61, RT/RW: 006/008, KEL: CISEUREUH, KEC: PURWAKARTA, KAB: PURWAKARTA | R38: 6 | S38: 8 | U38: PURWAKARTA | V38: CISEUREUH | W38: PURWAKARTA | X38: PERUM BUMI HEGAR ASIH CIMAUNG JLN. ANGGREK 3 NO:61, RT/RW: 006/008, KEL: CISEUREUH, KEC: PURWAKARTA, KAB: PURWAKARTA | Y38: 81382137201 | Z38: KRISTEN | AA38: S1 | AC38: 36 | AD38: 328000053 | AE38: VERA PURBA | AF38: PRODUCTION | AG38: 23165960693 | AH38: 2940886157
A39: =A38+1 | B39: 328000054 | C39: 3275067010990013 | D39: CHIKA PITALOKA | E39: BEKASI | F39: LINK | H39: Ex AMG | I39: 36464 | J39: =DATEDIF(I39, TODAY(), "Y") & " tahun, " & DATEDIF(I39, TODAY(), "YM") & " bulan, " & DATEDIF(I39, TODAY(), "MD") & " hari" | K39: P | L39: PACKER | M39: =VLOOKUP(B39,Sheet21!A:N,14,0) | N39: PRODUKSI | O39: Packer | P39: HARIAN | Q39: JL HARAPAN INDAH TANAH APIT, RT/RW : 003/009, KEL : MEDAN SATRIA, KEC : MEDAN SATIRA KOTA BEKASI | R39: 3 | S39: 9 | U39: MEDAN SATRIA | V39: MEDAN SATRIA | W39: KOTA BEKASI | X39: JL HARAPAN INDAH TANAH APIT, RT/RW : 003/009, KEL : MEDAN SATRIA, KEC : MEDAN SATIRA | Y39: 895332517291 | Z39: ISLAM | AA39: SMK | AC39: 37 | AD39: 328000054 | AE39: CHIKA PITALOKA | AF39: PRODUCTION | AG39: 23165960990 | AH39: 509762092
A40: =A39+1 | B40: 328000063 | C40: 3214122707030001 | D40: RIZKI AGUNG | E40: PURWAKARTA | F40: SMK 1 PWK | H40: SMKN 1 PURWAKARTA | I40: 37829 | J40: =DATEDIF(I40, TODAY(), "Y") & " tahun, " & DATEDIF(I40, TODAY(), "YM") & " bulan, " & DATEDIF(I40, TODAY(), "MD") & " hari" | K40: L | L40: PACKER | M40: =VLOOKUP(B40,Sheet21!A:N,14,0) | N40: PRODUKSI | O40: Packer | P40: HARIAN | Q40: KP. KRAJAN, RT/RW: 002/001, KEL: BABAKANCIKAO, KEC: BABAKANCIKAO, KAB: PURWAKARTA | R40: 2 | S40: 1 | T40: 41151 | U40: BABAKANCIKAO | V40: BABAKANCIKAO | W40: PURWAKARTA | X40: KP. KRAJAN, RT/RW: 002/001, KEL: BABAKANCIKAO, KEC: BABAKANCIKAO, KAB: PURWAKARTA | Y40: 087731075298/083123448763 | Z40: ISLAM | AA40: SMK | AC40: 38 | AD40: 328000063 | AE40: RIZKI AGUNG | AF40: PRODUCTION | AG40: 23165961121 | AH40: 1185075988
A41: =A40+1 | B41: 328000066 | C41: 3214124509040004 | D41: NADILA NAZIWA SOPIAN | E41: PURWAKARTA | F41: SMK 1 PWK | H41: SMKN 1 PURWAKARTA | I41: 38235 | J41: =DATEDIF(I41, TODAY(), "Y") & " tahun, " & DATEDIF(I41, TODAY(), "YM") & " bulan, " & DATEDIF(I41, TODAY(), "MD") & " hari" | K41: P | L41: QC LAB | M41: =VLOOKUP(B41,Sheet21!A:N,14,0) | N41: QC | O41: QC Lab | P41: HARIAN | Q41: KP. HEGARMANAH, RT/RW: 011/004, KEL :HEGARMANAH KEC: BABAKANCIKAO KAB: PURWAKARTA | R41: 11 | S41: 4 | T41: 41151 | U41: BABAKANCIKAO | V41: HEGARMANAH | W41: PURWAKARTA | X41: KP. HEGARMANAH, RT/RW. 011/004, KEL. HEGARMANAH, KEC. BABAKANCIKAO, KAB. PURWAKARTA | Y41: 83834909006 | Z41: ISLAM | AA41: SMK | AC41: 39 | AD41: 328000066 | AE41: NADILA NAZIWA SOPIAN | AF41: QUALITY AND RESEARCH & DEVELOPMENT | AG41: 23165961014 | AH41: 2961701504
A42: =A41+1 | B42: 328000067 | C42: 3214012210030013 | D42: ALIP RANGGA ALPAJRIN | E42: PURWAKARTA | F42: TKD | G42: Ormas Lodaya | H42: KETUA ORMAS LODAYA PAK LILI | I42: 37916 | J42: =DATEDIF(I42, TODAY(), "Y") & " tahun, " & DATEDIF(I42, TODAY(), "YM") & " bulan, " & DATEDIF(I42, TODAY(), "MD") & " hari" | K42: L | L42: ADMIN TSP | M42: =VLOOKUP(B42,Sheet21!A:N,14,0) | N42: PRODUKSI | O42: Admin TSP | P42: Kontrak | Q42: KP. KARANG SARI, RT/RW: 007/002, KEL:CITALANG KEC:PURWAKARTA, KAB: PURWAKARTA | R42: 7 | S42: 2 | T42: 41151 | U42: PURWAKARTA | V42: CITALANG | W42: PURWAKARTA | X42: KP. KARANG SARI, RT/RW: 007/002, KEL:CITALANG KEC:PURWAKARTA, KAB: PURWAKARTA | Y42: 81384243923 | Z42: ISLAM | AA42: SMK | AC42: 40 | AD42: 328000067 | AE42: ALIP RANGGA ALPAJRIN | AF42: PRODUCTION | AG42: 23165961188 | AH42: 1432639596
A43: =A42+1 | B43: 328000068 | C43: 3603284904040005 | D43: NADINE RIEZKI GHEFIRA | E43: KARAWANG | F43: LINK | H43: PT KMJ | I43: 38086 | J43: =DATEDIF(I43, TODAY(), "Y") & " tahun, " & DATEDIF(I43, TODAY(), "YM") & " bulan, " & DATEDIF(I43, TODAY(), "MD") & " hari" | K43: P | L43: QC LAB | M43: =VLOOKUP(B43,Sheet21!A:N,14,0) | N43: QC | O43: QC Lab | P43: HARIAN | Q43: KP. KEMBANGKUNING GG. ABAH SALIM NO. 28 RT/RW: 001/004, KEL: KEMBANGKUNING, KEC: JATILUHUR, KAB : PURWAKARTA | R43: 1 | S43: 4 | T43: 41111 | U43: JATILUHUR | V43: KEMBANGKUNING | W43: PURWAKARTA | X43: KP. KEMBANGKUNING GG. ABAH SALIN NO.28 RT/RW. 001/004, KEL. KEMBANGKUNING, KEC. JATILUHUR, KAB. PURWAKARTA | Y43: 82111185503 | Z43: ISLAM | AA43: SMK | AC43: 41 | AD43: 328000068 | AE43: NADINE RIEZKI GHEFIRA | AF43: QUALITY AND RESEARCH & DEVELOPMENT | AG43: 23165960842 | AH43: 2284272077
A44: =A43+1 | B44: 328000070 | C44: 3175062204970002 | D44: BAYU AJIE PANGESTU | E44: JAKARTA | F44: LINK | H44: Ex AMG | I44: 35542 | J44: =DATEDIF(I44, TODAY(), "Y") & " tahun, " & DATEDIF(I44, TODAY(), "YM") & " bulan, " & DATEDIF(I44, TODAY(), "MD") & " hari" | K44: L | L44: QUALITY PATROL | M44: =VLOOKUP(B44,Sheet21!A:N,14,0) | N44: QC | O44: QC Patrol | P44: HARIAN | Q44: JL.CEMPAKA VI, RT/RW: 009/009, KEL: CAKUNG TIMUR, KEC: CAKUNG, KOTA: JAKARTA TIMUR | R44: 9 | S44: 9 | U44: CAKUNG | V44: CAKUNG TIMUR | W44: KOTA JAKARTA TIMUR | X44: JL.CEMPAKA VI, RT/RW: 009/009, KEL: CAKUNG TIMUR, KEC: CAKUNG, KOTA: JAKARTA TIMUR | Y44: 81311382462 | Z44: ISLAM | AA44: SMA | AC44: 42 | AD44: 328000070 | AE44: BAYU AJIE PANGESTU | AF44: QUALITY AND RESEARCH & DEVELOPMENT | AG44: 23165960735 | AH44: 1157293787
A45: =A44+1 | B45: 328000072 | C45: 3204066906010005 | D45: ANISA FITALOKA | E45: BANDUNG | F45: TKD | G45: Ormas Lodaya | H45: ANAK KETUA ORMAS LODAYA PAK LILI | I45: 37071 | J45: =DATEDIF(I45, TODAY(), "Y") & " tahun, " & DATEDIF(I45, TODAY(), "YM") & " bulan, " & DATEDIF(I45, TODAY(), "MD") & " hari" | K45: P | L45: ADMIN RF | M45: =VLOOKUP(B45,Sheet21!A:N,14,0) | N45: PRODUKSI | O45: Admin RF | P45: HARIAN | Q45: AWILIGAR, RT/RW: 007/010, KEL: CIBEUNYING, KEC: CIMENYAN, KAB: PURWAKARTA | R45: 7 | S45: 10 | U45: CIMENYAN | V45: CIBEUNYING | W45: BANDUNG | X45: AWILIGAR, RT/RW: 007/010, KEL: CIBEUNYING, KEC: CIMENYAN, KAB: PURWAKARTA | Y45: 83121450691 | Z45: ISLAM | AA45: SMA | AC45: 43 | AD45: 328000072 | AE45: ANISA FITALOKA | AF45: PRODUCTION | AG45: 23165960537 | AH45: 3221828021
A46: =A45+1 | B46: 328000078 | C46: 3175065805990011 | D46: KRISNA AIDA | E46: WONOGIRI | F46: LINK | H46: Ex AMG | I46: 36298 | J46: =DATEDIF(I46, TODAY(), "Y") & " tahun, " & DATEDIF(I46, TODAY(), "YM") & " bulan, " & DATEDIF(I46, TODAY(), "MD") & " hari" | K46: P | L46: PACKER | M46: =VLOOKUP(B46,Sheet21!A:N,14,0) | N46: PRODUKSI | O46: Packer | P46: HARIAN | Q46: KP. BARU, RT/RW : 001/007, KEL : CAKUNG BARAT, KEC : CAKUNG, KOTA: JAKARTA TIMUR | R46: 1 | S46: 7 | U46: CAKUNG | V46: CAKUNG BARAT | W46: JAKARTA TIMUR | X46: KP. BARU, RT/RW : 001/007, KEL : CAKUNG BARAT, KEC : CAKUNG, KOTA: JAKARTA TIMUR | Y46: 81584994348 | Z46: ISLAM | AA46: SMK | AC46: 44 | AD46: 328000078 | AE46: KRISNA AIDA | AF46: PRODUCTION | AG46: 23165961196 | AH46: 1739134113
A47: =A46+1 | B47: 328000080 | C47: 3206180805980001 | D47: ILHAM PAOJI MUHAROM | E47: TASIK MALAYA | F47: LINK | H47: PT KMJ | I47: 35923 | J47: =DATEDIF(I47, TODAY(), "Y") & " tahun, " & DATEDIF(I47, TODAY(), "YM") & " bulan, " & DATEDIF(I47, TODAY(), "MD") & " hari" | K47: L | L47: OP FORKLIFT WRM | M47: =VLOOKUP(B47,Sheet21!A:N,14,0) | N47: LOGISTIK | O47: Operator Forklift | P47: HARIAN | Q47: DUSUN BOJONGRAPIH, RT/RW 001/005 KEL: MANDALAHAYU, KECAMATAN: SALOPA KAB: TASIKMALAYA | R47: 1 | S47: 5 | U47: SALOPA | V47: MANDALAYU | W47: TASIKMALAYA | X47: DUSUN BOJONGRAPIH, RT/RW 001/005 KEL: MANDALAHAYU, KECAMATAN: SALOPA KAB: TASIKMALAYA | Y47: 83816957498 | Z47: ISLAM | AA47: SMK | AC47: 45 | AD47: 328000080 | AE47: ILHAM PAOJI MUHAROM | AF47: LOGISTIC | AG47: 23165961055 | AH47: 3091176843
A48: =A47+1 | B48: 328000081 | C48: 3214122001990001 | D48: M QORI ALMAHMUD | E48: PURWAKARTA | F48: SMK 1 PWK | H48: SMKN 1 PURWAKARTA | I48: 36180 | J48: =DATEDIF(I48, TODAY(), "Y") & " tahun, " & DATEDIF(I48, TODAY(), "YM") & " bulan, " & DATEDIF(I48, TODAY(), "MD") & " hari" | K48: L | L48: ADMIN WSP | M48: =VLOOKUP(B48,Sheet21!A:N,14,0) | N48: ENG | O48: Admin WSP | P48: HARIAN | Q48: KP KRAJAN, RT/RW: 008/002 KEL: MARACANG, KEC:BABAKANCIKAO PURWAKARTA | R48: 8 | S48: 2 | U48: BABAKANCIKAO | V48: MARACANG | W48: PURWAKARTA | X48: KP KRAJAN, RT/RW: 008/002 KEL: MARACANG, KEC:BABAKANCIKAO PURWAKARTA | Y48: 87847442700 | Z48: ISLAM | AA48: SMK | AC48: 46 | AD48: 328000081 | AE48: M QORI ALMAHMUD | AF48: LOGISTIC | AG48: 23165961063 | AH48: 1659885355
A49: =A48+1 | B49: 328000083 | C49: 3214120101040001 | D49: ALDI SUTRISNA | E49: PURWAKARTA | F49: SMK 1 PWK | H49: SMKN 1 PURWAKARTA | I49: 37987 | J49: =DATEDIF(I49, TODAY(), "Y") & " tahun, " & DATEDIF(I49, TODAY(), "YM") & " bulan, " & DATEDIF(I49, TODAY(), "MD") & " hari" | K49: L | L49: PACKER | M49: =VLOOKUP(B49,Sheet21!A:N,14,0) | N49: PRODUKSI | O49: Packer | P49: HARIAN | Q49: KP.KRAJAN RT/RW: 003/002, KEL: BABAKANCIKAO, KEC: BABAKANCIKAO, KAB: PURWAKARTA | R49: 3 | S49: 2 | U49: BABAKANCIKAO | V49: BABAKANCIKAO | W49: PURWAKARTA | X49: KP.KRAJAN RT/RW: 003/002, KEL: BABAKANCIKAO, KEC: BABAKANCIKAO, KAB: PURWAKARTA | Y49: 83140939049 | Z49: ISLAM | AA49: SMK | AC49: 47 | AD49: 328000083 | AE49: ALDI SUTRISNA | AF49: PRODUCTION | AG49: 23165960776 | AH49: 1882085027
A50: =A49+1 | B50: 328000086 | C50: 3214122609040002 | D50: ARIA PERMANA ZIDANE | E50: PURWAKARTA | F50: LINK | H50: PT KMJ | I50: 38256 | J50: =DATEDIF(I50, TODAY(), "Y") & " tahun, " & DATEDIF(I50, TODAY(), "YM") & " bulan, " & DATEDIF(I50, TODAY(), "MD") & " hari" | K50: L | L50: PIC AREA | M50: =VLOOKUP(B50,Sheet21!A:N,14,0) | N50: LOGISTIK | O50: PIC Area | P50: HARIAN | Q50: KP. WARUNG BUAH, RT/RW 004/002, KEL: HEGARMANAH, KEC: BABAKANCIKAO, KAB: PURWAKARTA | R50: 4 | S50: 2 | U50: BABAKANCIKAO | V50: HEGARMANAH | W50: PURWAKARTA | X50: KP. WARUNG BUAH, RT/RW 004/002, KEL: HEGARMANAH, KEC: BABAKANCIKAO, KAB: PURWAKARTA | Y50: 83130583749 | Z50: ISLAM | AA50: SMA | AC50: 48 | AD50: 328000086 | AE50: ARIA PERMANA ZIDANE | AF50: LOGISTIC | AG50: 23165961030 | AH50: 1661915169
A51: =A50+1 | B51: 328000088 | C51: 3214014505030002 | D51: MEISY TRESA HANDAYANI | E51: PURWAKARTA | F51: TKD | H51: SAEPUL KONPAK | I51: 37744 | J51: =DATEDIF(I51, TODAY(), "Y") & " tahun, " & DATEDIF(I51, TODAY(), "YM") & " bulan, " & DATEDIF(I51, TODAY(), "MD") & " hari" | K51: P | L51: ADMIN RF | M51: =VLOOKUP(B51,Sheet21!A:N,14,0) | N51: PRODUKSI | O51: Admin RF | P51: HARIAN | Q51: KP BOJONG, RT/RW:012/005, KEL: NAGRIKIDUL, KEC: PURWAKARTA, KAB: PURWAKARTA | R51: 12 | S51: 5 | U51: PURWAKARTA | V51: NAGRIKIDUL | W51: PURWAKARTA | X51: KP BOJONG, RT/RW:012/005, KEL: NAGRIKIDUL, KEC: PURWAKARTA, KAB: PURWAKARTA | Y51: 89507007257 | Z51: ISLAM | AA51: SMK | AC51: 49 | AD51: 328000088 | AE51: MEISY TRESA HANDAYANI | AF51: PRODUCTION | AG51: 23165961212 | AH51: 1517143364
A52: =A51+1 | B52: 328000090 | C52: 3275024602980026 | D52: MELIANA FITRI | E52: TEGAL | F52: LINK | H52: Ex AMG | I52: 35832 | J52: =DATEDIF(I52, TODAY(), "Y") & " tahun, " & DATEDIF(I52, TODAY(), "YM") & " bulan, " & DATEDIF(I52, TODAY(), "MD") & " hari" | K52: P | L52: QUALITY PATROL | M52: =VLOOKUP(B52,Sheet21!A:N,14,0) | N52: QC | O52: QC Patrol | P52: HARIAN | Q52: JL. TAHIR NO.14, RT/RW: 002/011, KEL: KRANJI, KEC: BEKASI BARAT, KOTA: BEKASI | R52: 2 | S52: 11 | U52: BEKASI BARAT | V52: KRANJI | W52: KOTA BEKASI | X52: JL. TAHIR NO.14, RT/RW: 002/011, KEL: KRANJI, KEC: BEKASI BARAT, KOTA: BEKASI | Y52: 89693347398 | Z52: ISLAM | AA52: SMK | AC52: 50 | AD52: 328000090 | AE52: MELIANA FITRI | AF52: QUALITY AND RESEARCH & DEVELOPMENT | AG52: 23165961048 | AH52: 628978858
A53: =A52+1 | B53: 328000095 | C53: 3214121808990004 | D53: AGUS JONI | E53: PURWAKARTA | F53: SMK 1 PWK | H53: SMKN 1 PURWAKARTA | I53: 36390 | J53: =DATEDIF(I53, TODAY(), "Y") & " tahun, " & DATEDIF(I53, TODAY(), "YM") & " bulan, " & DATEDIF(I53, TODAY(), "MD") & " hari" | K53: L | L53: PACKER | M53: =VLOOKUP(B53,Sheet21!A:N,14,0) | N53: PRODUKSI | O53: Operator Produksi | P53: HARIAN | Q53: KP. WARUNG BUAH, RT/RW 005/006, KEL: HEGARMANAH, KEC: BABAKANCIKAO, KAB: PURWAKARTA | R53: 5 | S53: 6 | U53: BABAKANCIKAO | V53: HEGARMANAH | W53: PURWAKARTA | X53: KP. WARUNG BUAH, RT/RW 005/006, KEL: HEGARMANAH, KEC: BABAKANCIKAO, KAB: PURWAKARTA | Y53: 85798800713 | Z53: ISLAM | AA53: SMK | AC53: 51 | AD53: 328000095 | AE53: AGUS JONI | AF53: PRODUCTION | AG53: 23165960958 | AH53: 2394494133
A54: =A53+1 | B54: 328000097 | C54: 3215061610000003 | D54: YOGI RUDIYANTO | E54: KARAWANG | F54: LINK | H54: PT KMJ | I54: 36815 | J54: =DATEDIF(I54, TODAY(), "Y") & " tahun, " & DATEDIF(I54, TODAY(), "YM") & " bulan, " & DATEDIF(I54, TODAY(), "MD") & " hari" | K54: L | L54: ADMIN WRM | M54: =VLOOKUP(B54,Sheet21!A:N,14,0) | N54: LOGISTIK | O54: Admin WRM | P54: HARIAN | Q54: DUSUN JATI, RT/RW: 009/006, KEL: RENGASDENGKLOK UTARA, KEC: RENGASDENGKLOK, KAB: KARAWANG | R54: 9 | S54: 6 | U54: RENGASDENGKLOK | V54: RENGAS DENGKLOK UTARA | W54: KARAWANG | X54: DUSUN JATI, RT/RW: 009/006, KEL: RENGASDENGKLOK UTARA, KEC: RENGASDENGKLOK, KAB: KARAWANG | Y54: 89510257342 | Z54: ISLAM | AA54: SMK | AC54: 52 | AD54: 328000097 | AE54: YOGI RUDIYANTO | AF54: LOGISTIC | AG54: 23165960586 | AH54: 2394895689
A55: =A54+1 | B55: 328000100 | C55: 3214131502010002 | D55: FIKRIE ABI HASAN | E55: PURWAKARTA | F55: LINK | H55: PT KMJ | I55: 37051 | J55: =DATEDIF(I55, TODAY(), "Y") & " tahun, " & DATEDIF(I55, TODAY(), "YM") & " bulan, " & DATEDIF(I55, TODAY(), "MD") & " hari" | K55: L | L55: ADMIN WSP | M55: =VLOOKUP(B55,Sheet21!A:N,14,0) | N55: ENG | O55: Admin WSP | P55: HARIAN | Q55: KP BUNDER, RT/RW: 0021/007, KEL: CIBENING, KEC: BUNGURSARI, KAB: PURWAKARTA | R55: 21 | S55: 7 | U55: BUNGURSARI | V55: CIBENING | W55: PURWAKARTA | X55: KP BUNDER, RT/RW: 0021/007, KEL: CIBENING, KEC: BUNGURSARI, KAB: PURWAKARTA | Y55: 83827160685 | Z55: ISLAM | AA55: SMK | AC55: 53 | AD55: 328000100 | AE55: FIKRIE ABI HASAN | AF55: LOGISTIC | AG55: 23165960792 | AH55: 63379541
A56: =A55+1 | B56: 328000104 | C56: 3214124104050001 | D56: TASYA APRIANI | E56: PURWAKARTA | F56: TKD | G56: Pak Wahyudin | H56: ANAKNYA SUPIR PAK WAHYUDIN | I56: 38443 | J56: =DATEDIF(I56, TODAY(), "Y") & " tahun, " & DATEDIF(I56, TODAY(), "YM") & " bulan, " & DATEDIF(I56, TODAY(), "MD") & " hari" | K56: P | L56: PACKER | M56: =VLOOKUP(B56,Sheet21!A:N,14,0) | N56: PRODUKSI | O56: Packer | P56: HARIAN | Q56: KP.MULYASARI, RT/RW 004/003, DES: CIWARENG, KEC: BABAKANCIKAO KAB: PURWAKARTA | R56: 4 | S56: 3 | T56: 41151 | U56: BABAKANCIKAO | V56: CIWARENG | W56: PURWAKARTA | X56: KP.MULYASARI, RT/RW 004/003, DES: CIWARENG, KEC: BABAKANCIKAO KAB: PURWAKARTA | Y56: 89665347150 | Z56: ISLAM | AA56: SMK | AC56: 54 | AD56: 328000104 | AE56: TASYA APRIANI | AF56: PRODUCTION | AG56: 23165960750 | AH56: 2394925143
